Workbook
Name Budgeted_year: '[1]Setup Fields'!$B$1
Name Currency: '[1]Setup Fields'!$H$30
Name CurrencyChoice: '[1]Setup Fields'!$F$30
Name data_type: '[1]Setup Fields'!$A$67:$A$71
Name data_type_Short: '[1]Setup Fields'!$B$67:$B$71
Name Dept_Table: '[1]Dept Settings'!$A$2:$K$261
Name FTEHours: '[1]Setup Fields'!$B$10
Name Hotel_Name: '[1]Setup Fields'!$B$3
Name InflationRate: '[1]Setup Fields'!$B$11
Name PSF_FixedCost: '[1]Setup Fields'!$A$162
Name PSF_PercentageGRR: '[1]Setup Fields'!$A$163
Name PSF_PerKey: '[1]Setup Fields'!$A$164
Name WageIncrease: '[1]Setup Fields'!$B$13

Sheet Cover
D28: The foregoing information is based upon a variety of assumptions and estimates.
D29: There can be no assurance that the projections stated will be realized. Actual results may vary significantly from those shown.

Sheet Pricing Structure Description
D2: Product Item | E2: Spark | F2: Spark + | G2: Blaze | H2: Internal Notes | I2: Availability
D3: Description | E3: Small operations, such as start ups, single tenant | F3: Small operations that need a bit more configuration to drive usage, Single Tenant | G3: Core offering, Tentant, and Sub-tenant | H3: Enterprise, Organization, Department
B4: Reoccuring | C4: Base | D4: Licensing | E4: User | F4: User | G4: Site + 2 Users | H4: Site + Users
D5: Reoccurring fee
C6: Support | D6: Support | E6: E-mail, Chat | F6: E-mail, Chat | G6: Call, E-mail, Chat
D7: Support Guidelines | E7: E-mail 8:00 am ET - 8:00 pm ET, Chat: 8:00am ET- 8 pm ET | F7: E-mail 8:00 am ET - 8:00 pm ET, Chat: 8:00am ET- 8 pm ET | G7: E-mail 8:00 am ET - 8:00 pm ET, Chat: 24 hr., Call: Customer Success 8:00 ET - 8:00 pm ET
D8: Support Fee | E8: 50 | G8: 100
B9: One Time | C9: Configuration | D9: Configuration | E9: Limited Functionality, Templatized | F9: Limited, Functionality, templatized by industry, small configuration to enable user experience | G9: Full Functionality, configured for the organization
D10: Configuration Guidelines | G10: First four hours included in fee, additional fees- One Time Fee
D11: Configuration Fee | E11: N/A | F11: $250 hourly rate | G11: $250 hourly rate
C12: On-boarding | D12: Onboarding- User Training | E12: User Experience | F12: Wizardry, with the ability to purchase hours- E-training | G12: Up to 10 ppl per session, Two 1-hour sessions- E-training
D13: Onboarding- User Training Fee | E13: N/A | F13: $200 per hour | G13: $600 per session
D14: Onboarding- Administrator | E14: Templatized | F14: wizardry, with the ability to purchase hours | G14: On-boarding training of Administrators, up to 3 administrators, Three 1-hour sessions
D15: Onboarding- Administrator Fee | E15: N/A | F15: $200 per hour | G15: $600 per session
C16: Import | D16: Import | E16: spreadsheet mapping | F16: API- Configuration tool (ETL)- DOMO | G16: API- We Build, $100 per hour
D17: Import Fee | E17: N/A | G17: $150 per hour
D19: Thought Leadership Library | H19: Access to thought library content per license
D20: Consultancy | H20: Four hour session, that can be allocated at user's discretion.
D22: Ignite Talent

Sheet Pricing Calcuator
C3: Pricing Matrix
C6: Type of User | D6: License | E6: User
C7: Hospitality | D7: 250
C8: Hospitality Reseller | D8: 100
C9: Real Estate | D9: 400
C10: Real Estate Reseller | D10: 250
C11: Pharma | D11: 400
C12: Pharma- Reseller | D12: 250
C13: Small Start ups | D13: 150
C14: Small Start ups Reseller | D14: 75
C16: Pricing Calculator
C17: Rate Sheet
E18: Subscription | G18: One-Time Cost | I18: Description
C20: =C6 | D20: Hospitality | E20: =IF(D20="","",IF(D20=$C$7,$D$7,IF(D20=$C$8,D8,IF(D20=$C$9,D9,IF(D20=$C$11,D11,IF(D20=$C$12,D12,IF(D20=$C$10,D10,IF(D20=$C$13,D13,IF(D20=$C$14,D14)))))))))
C22: Number of
C23: Sites | D23: 5 | E23: =E20*D23 | I23: With each site license you will receive 2 users
C24: Additional User | D24: 10 | E24: =(E23*D24)*0.5 | I24: Additional User licenses over an above the 2 per site, 50% discount for additional users
C26: =C68 | D26: Support Blaze | E26: =IF(D26="","",IF(D26=C69,D69,IF(D26=C70,D70))) | I26: =IF(D26="","",IF(D26=C69,'Pricing Structure Description'!F7,IF('Pricing Calcuator'!D26='Pricing Calcuator'!C70,'Pricing Structure Description'!G7)))
C28: Number of Months | E28: 12
C30: One- Time Fees
C31: =C73 | D31: Blaze | G31: =IF(D31="","",IF(D31=$C$74,D74,IF(D31=$C$75,D75)))*D32 | I31: =IF(D31="","",IF(D31=C74,'Pricing Structure Description'!F9,IF('Pricing Calcuator'!D31='Pricing Calcuator'!C75,'Pricing Structure Description'!G9)))
C32: Number of hours | D32: 10
C33: Importing | D33: Blaze | G33: =D86*D23 | I33: =IF(D6="","",IF(D33=C75,'Pricing Structure Description'!G16,IF('Pricing Calcuator'!D33='Pricing Calcuator'!C74,'Pricing Structure Description'!F16)))
C36: =C77
C37: Administrator Training | D37: Yes | F37: =IF(D37="","",IF(D37=C79,D79,IF(D37=C80,D80))) | G37: =F37*D38 | I37: ='Pricing Structure Description'!G14
C38: If yes, number of Administrators | D38: 3
C40: User Training | D40: Yes | F40: =IF(D40="","",IF(D40=C82,D82,IF(D40=C83,D83))) | G40: =D41*F40 | I40: ='Pricing Structure Description'!G12
C41: If yes, number of sessions | D41: 5
C43: =C88 | E43: =IF(D44="","",IF(D44=C90,D90,IF(D44=C91,D91)))
C44: =C89 | D44: Yes | E44: =E43*D23 | I44: =IF(D44="","",IF(D44=C90,'Pricing Structure Description'!G11,IF('Pricing Calcuator'!D44='Pricing Calcuator'!C91,'Pricing Structure Description'!H19)))
C46: Consultancy Services | D46: Yes | G46: =IF(D46="","",IF(D46=C93,D93,IF(D46=C94,D94))) | I46: =IF(D46="","",IF(D46=C93,'Pricing Structure Description'!G12,IF('Pricing Calcuator'!D46='Pricing Calcuator'!C94,'Pricing Structure Description'!H22)))
E49: =((E23+E24+E26)*E28)+E44 | G49: =SUM(G20:G48)
C51: First Year | E51: =E49+G49
C53: =C84 | D53: Yes | E53: =E49*0.2
C54: Year Commitment | D54: 2 | E54: =IF(D54>1,((E49*D54)-E53),IF(D54<1,0)) | I54: Multi-Year with Discount of 20% per year
C56: Total Investment | E56: =E54+G49
C61: Outline of Service
C62: Service | D62: Pricing | E62: Offering | F62: Description
C63: Reoccuring
C64: Site / User
C65: Site
C66: User
C68: Tech Support
C69: Support Spark | D69: 50 | E69: ='Pricing Structure Description'!F6
C70: Support Blaze | D70: 100 | E70: ='Pricing Structure Description'!F7
C72: One Time
C73: Configuration
C74: Spark | D74: 100
C75: Blaze | D75: 250
C77: On-Boarding
C78: admin training
C79: Yes | D79: 600 | E79: per session
C80: No | D80: 0
C81: user training
C82: Yes | D82: 600 | E82: per session
C83: No | D83: 0
C84: Multi-Year | D84: Yes
D85: No
C86: Import | D86: 700
C88: Thought Leadership
C89: Thought Library
C90: Yes | D90: 50
C91: No | D91: 0
C92: Consultancy as a Service
C93: Yes | D93: 250
C94: No | D94: 0

Sheet Revenue 2025
C3: 2025 | D3: Pricing
C4: Offerings and Distribution | D4: Price | E4: COGS | F4: Margin Per Subscription
C5: Administrative | H5: Growth Model
C6: Configuration | D6: 250 | E6: 50 | F6: =D6-E6
C7: On-Boarding- Administrator | D7: 500 | E7: 100 | F7: =D7-E7
C8: On-Boarding Users | D8: 500 | E8: 100 | F8: =D8-E8
C9: Import | D9: ='Pricing Calcuator'!D86 | E9: 600 | F9: =D9-E9
C10: Support | D10: 100 | E10: 50 | F10: =D10-E10
C11: Industry Break Down | E11: ='COGS Analysis'!D18
C12: Hospitality | D12: 250 | E12: ='Revenue 2030'!$Q$210 | F12: =D12-E12
C13: Hospitality- Reseller | D13: 100 | E13: ='Revenue 2030'!$Q$210 | F13: =D13-E13
C14: Real Estate Development | D14: 400 | E14: ='Revenue 2030'!$Q$210 | F14: =D14-E14
C15: Real Estate Development- Reseller | D15: 250 | E15: ='Revenue 2030'!$Q$210 | F15: =D15-E15
C16: Pharma | D16: 400 | E16: ='Revenue 2030'!$Q$210 | F16: =D16-E16
C17: Pharma- Reseller | D17: 250 | E17: ='Revenue 2030'!$Q$210 | F17: =D17-E17
C18: Start up - Small Firms | D18: 200 | E18: ='Revenue 2030'!$Q$210 | F18: =D18-E18
C19: Start up Reseller | D19: 100 | E19: ='Revenue 2030'!$Q$210 | F19: =D19-E19
C20: Training / Consultancy Training as a Service
C21: Thought Library | D21: 50 | E21: 25 | F21: =D21-E21
C22: Consultancy Services | D22: 225 | E22: 125 | F22: =D22-E22
C24: Segments | D24: January | E24: February | F24: March | G24: April | H24: May | I24: June | J24: July | K24: August | L24: September | M24: October | N24: November | O24: December | P24: Annual Totals | Q24: Profit Margin | R24: Profit margin comparison | S24: CHURN
B26: Hospitality | C26: =C12 | T26: Assumptions
C27: Licences Sold | D27: 120 | E27: 120 | F27: 150 | G27: 150 | H27: 160 | I27: 175 | J27: 250 | K27: 300 | L27: 325 | M27: 325 | N27: 325 | O27: 325 | P27: =O27 | S27: 0.03
D28: =D27*$S$27 | E28: =E27*$S$27 | F28: =F27*$S$27 | G28: =G27*$S$27 | H28: =H27*$S$27 | I28: =I27*$S$27 | J28: =J27*$S$27 | K28: =K27*$S$27 | ... O28: =O27*$S$27
C29: Total Sales | D29: =(D27-D28)*$D$12 | E29: =E27*$D$12 | F29: =F27*$D$12 | G29: =G27*$D$12 | H29: =H27*$D$12 | I29: =I27*$D$12 | J29: =J27*$D$12 | K29: =K27*$D$12 | L29: =L27*$D$12 | ... O29: =O27*$D$12 | P29: =SUM(D29:O29) | Q29: =(Q30+Q31) | T29: t Growing first within the hotel B2B market and looking for strategic partners and resellers, i.e. BI
C30: Total COGS | D30: =D27*$E$12 | E30: =E27*$E$12 | F30: =F27*$E$12 | G30: =G27*$E$12 | H30: =H27*$E$12 | I30: =I27*$E$12 | J30: =J27*$E$12 | K30: =K27*$E$12 | ... O30: =O27*$E$12 | P30: =SUM(D30:O30) | Q30: =IF(P29=0,0,P30/P29)
C31: Total Margin | D31: =D29-D30 | E31: =E29-E30 | F31: =F29-F30 | G31: =G29-G30 | H31: =H29-H30 | I31: =I29-I30 | J31: =J29-J30 | K31: =K29-K30 | ... O31: =O29-O30 | P31: =SUM(D31:O31) | Q31: =IF(P29=0,0,P31/P29)
T32: t The growth coming from Strategic Partners
C33: =C13
C34: Licences Sold | D34: 0 | E34: 0 | F34: 0 | G34: 0 | H34: 0 | I34: 0 | J34: 0 | K34: 0 | L34: 0 | M34: 0 | N34: 0 | O34: 0 | P34: =O34 | T34: t Sales coming from current team
C35: Total Sales | D35: =D34*$D$13 | E35: =E34*$D$13 | F35: =F34*$D$13 | G35: =G34*$D$13 | H35: =H34*$D$13 | I35: =I34*$D$13 | J35: =J34*$D$13 | K35: =K34*$D$13 | ... O35: =O34*$D$13 | P35: =SUM(D35:O35) | Q35: =(Q36+Q37)
C36: Total COGS | D36: =D34*$E$13 | E36: =E34*$E$13 | F36: =F34*$E$13 | G36: =G34*$E$13 | H36: =H34*$E$13 | I36: =I34*$E$13 | J36: =J34*$E$13 | K36: =K34*$E$13 | ... O36: =O34*$E$13 | P36: =SUM(D36:O36) | Q36: =IF(P35=0,0,P36/P35)
C37: Total Margin | D37: =D35-D36 | E37: =E35-E36 | F37: =F35-F36 | G37: =G35-G36 | H37: =H35-H36 | I37: =I35-I36 | J37: =J35-J36 | K37: =K35-K36 | ... O37: =O35-O36 | P37: =SUM(D37:O37) | Q37: =IF(P35=0,0,P37/P35)
B39: Real Estate | C39: =C14
C40: Licences Sold | D40: 50 | E40: 50 | F40: 50 | G40: 50 | H40: 50 | I40: 175 | J40: 175 | K40: 180 | L40: 180 | M40: 200 | N40: 200 | O40: 230 | P40: =O40
C41: Total Sales | D41: =D40*$D$14 | E41: =E40*$D$14 | F41: =F40*$D$14 | G41: =G40*$D$14 | H41: =H40*$D$14 | I41: =I40*$D$14 | J41: =J40*$D$14 | K41: =K40*$D$14 | ... O41: =O40*$D$14 | P41: =SUM(D41:O41) | Q41: =(Q42+Q43)
C42: Total COGS | D42: =D40*$E$14 | E42: =E40*$E$14 | F42: =F40*$E$14 | G42: =G40*$E$14 | H42: =H40*$E$14 | I42: =I40*$E$14 | J42: =J40*$E$14 | K42: =K40*$E$14 | ... O42: =O40*$E$14 | P42: =SUM(D42:O42) | Q42: =IF(P41=0,0,P42/P41)
C43: Total Margin | D43: =D41-D42 | E43: =E41-E42 | F43: =F41-F42 | G43: =G41-G42 | H43: =H41-H42 | I43: =I41-I42 | J43: =J41-J42 | K43: =K41-K42 | ... O43: =O41-O42 | P43: =SUM(D43:O43) | Q43: =IF(P41=0,0,P43/P41)
C45: =C15
C46: Licences Sold | D46: 0 | E46: 0 | F46: 0 | G46: 0 | H46: 0 | I46: 0 | J46: 0 | K46: 0 | L46: 0 | M46: 0 | N46: 0 | O46: 0 | P46: =O46
C47: Total Sales | D47: =D46*$D$15 | E47: =E46*$D$15 | F47: =F46*$D$15 | G47: =G46*$D$15 | H47: =H46*$D$15 | I47: =I46*$D$15 | J47: =J46*$D$15 | K47: =K46*$D$15 | ... O47: =O46*$D$15 | P47: =SUM(D47:O47) | Q47: =(Q48+Q49)
C48: Total COGS | D48: =D46*$E$15 | E48: =E46*$E$15 | F48: =F46*$E$15 | G48: =G46*$E$15 | H48: =H46*$E$15 | I48: =I46*$E$15 | J48: =J46*$E$15 | K48: =K46*$E$15 | ... O48: =O46*$E$15 | P48: =SUM(D48:O48) | Q48: =IF(P47=0,0,P48/P47)
C49: Total Margin | D49: =D47-D48 | E49: =E47-E48 | F49: =F47-F48 | G49: =G47-G48 | H49: =H47-H48 | I49: =I47-I48 | J49: =J47-J48 | K49: =K47-K48 | ... O49: =O47-O48 | P49: =SUM(D49:O49) | Q49: =IF(P47=0,0,P49/P47)
B51: Pharma | C51: =C16
C52: Licences Sold | D52: 0 | E52: 0 | F52: 0 | G52: 0 | H52: 0 | I52: 0 | J52: 0 | K52: 0 | L52: 0 | M52: 0 | N52: 0 | O52: 0 | P52: =O52
C53: Total Sales | D53: =D52*$D$16 | E53: =E52*$D$16 | F53: =F52*$D$16 | G53: =G52*$D$16 | H53: =H52*$D$16 | I53: =I52*$D$16 | J53: =J52*$D$16 | K53: =K52*$D$16 | ... O53: =O52*$D$16 | P53: =SUM(D53:O53) | Q53: =(Q54+Q55)
C54: Total COGS | D54: =D52*$E$16 | E54: =E52*$E$16 | F54: =F52*$E$16 | G54: =G52*$E$16 | H54: =H52*$E$16 | I54: =I52*$E$16 | J54: =J52*$E$16 | K54: =K52*$E$16 | ... O54: =O52*$E$16 | P54: =SUM(D54:O54) | Q54: =IF(P53=0,0,P54/P53)
C55: Total Margin | D55: =D53-D54 | E55: =E53-E54 | F55: =F53-F54 | G55: =G53-G54 | H55: =H53-H54 | I55: =I53-I54 | J55: =J53-J54 | K55: =K53-K54 | ... O55: =O53-O54 | P55: =SUM(D55:O55) | Q55: =IF(P53=0,0,P55/P53)
C57: =C17
C58: Licences Sold | D58: 0 | E58: 0 | F58: 0 | G58: 0 | H58: 0 | I58: 0 | J58: 0 | K58: 0 | L58: 0 | M58: 0 | N58: 0 | O58: 0 | P58: =O58
C59: Total Sales | D59: =D58*$D$17 | E59: =E58*$D$17 | F59: =F58*$D$17 | G59: =G58*$D$17 | H59: =H58*$D$17 | I59: =I58*$D$17 | J59: =J58*$D$17 | K59: =K58*$D$17 | ... O59: =O58*$D$17 | P59: =SUM(D59:O59) | Q59: =(Q60+Q61)
C60: Total COGS | D60: =D58*$E$17 | E60: =E58*$E$17 | F60: =F58*$E$17 | G60: =G58*$E$17 | H60: =H58*$E$17 | I60: =I58*$E$17 | J60: =J58*$E$17 | K60: =K58*$E$17 | ... O60: =O58*$E$17 | P60: =SUM(D60:O60) | Q60: =IF(P59=0,0,P60/P59)
C61: Total Margin | D61: =D59-D60 | E61: =E59-E60 | F61: =F59-F60 | G61: =G59-G60 | H61: =H59-H60 | I61: =I59-I60 | J61: =J59-J60 | K61: =K59-K60 | ... O61: =O59-O60 | P61: =SUM(D61:O61) | Q61: =IF(P59=0,0,P61/P59)
B63: Start ups | C63: =C18
C64: Licences Sold | D64: 40 | E64: 50 | F64: 55 | G64: 55 | H64: 56 | I64: 60 | J64: 60 | K64: 60 | L64: 65 | M64: 70 | N64: 70 | O64: 75 | P64: =O64 | S64: 0.05
D65: =D64*$S$64 | E65: =E64*$S$64 | F65: =F64*$S$64 | G65: =G64*$S$64 | H65: =H64*$S$64 | I65: =I64*$S$64 | J65: =J64*$S$64 | K65: =K64*$S$64 | ... O65: =O64*$S$64
C66: Total Sales | D66: =(D64-D65)*$D$18 | E66: =(E64-E65)*$D$18 | F66: =(F64-F65)*$D$18 | G66: =(G64-G65)*$D$18 | H66: =(H64-H65)*$D$18 | I66: =(I64-I65)*$D$18 | J66: =(J64-J65)*$D$18 | K66: =(K64-K65)*$D$18 | ... O66: =(O64-O65)*$D$18 | P66: =SUM(D66:O66) | Q66: =(Q67+Q68)
C67: Total COGS | D67: =D64*$E$18 | E67: =E64*$E$18 | F67: =F64*$E$18 | G67: =G64*$E$18 | H67: =H64*$E$18 | I67: =I64*$E$18 | J67: =J64*$E$18 | K67: =K64*$E$18 | ... O67: =O64*$E$18 | P67: =SUM(D67:O67) | Q67: =IF(P66=0,0,P67/P66)
C68: Total Margin | D68: =D66-D67 | E68: =E66-E67 | F68: =F66-F67 | G68: =G66-G67 | H68: =H66-H67 | I68: =I66-I67 | J68: =J66-J67 | K68: =K66-K67 | ... O68: =O66-O67 | P68: =SUM(D68:O68) | Q68: =IF(P66=0,0,P68/P66)
C70: =C19
C71: Licences Sold | D71: 0 | E71: 0 | F71: 0 | G71: 0 | H71: 0 | I71: 0 | J71: 0 | K71: 0 | L71: 0 | M71: 0 | N71: 0 | O71: 0 | P71: =O71
C72: Total Sales | D72: =D71*$D$19 | E72: =E71*$D$19 | F72: =F71*$D$19 | G72: =G71*$D$19 | H72: =H71*$D$19 | I72: =I71*$D$19 | J72: =J71*$D$19 | K72: =K71*$D$19 | ... O72: =O71*$D$19 | P72: =SUM(D72:O72) | Q72: =(Q73+Q74)
C73: Total COGS | D73: =D71*$E$19 | E73: =E71*$E$19 | F73: =F71*$E$19 | G73: =G71*$E$19 | H73: =H71*$E$19 | I73: =I71*$E$19 | J73: =J71*$E$19 | K73: =K71*$E$19 | ... O73: =O71*$E$19 | P73: =SUM(D73:O73) | Q73: =IF(P72=0,0,P73/P72)
C74: Total Margin | D74: =D72-D73 | E74: =E72-E73 | F74: =F72-F73 | G74: =G72-G73 | H74: =H72-H73 | I74: =I72-I73 | J74: =J72-J73 | K74: =K72-K73 | ... O74: =O72-O73 | P74: =SUM(D74:O74) | Q74: =IF(P72=0,0,P74/P72)
B77: Consultancy / Training | C77: =C21
C78: Access Sold | F78: 0 | G78: 0 | H78: 0 | I78: 0 | J78: 0 | K78: 0 | L78: 0 | M78: 0 | N78: 0 | O78: 0
C79: Total Sales | D79: =D78*$D$21 | E79: =E78*$D$21 | F79: =F78*$D$21 | G79: =G78*$D$21 | H79: =H78*$D$21 | I79: =I78*$D$21 | J79: =J78*$D$21 | K79: =K78*$D$21 | ... O79: =O78*$D$21 | P79: =SUM(D79:O79) | Q79: =(Q80+Q81)
C80: Total COGS | D80: =D78*$E$21 | E80: =E78*$E$21 | F80: =F78*$E$21 | G80: =G78*$E$21 | H80: =H78*$E$21 | I80: =I78*$E$21 | J80: =J78*$E$21 | K80: =K78*$E$21 | ... O80: =O78*$E$21 | P80: =SUM(D80:O80) | Q80: =IF(P79=0,0,P80/P79)
C81: Total Margin | D81: =D79-D80 | E81: =E79-E80 | F81: =F79-F80 | G81: =G79-G80 | H81: =H79-H80 | I81: =I79-I80 | J81: =J79-J80 | K81: =K79-K80 | ... O81: =O79-O80 | P81: =SUM(D81:O81) | Q81: =IF(P79=0,0,P81/P79)
C83: =C22
C84: Hours Sold | F84: 0 | G84: 0 | H84: 0 | I84: 0 | J84: 0 | K84: 0 | L84: 0 | M84: 0 | N84: 0 | O84: 0
C85: Total Sales | D85: =D84*$D$22 | E85: =E84*$D$22 | F85: =F84*$D$22 | G85: =G84*$D$22 | H85: =H84*$D$22 | I85: =I84*$D$22 | J85: =J84*$D$22 | K85: =K84*$D$22 | ... O85: =O84*$D$22 | P85: =SUM(D85:O85) | Q85: =(Q86+Q87)
C86: Total COGS | D86: =D84*$E$22 | E86: =E84*$E$22 | F86: =F84*$E$22 | G86: =G84*$E$22 | H86: =H84*$E$22 | I86: =I84*$E$22 | J86: =J84*$E$22 | K86: =K84*$E$22 | ... O86: =O84*$E$22 | P86: =SUM(D86:O86) | Q86: =IF(P85=0,0,P86/P85)
C87: Total Margin | D87: =D85-D86 | E87: =E85-E86 | F87: =F85-F86 | G87: =G85-G86 | H87: =H85-H86 | I87: =I85-I86 | J87: =J85-J86 | K87: =K85-K86 | ... O87: =O85-O86 | P87: =SUM(D87:O87) | Q87: =IF(P85=0,0,P87/P85)
C89: Total Training Consultancy
C90: Total Sales | D90: =D85+D79 | E90: =E85+E79 | F90: =F85+F79 | G90: =G85+G79 | H90: =H85+H79 | I90: =I85+I79 | J90: =J85+J79 | K90: =K85+K79 | ... O90: =O85+O79 | P90: =SUM(D90:O90) | Q90: =(Q91+Q92)
C91: Total COGS | D91: =D86+D80 | E91: =E86+E80 | F91: =F86+F80 | G91: =G86+G80 | H91: =H86+H80 | I91: =I86+I80 | J91: =J86+J80 | K91: =K86+K80 | ... O91: =O86+O80 | P91: =SUM(D91:O91) | Q91: =IF(P90=0,0,P91/P90)
C92: Total Margin | D92: =D90-D91 | E92: =E90-E91 | F92: =F90-F91 | G92: =G90-G91 | H92: =H90-H91 | I92: =I90-I91 | J92: =J90-J91 | K92: =K90-K91 | ... O92: =O90-O91 | P92: =SUM(D92:O92) | Q92: =IF(P90=0,0,P92/P90)
D93: =D71+D64+D58+D52+D46+D40+D34+D27 | E93: =E71+E64+E58+E52+E46+E40+E34+E27 | F93: =F71+F64+F58+F52+F46+F40+F34+F27 | G93: =G71+G64+G58+G52+G46+G40+G34+G27 | H93: =H71+H64+H58+H52+H46+H40+H34+H27 | I93: =I71+I64+I58+I52+I46+I40+I34+I27 | J93: =J71+J64+J58+J52+J46+J40+J34+J27 | K93: =K71+K64+K58+K52+K46+K40+K34+K27 | ... O93: =O71+O64+O58+O52+O46+O40+O34+O27 | T93: Assumptions
C94: Net New | D94: =D71+D64+D58+D52+D46+D40+D34+D27 | E94: =E93-D93 | F94: =F93-E93 | G94: =G93-F93 | H94: =H93-G93 | I94: =I93-H93 | J94: =J93-I93 | K94: =K93-J93 | L94: =L93-K93 | ... O94: =O93-N93 | T94: work hours
B95: Administrative | C95: =C6 | T95: per new acct
C96: Net New Licences Sold | D96: =D94*$T$96 | E96: =E94*$T$96 | F96: =F94*$T$96 | G96: =G94*$T$96 | H96: =H94*$T$96 | I96: =I94*$T$96 | J96: =J94*$T$96 | K96: =K94*$T$96 | ... O96: =O94*$T$96 | T96: 3
C97: Total Sales | D97: =D96*$D$6 | E97: =E96*$D$6 | F97: =F96*$D$6 | G97: =G96*$D$6 | H97: =H96*$D$6 | I97: =I96*$D$6 | J97: =J96*$D$6 | K97: =K96*$D$6 | ... O97: =O96*$D$6 | P97: =SUM(D97:O97) | Q97: =(Q98+Q99)
C98: Total COGS | D98: =D96*$E$6 | E98: =E96*$E$6 | F98: =F96*$E$6 | G98: =G96*$E$6 | H98: =H96*$E$6 | I98: =I96*$E$6 | J98: =J96*$E$6 | K98: =K96*$E$6 | ... O98: =O96*$E$6 | P98: =SUM(D98:O98) | Q98: =IF(P97=0,0,P98/P97)
C99: Total Margin | D99: =D97-D98 | E99: =E97-E98 | F99: =F97-F98 | G99: =G97-G98 | H99: =H97-H98 | I99: =I97-I98 | J99: =J97-J98 | K99: =K97-K98 | ... O99: =O97-O98 | P99: =SUM(D99:O99) | Q99: =IF(P97=0,0,P99/P97)
C101: =C7
C102: Net New Licences Sold | D102: =D94*$T$102 | E102: =E94*$T$102 | F102: =F94*$T$102 | G102: =G94*$T$102 | H102: =H94*$T$102 | I102: =I94*$T$102 | J102: =J94*$T$102 | K102: =K94*$T$102 | ... O102: =O94*$T$102 | T102: 1
C103: Total Sales | D103: =D102*$D$7 | E103: =E102*$D$7 | F103: =F102*$D$7 | G103: =G102*$D$7 | H103: =H102*$D$7 | I103: =I102*$D$7 | J103: =J102*$D$7 | K103: =K102*$D$7 | ... O103: =O102*$D$7 | P103: =SUM(D103:O103) | Q103: =(Q104+Q105)
C104: Total COGS | D104: =D102*$E$7 | E104: =E102*$E$7 | F104: =F102*$E$7 | G104: =G102*$E$7 | H104: =H102*$E$7 | I104: =I102*$E$7 | J104: =J102*$E$7 | K104: =K102*$E$7 | ... O104: =O102*$E$7 | P104: =SUM(D104:O104) | Q104: =IF(P103=0,0,P104/P103)
C105: Total Margin | D105: =D103-D104 | E105: =E103-E104 | F105: =F103-F104 | G105: =G103-G104 | H105: =H103-H104 | I105: =I103-I104 | J105: =J103-J104 | K105: =K103-K104 | ... O105: =O103-O104 | P105: =SUM(D105:O105) | Q105: =IF(P103=0,0,P105/P103)
C107: =C8
C108: Net New Licences Sold | D108: =D94*$T$108 | E108: =E94*$T$108 | F108: =F94*$T$108 | G108: =G94*$T$108 | H108: =H94*$T$108 | I108: =I94*$T$108 | J108: =J94*$T$108 | K108: =K94*$T$108 | ... O108: =O94*$T$108 | T108: 2
C109: Total Sales | D109: =D108*$D$8 | E109: =E108*$D$8 | F109: =F108*$D$8 | G109: =G108*$D$8 | H109: =H108*$D$8 | I109: =I108*$D$8 | J109: =J108*$D$8 | K109: =K108*$D$8 | ... O109: =O108*$D$8 | P109: =SUM(D109:O109) | Q109: =(Q110+Q111)
C110: Total COGS | D110: =D108*$E$8 | E110: =E108*$E$8 | F110: =F108*$E$8 | G110: =G108*$E$8 | H110: =H108*$E$8 | I110: =I108*$E$8 | J110: =J108*$E$8 | K110: =K108*$E$8 | ... O110: =O108*$E$8 | P110: =SUM(D110:O110) | Q110: =IF(P109=0,0,P110/P109)
C111: Total Margin | D111: =D109-D110 | E111: =E109-E110 | F111: =F109-F110 | G111: =G109-G110 | H111: =H109-H110 | I111: =I109-I110 | J111: =J109-J110 | K111: =K109-K110 | ... O111: =O109-O110 | P111: =SUM(D111:O111) | Q111: =IF(P109=0,0,P111/P109)
C113: =C9
C114: Net New Licences Sold | D114: =D94*$T$114 | E114: =E94*$T$114 | F114: =F94*$T$114 | G114: =G94*$T$114 | H114: =H94*$T$114 | I114: =I94*$T$114 | J114: =J94*$T$114 | K114: =K94*$T$114 | ... O114: =O94*$T$114 | T114: 1
C115: Total Sales | D115: =D114*$D$9 | E115: =E114*$D$9 | F115: =F114*$D$9 | G115: =G114*$D$9 | H115: =H114*$D$9 | I115: =I114*$D$9 | J115: =J114*$D$9 | K115: =K114*$D$9 | ... O115: =O114*$D$9 | P115: =SUM(D115:O115) | Q115: =(Q116+Q117)
C116: Total COGS | D116: =D114*$E$9 | E116: =E114*$E$9 | F116: =F114*$E$9 | G116: =G114*$E$9 | H116: =H114*$E$9 | I116: =I114*$E$9 | J116: =J114*$E$9 | K116: =K114*$E$9 | ... O116: =O114*$E$9 | P116: =SUM(D116:O116) | Q116: =IF(P115=0,0,P116/P115)
C117: Total Margin | D117: =D115-D116 | E117: =E115-E116 | F117: =F115-F116 | G117: =G115-G116 | H117: =H115-H116 | I117: =I115-I116 | J117: =J115-J116 | K117: =K115-K116 | ... O117: =O115-O116 | P117: =SUM(D117:O117) | Q117: =IF(P115=0,0,P117/P115)
...

Sheet Revenue 2026
C3: 2026 | D3: Pricing
C4: Offerings and Distribution | D4: Price | E4: COGS | F4: Margin Per Subscription
C5: Administrative
C6: Configuration | D6: 250 | E6: 50 | F6: =D6-E6
C7: On-Boarding- Administrator | D7: 500 | E7: 100 | F7: =D7-E7
C8: On-Boarding Users | D8: 500 | E8: 100 | F8: =D8-E8
C9: Import | D9: ='Pricing Calcuator'!D86 | E9: 600 | F9: =D9-E9
C10: Support | D10: 100 | E10: 50 | F10: =D10-E10
C11: Industry Break Down | E11: ='COGS Analysis'!D18
C12: Hospitality | D12: 250 | E12: ='Revenue 2030'!$Q$210 | F12: =D12-E12
C13: Hospitality- Reseller | D13: 150 | E13: ='Revenue 2030'!$Q$210 | F13: =D13-E13
C14: Real Estate Development | D14: 400 | E14: ='Revenue 2030'!$Q$210 | F14: =D14-E14
C15: Real Estate Development- Reseller | D15: 250 | E15: ='Revenue 2030'!$Q$210 | F15: =D15-E15
C16: Pharma | D16: 400 | E16: ='Revenue 2030'!$Q$210 | F16: =D16-E16
C17: Pharma- Reseller | D17: 250 | E17: ='Revenue 2030'!$Q$210 | F17: =D17-E17
C18: Start up - Small Firms | D18: 200 | E18: ='Revenue 2030'!$Q$210 | F18: =D18-E18
C19: Start up Reseller | D19: 100 | E19: ='Revenue 2030'!$Q$210 | F19: =D19-E19
C20: Training / Consultancy Training as a Service
C21: Thought Library | D21: 50 | E21: 25 | F21: =D21-E21
C22: Consultancy Services | D22: 225 | E22: 125 | F22: =D22-E22
C24: Segments | D24: January | E24: February | F24: March | G24: April | H24: May | I24: June | J24: July | K24: August | L24: September | M24: October | N24: November | O24: December | P24: Annual Totals | Q24: Profit Margin | R24: Profit margin comparison | S24: Churn
B26: Hospitality | C26: =C12
C27: Licences Sold | D27: 340 | E27: 350 | F27: 360 | G27: 380 | H27: 390 | I27: 400 | J27: 425 | K27: 425 | L27: 475 | M27: 490 | N27: 490 | O27: 490 | P27: =O27 | S27: 0.03 | T27: Assumptions
D28: =D27*$S$27 | E28: =E27*$S$27 | F28: =F27*$S$27 | G28: =G27*$S$27 | H28: =H27*$S$27 | I28: =I27*$S$27 | J28: =J27*$S$27 | K28: =K27*$S$27 | ... O28: =O27*$S$27
C29: Total Sales | D29: =(D27-D28)*$D$12 | E29: =(E27-E28)*$D$12 | F29: =(F27-F28)*$D$12 | G29: =(G27-G28)*$D$12 | H29: =(H27-H28)*$D$12 | I29: =(I27-I28)*$D$12 | J29: =(J27-J28)*$D$12 | K29: =(K27-K28)*$D$12 | ... O29: =(O27-O28)*$D$12 | P29: =SUM(D29:O29) | Q29: =(Q30+Q31)
C30: Total COGS | D30: =D27*$E$12 | E30: =E27*$E$12 | F30: =F27*$E$12 | G30: =G27*$E$12 | H30: =H27*$E$12 | I30: =I27*$E$12 | J30: =J27*$E$12 | K30: =K27*$E$12 | ... O30: =O27*$E$12 | P30: =SUM(D30:O30) | Q30: =IF(P29=0,0,P30/P29)
C31: Total Margin | D31: =D29-D30 | E31: =E29-E30 | F31: =F29-F30 | G31: =G29-G30 | H31: =H29-H30 | I31: =I29-I30 | J31: =J29-J30 | K31: =K29-K30 | ... O31: =O29-O30 | P31: =SUM(D31:O31) | Q31: =IF(P29=0,0,P31/P29) | T31: t Additional sales person added to focus on Hospitality - Real Estate both B2B and Reseller
C33: =C13 | T33: t Growth within partners ships with Development companies, i.e. CBRE or smaller entrants
C34: Licences Sold | D34: 10 | E34: 20 | F34: 40 | G34: 50 | H34: 90 | I34: 100 | J34: 125 | K34: 135 | L34: 150 | M34: 160 | N34: 200 | O34: 200 | P34: =O34 | S34: 0.03
D35: =D34*S34
C36: Total Sales | D36: =(D34-D35)*$D$13 | E36: =E34*$D$13 | F36: =F34*$D$13 | G36: =G34*$D$13 | H36: =H34*$D$13 | I36: =I34*$D$13 | J36: =J34*$D$13 | K36: =K34*$D$13 | L36: =L34*$D$13 | ... O36: =O34*$D$13 | P36: =SUM(D36:O36) | Q36: =(Q37+Q38) | T36: t Thought library usage is based on 35% of new users purhasing the thought library access
C37: Total COGS | D37: =D34*$E$13 | E37: =E34*$E$13 | F37: =F34*$E$13 | G37: =G34*$E$13 | H37: =H34*$E$13 | I37: =I34*$E$13 | J37: =J34*$E$13 | K37: =K34*$E$13 | ... O37: =O34*$E$13 | P37: =SUM(D37:O37) | Q37: =IF(P36=0,0,P37/P36)
C38: Total Margin | D38: =D36-D37 | E38: =E36-E37 | F38: =F36-F37 | G38: =G36-G37 | H38: =H36-H37 | I38: =I36-I37 | J38: =J36-J37 | K38: =K36-K37 | ... O38: =O36-O37 | P38: =SUM(D38:O38) | Q38: =IF(P36=0,0,P38/P36) | T38: t Consultancy as a Service based upon 25% of new users
B40: Real Estate | C40: =C14 | T40: t ABM Build- Marketing Insights
C41: Licences Sold | D41: 260 | E41: 275 | F41: 300 | G41: 325 | H41: 325 | I41: 360 | J41: 375 | K41: 380 | L41: 385 | M41: 390 | N41: 400 | O41: 400 | P41: =O41 | S41: 0.03
D42: =D41*$S$41 | E42: =E41*$S$41
C43: Total Sales | D43: =(D41-D42)*$D$14 | E43: =(E41-E42)*$D$14 | F43: =F41*$D$14 | G43: =G41*$D$14 | H43: =H41*$D$14 | I43: =I41*$D$14 | J43: =J41*$D$14 | K43: =K41*$D$14 | L43: =L41*$D$14 | M43: =M41*$D$14 | ... O43: =O41*$D$14 | P43: =SUM(D43:O43) | Q43: =(Q44+Q45)
C44: Total COGS | D44: =D41*$E$14 | E44: =E41*$E$14 | F44: =F41*$E$14 | G44: =G41*$E$14 | H44: =H41*$E$14 | I44: =I41*$E$14 | J44: =J41*$E$14 | K44: =K41*$E$14 | ... O44: =O41*$E$14 | P44: =SUM(D44:O44) | Q44: =IF(P43=0,0,P44/P43)
C45: Total Margin | D45: =D43-D44 | E45: =E43-E44 | F45: =F43-F44 | G45: =G43-G44 | H45: =H43-H44 | I45: =I43-I44 | J45: =J43-J44 | K45: =K43-K44 | ... O45: =O43-O44 | P45: =SUM(D45:O45) | Q45: =IF(P43=0,0,P45/P43)
C47: =C15
C48: Licences Sold | D48: 10 | E48: 10 | F48: 10 | G48: 40 | H48: 40 | I48: 50 | J48: 60 | K48: 75 | L48: 80 | M48: 95 | N48: 100 | O48: 150 | P48: =O48 | S48: 0.03
D49: =D48*$S$55 | E49: =E48*$S$55 | F49: =F48*$S$55 | G49: =G48*$S$55 | H49: =H48*$S$55 | I49: =I48*$S$55 | J49: =J48*$S$55 | K49: =K48*$S$55 | ... O49: =O48*$S$55
C50: Total Sales | D50: =(D48-D49)*$D$15 | E50: =(E48-E49)*$D$15 | F50: =(F48-F49)*$D$15 | G50: =(G48-G49)*$D$15 | H50: =(H48-H49)*$D$15 | I50: =(I48-I49)*$D$15 | J50: =(J48-J49)*$D$15 | K50: =(K48-K49)*$D$15 | ... O50: =(O48-O49)*$D$15 | P50: =SUM(D50:O50) | Q50: =(Q51+Q52)
C51: Total COGS | D51: =D48*$E$15 | E51: =E48*$E$15 | F51: =F48*$E$15 | G51: =G48*$E$15 | H51: =H48*$E$15 | I51: =I48*$E$15 | J51: =J48*$E$15 | K51: =K48*$E$15 | ... O51: =O48*$E$15 | P51: =SUM(D51:O51) | Q51: =IF(P50=0,0,P51/P50)
C52: Total Margin | D52: =D50-D51 | E52: =E50-E51 | F52: =F50-F51 | G52: =G50-G51 | H52: =H50-H51 | I52: =I50-I51 | J52: =J50-J51 | K52: =K50-K51 | ... O52: =O50-O51 | P52: =SUM(D52:O52) | Q52: =IF(P50=0,0,P52/P50)
B54: Pharma | C54: =C16
C55: Licences Sold | D55: 0 | E55: 0 | F55: 0 | G55: 0 | H55: 0 | I55: 0 | J55: 0 | K55: 0 | L55: 0 | M55: 0 | N55: 0 | O55: 0 | P55: =O55 | S55: 0.03
D56: =D55*$S$55 | E56: =E55*$S$55 | F56: =F55*$S$55 | G56: =G55*$S$55 | H56: =H55*$S$55 | I56: =I55*$S$55 | J56: =J55*$S$55 | K56: =K55*$S$55 | ... O56: =O55*$S$55
C57: Total Sales | D57: =(D55-D56)*$D$16 | E57: =(E55-E56)*$D$16 | F57: =(F55-F56)*$D$16 | G57: =(G55-G56)*$D$16 | H57: =(H55-H56)*$D$16 | I57: =(I55-I56)*$D$16 | J57: =(J55-J56)*$D$16 | K57: =(K55-K56)*$D$16 | ... O57: =(O55-O56)*$D$16 | P57: =SUM(D57:O57) | Q57: =(Q58+Q59)
C58: Total COGS | D58: =D55*$E$16 | E58: =E55*$E$16 | F58: =F55*$E$16 | G58: =G55*$E$16 | H58: =H55*$E$16 | I58: =I55*$E$16 | J58: =J55*$E$16 | K58: =K55*$E$16 | ... O58: =O55*$E$16 | P58: =SUM(D58:O58) | Q58: =IF(P57=0,0,P58/P57)
C59: Total Margin | D59: =D57-D58 | E59: =E57-E58 | F59: =F57-F58 | G59: =G57-G58 | H59: =H57-H58 | I59: =I57-I58 | J59: =J57-J58 | K59: =K57-K58 | ... O59: =O57-O58 | P59: =SUM(D59:O59) | Q59: =IF(P57=0,0,P59/P57)
C61: =C17
C62: Licences Sold | D62: 0 | E62: 0 | F62: 0 | G62: 0 | H62: 0 | I62: 0 | J62: 0 | K62: 0 | L62: 0 | M62: 0 | N62: 0 | O62: 0 | P62: =O62 | S62: 0.03
D63: =D62*$S$62 | E63: =E62*$S$62 | F63: =F62*$S$62 | G63: =G62*$S$62 | H63: =H62*$S$62 | I63: =I62*$S$62 | J63: =J62*$S$62 | K63: =K62*$S$62 | ... O63: =O62*$S$62
C64: Total Sales | D64: =(D62-D63)*$D$17 | E64: =E62*$D$17 | F64: =F62*$D$17 | G64: =G62*$D$17 | H64: =H62*$D$17 | I64: =I62*$D$17 | J64: =J62*$D$17 | K64: =K62*$D$17 | L64: =L62*$D$17 | ... O64: =O62*$D$17 | P64: =SUM(D64:O64) | Q64: =(Q65+Q66)
C65: Total COGS | D65: =D62*$E$17 | E65: =E62*$E$17 | F65: =F62*$E$17 | G65: =G62*$E$17 | H65: =H62*$E$17 | I65: =I62*$E$17 | J65: =J62*$E$17 | K65: =K62*$E$17 | ... O65: =O62*$E$17 | P65: =SUM(D65:O65) | Q65: =IF(P64=0,0,P65/P64)
C66: Total Margin | D66: =D64-D65 | E66: =E64-E65 | F66: =F64-F65 | G66: =G64-G65 | H66: =H64-H65 | I66: =I64-I65 | J66: =J64-J65 | K66: =K64-K65 | ... O66: =O64-O65 | P66: =SUM(D66:O66) | Q66: =IF(P64=0,0,P66/P64)
B68: Start up | C68: =C18
C69: Licences Sold | D69: 80 | E69: 100 | F69: 180 | G69: 200 | H69: 225 | I69: 230 | J69: 245 | K69: 250 | L69: 300 | M69: 325 | N69: 325 | O69: 325 | P69: =O69 | S69: 0.05
D70: =D69*$S$69 | E70: =E69*$S$69 | F70: =F69*$S$69 | G70: =G69*$S$69 | H70: =H69*$S$69 | I70: =I69*$S$69 | J70: =J69*$S$69 | K70: =K69*$S$69 | ... O70: =O69*$S$69
C71: Total Sales | D71: =(D69-D70)*$D$18 | E71: =(E69-E70)*$D$18 | F71: =(F69-F70)*$D$18 | G71: =(G69-G70)*$D$18 | H71: =(H69-H70)*$D$18 | I71: =(I69-I70)*$D$18 | J71: =(J69-J70)*$D$18 | K71: =(K69-K70)*$D$18 | ... O71: =(O69-O70)*$D$18 | P71: =SUM(D71:O71) | Q71: =(Q72+Q73)
C72: Total COGS | D72: =D69*$E$18 | E72: =E69*$E$18 | F72: =F69*$E$18 | G72: =G69*$E$18 | H72: =H69*$E$18 | I72: =I69*$E$18 | J72: =J69*$E$18 | K72: =K69*$E$18 | ... O72: =O69*$E$18 | P72: =SUM(D72:O72) | Q72: =IF(P71=0,0,P72/P71)
C73: Total Margin | D73: =D71-D72 | E73: =E71-E72 | F73: =F71-F72 | G73: =G71-G72 | H73: =H71-H72 | I73: =I71-I72 | J73: =J71-J72 | K73: =K71-K72 | ... O73: =O71-O72 | P73: =SUM(D73:O73) | Q73: =IF(P71=0,0,P73/P71)
C75: =C19
C76: Licences Sold | D76: 0 | E76: 0 | F76: 0 | G76: 0 | H76: 0 | I76: 0 | J76: 0 | K76: 0 | L76: 0 | M76: 0 | N76: 0 | O76: 0 | P76: =O76 | S76: 0.05
D77: =D76*S76 | E77: =E76*T76 | F77: =F76*U76 | G77: =G76*V76 | H77: =H76*W76 | I77: =I76*X76 | J77: =J76*Y76 | K77: =K76*Z76 | ... O77: =O76*AD76
C78: Total Sales | D78: =(D76-D77)*$D$19 | E78: =E76*$D$19 | F78: =F76*$D$19 | G78: =G76*$D$19 | H78: =H76*$D$19 | I78: =I76*$D$19 | J78: =J76*$D$19 | K78: =K76*$D$19 | L78: =L76*$D$19 | ... O78: =O76*$D$19 | P78: =SUM(D78:O78) | Q78: =(Q79+Q80)
C79: Total COGS | D79: =D76*$E$19 | E79: =E76*$E$19 | F79: =F76*$E$19 | G79: =G76*$E$19 | H79: =H76*$E$19 | I79: =I76*$E$19 | J79: =J76*$E$19 | K79: =K76*$E$19 | ... O79: =O76*$E$19 | P79: =SUM(D79:O79) | Q79: =IF(P78=0,0,P79/P78)
C80: Total Margin | D80: =D78-D79 | E80: =E78-E79 | F80: =F78-F79 | G80: =G78-G79 | H80: =H78-H79 | I80: =I78-I79 | J80: =J78-J79 | K80: =K78-K79 | ... O80: =O78-O79 | P80: =SUM(D80:O80) | Q80: =IF(P78=0,0,P80/P78)
B83: Consultancy / Training | C83: =C21
C84: Access Sold | D84: =D175*0.35 | E84: =E175*0.35 | F84: =F175*0.35 | G84: =G175*0.35 | H84: =H175*0.35 | I84: =I175*0.35 | J84: =J175*0.35 | K84: =K175*0.35 | ... O84: =O175*0.35
C85: Total Sales | D85: =D84*$D$21 | E85: =E84*$D$21 | F85: =F84*$D$21 | G85: =G84*$D$21 | H85: =H84*$D$21 | I85: =I84*$D$21 | J85: =J84*$D$21 | K85: =K84*$D$21 | ... O85: =O84*$D$21 | P85: =SUM(D85:O85) | Q85: =(Q86+Q87)
C86: Total COGS | D86: =D84*$E$21 | E86: =E84*$E$21 | F86: =F84*$E$21 | G86: =G84*$E$21 | H86: =H84*$E$21 | I86: =I84*$E$21 | J86: =J84*$E$21 | K86: =K84*$E$21 | ... O86: =O84*$E$21 | P86: =SUM(D86:O86) | Q86: =IF(P85=0,0,P86/P85)
C87: Total Margin | D87: =D85-D86 | E87: =E85-E86 | F87: =F85-F86 | G87: =G85-G86 | H87: =H85-H86 | I87: =I85-I86 | J87: =J85-J86 | K87: =K85-K86 | ... O87: =O85-O86 | P87: =SUM(D87:O87) | Q87: =IF(P85=0,0,P87/P85)
C89: =C22
C90: Hours Sold | D90: =D175*0.25 | E90: =E175*0.25 | F90: =F175*0.25 | G90: =G175*0.25 | H90: =H175*0.25 | I90: =I175*0.25 | J90: =J175*0.25 | K90: =K175*0.25 | ... O90: =O175*0.25
C91: Total Sales | D91: =D90*$D$22 | E91: =E90*$D$22 | F91: =F90*$D$22 | G91: =G90*$D$22 | H91: =H90*$D$22 | I91: =I90*$D$22 | J91: =J90*$D$22 | K91: =K90*$D$22 | ... O91: =O90*$D$22 | P91: =SUM(D91:O91) | Q91: =(Q92+Q93)
C92: Total COGS | D92: =D90*$E$22 | E92: =E90*$E$22 | F92: =F90*$E$22 | G92: =G90*$E$22 | H92: =H90*$E$22 | I92: =I90*$E$22 | J92: =J90*$E$22 | K92: =K90*$E$22 | ... O92: =O90*$E$22 | P92: =SUM(D92:O92) | Q92: =IF(P91=0,0,P92/P91)
C93: Total Margin | D93: =D91-D92 | E93: =E91-E92 | F93: =F91-F92 | G93: =G91-G92 | H93: =H91-H92 | I93: =I91-I92 | J93: =J91-J92 | K93: =K91-K92 | ... O93: =O91-O92 | P93: =SUM(D93:O93) | Q93: =IF(P91=0,0,P93/P91)
C95: Total Training Consultancy
C96: Total Sales | D96: =D91+D85 | E96: =E91+E85 | F96: =F91+F85 | G96: =G91+G85 | H96: =H91+H85 | I96: =I91+I85 | J96: =J91+J85 | K96: =K91+K85 | ... O96: =O91+O85 | P96: =SUM(D96:O96) | Q96: =(Q97+Q98)
C97: Total COGS | D97: =D92+D86 | E97: =E92+E86 | F97: =F92+F86 | G97: =G92+G86 | H97: =H92+H86 | I97: =I92+I86 | J97: =J92+J86 | K97: =K92+K86 | ... O97: =O92+O86 | P97: =SUM(D97:O97) | Q97: =IF(P96=0,0,P97/P96)
C98: Total Margin | D98: =D96-D97 | E98: =E96-E97 | F98: =F96-F97 | G98: =G96-G97 | H98: =H96-H97 | I98: =I96-I97 | J98: =J96-J97 | K98: =K96-K97 | ... O98: =O96-O97 | P98: =SUM(D98:O98) | Q98: =IF(P96=0,0,P98/P96)
D99: =D76+D69+D62+D55+D48+D41+D34+D27 | E99: =E76+E69+E62+E55+E48+E41+E34+E27 | F99: =F76+F69+F62+F55+F48+F41+F34+F27 | G99: =G76+G69+G62+G55+G48+G41+G34+G27 | H99: =H76+H69+H62+H55+H48+H41+H34+H27 | I99: =I76+I69+I62+I55+I48+I41+I34+I27 | J99: =J76+J69+J62+J55+J48+J41+J34+J27 | K99: =K76+K69+K62+K55+K48+K41+K34+K27 | ... O99: =O76+O69+O62+O55+O48+O41+O34+O27 | T99: Assumptions
C100: Net New | D100: =(D76+D69+D62+D55+D48+D41+D34+D27)-'Revenue 2025'!P169 | E100: =E99-D99 | F100: =F99-E99 | G100: =G99-F99 | H100: =H99-G99 | I100: =I99-H99 | J100: =J99-I99 | K100: =K99-J99 | L100: =L99-K99 | ... O100: =O99-N99 | T100: work hours
B101: Administrative | C101: =C6 | T101: per new acct
C102: Net New Licences Sold | F102: =F100*$T$102 | G102: =G100*$T$102 | H102: =H100*$T$102 | I102: =I100*$T$102 | J102: =J100*$T$102 | K102: =K100*$T$102 | L102: =L100*$T$102 | M102: =M100*$T$102 | ... O102: =O100*$T$102 | T102: 1
C103: Total Sales | D103: 80000 | E103: =E102*$D$6 | F103: =F102*$D$6 | G103: =G102*$D$6 | H103: =H102*$D$6 | I103: =I102*$D$6 | J103: =J102*$D$6 | K103: =K102*$D$6 | L103: =L102*$D$6 | ... O103: =O102*$D$6 | P103: =SUM(D103:O103) | Q103: =(Q104+Q105)
C104: Total COGS | D104: =D102*$E$6 | E104: =E102*$E$6 | F104: =F102*$E$6 | G104: =G102*$E$6 | H104: =H102*$E$6 | I104: =I102*$E$6 | J104: =J102*$E$6 | K104: =K102*$E$6 | ... O104: =O102*$E$6 | P104: =SUM(D104:O104) | Q104: =IF(P103=0,0,P104/P103)
C105: Total Margin | D105: =D103-D104 | E105: =E103-E104 | F105: =F103-F104 | G105: =G103-G104 | H105: =H103-H104 | I105: =I103-I104 | J105: =J103-J104 | K105: =K103-K104 | ... O105: =O103-O104 | P105: =SUM(D105:O105) | Q105: =IF(P103=0,0,P105/P103)
C107: =C7
C108: Net New Licences Sold | D108: =D100*$T$108 | E108: =E100*$T$108 | F108: =F100*$T$108 | G108: =G100*$T$108 | H108: =H100*$T$108 | I108: =I100*$T$108 | J108: =J100*$T$108 | K108: =K100*$T$108 | ... O108: =O100*$T$108 | T108: 1
C109: Total Sales | D109: =D108*$D$7 | E109: =E108*$D$7 | F109: =F108*$D$7 | G109: =G108*$D$7 | H109: =H108*$D$7 | I109: =I108*$D$7 | J109: =J108*$D$7 | K109: =K108*$D$7 | ... O109: =O108*$D$7 | P109: =SUM(D109:O109) | Q109: =(Q110+Q111)
C110: Total COGS | D110: =D108*$E$7 | E110: =E108*$E$7 | F110: =F108*$E$7 | G110: =G108*$E$7 | H110: =H108*$E$7 | I110: =I108*$E$7 | J110: =J108*$E$7 | K110: =K108*$E$7 | ... O110: =O108*$E$7 | P110: =SUM(D110:O110) | Q110: =IF(P109=0,0,P110/P109)
C111: Total Margin | D111: =D109-D110 | E111: =E109-E110 | F111: =F109-F110 | G111: =G109-G110 | H111: =H109-H110 | I111: =I109-I110 | J111: =J109-J110 | K111: =K109-K110 | ... O111: =O109-O110 | P111: =SUM(D111:O111) | Q111: =IF(P109=0,0,P111/P109)
C113: =C8
C114: Net New Licences Sold | D114: =D100*$T$114 | E114: =E100*$T$114 | F114: =F100*$T$114 | G114: =G100*$T$114 | H114: =H100*$T$114 | I114: =I100*$T$114 | J114: =J100*$T$114 | K114: =K100*$T$114 | ... O114: =O100*$T$114 | T114: 2
C115: Total Sales | D115: =D114*$D$8 | E115: =E114*$D$8 | F115: =F114*$D$8 | G115: =G114*$D$8 | H115: =H114*$D$8 | I115: =I114*$D$8 | J115: =J114*$D$8 | K115: =K114*$D$8 | ... O115: =O114*$D$8 | P115: =SUM(D115:O115) | Q115: =(Q116+Q117)
C116: Total COGS | D116: =D114*$E$8 | E116: =E114*$E$8 | F116: =F114*$E$8 | G116: =G114*$E$8 | H116: =H114*$E$8 | I116: =I114*$E$8 | J116: =J114*$E$8 | K116: =K114*$E$8 | ... O116: =O114*$E$8 | P116: =SUM(D116:O116) | Q116: =IF(P115=0,0,P116/P115)
C117: Total Margin | D117: =D115-D116 | E117: =E115-E116 | F117: =F115-F116 | G117: =G115-G116 | H117: =H115-H116 | I117: =I115-I116 | J117: =J115-J116 | K117: =K115-K116 | ... O117: =O115-O116 | P117: =SUM(D117:O117) | Q117: =IF(P115=0,0,P117/P115)
...

Sheet Revenue 2027
C3: 2027 | D3: Pricing
C4: Offerings and Distribution | D4: Price | E4: COGS | F4: Margin Per Subscription
C5: Administrative | H5: Growth Model
C6: Configuration | D6: 250 | E6: 50 | F6: =D6-E6
C7: On-Boarding- Administrator | D7: 500 | E7: 100 | F7: =D7-E7
C8: On-Boarding Users | D8: 500 | E8: 100 | F8: =D8-E8
C9: Import | D9: ='Pricing Calcuator'!D86 | E9: 600 | F9: =D9-E9
C10: Support | D10: 100 | E10: 50 | F10: =D10-E10
C11: Industry Break Down | E11: ='COGS Analysis'!D18
C12: Hospitality | D12: 250 | E12: ='Revenue 2030'!Q210 | F12: =D12-E12
C13: Hospitality- Reseller | D13: 100 | E13: ='Revenue 2030'!$Q$210 | F13: =D13-E13
C14: Real Estate Development | D14: 400 | E14: ='Revenue 2030'!$Q$210 | F14: =D14-E14
C15: Real Estate Development- Reseller | D15: 250 | E15: ='Revenue 2030'!$Q$210 | F15: =D15-E15
C16: Pharma | D16: 400 | E16: ='Revenue 2030'!$Q$210 | F16: =D16-E16
C17: Pharma- Reseller | D17: 250 | E17: ='Revenue 2030'!$Q$210 | F17: =D17-E17
C18: Start up - Small Firms | D18: 200 | E18: ='Revenue 2030'!$Q$210 | F18: =D18-E18
C19: Start up Reseller | D19: 100 | E19: ='Revenue 2030'!$Q$210 | F19: =D19-E19
C20: Training / Consultancy Training as a Service
C21: Thought Library | D21: 50 | E21: 25 | F21: =D21-E21
C22: Consultancy Services | D22: 225 | E22: 125 | F22: =D22-E22
C24: Segments | D24: January | E24: February | F24: March | G24: April | H24: May | I24: June | J24: July | K24: August | L24: September | M24: October | N24: November | O24: December | P24: Annual Totals | Q24: Profit Margin | R24: Profit margin comparison | S24: Churn
B26: Hospitality | C26: =C12 | T26: Assumptions
C27: Licences Sold | D27: 500 | E27: 525 | F27: 540 | G27: 600 | H27: 625 | I27: 680 | J27: 700 | K27: 725 | L27: 725 | M27: 725 | N27: 725 | O27: 750 | P27: =O27 | S27: 0.03
D28: =D27*$S$27 | E28: =E27*$S$27 | F28: =F27*$S$27 | G28: =G27*$S$27 | H28: =H27*$S$27 | I28: =I27*$S$27 | J28: =J27*$S$27 | K28: =K27*$S$27 | ... O28: =O27*$S$27
C29: Total Sales | D29: =(D27-D28)*$D$12 | E29: =(E27-E28)*$D$12 | F29: =(F27-F28)*$D$12 | G29: =(G27-G28)*$D$12 | H29: =(H27-H28)*$D$12 | I29: =(I27-I28)*$D$12 | J29: =(J27-J28)*$D$12 | K29: =(K27-K28)*$D$12 | ... O29: =(O27-O28)*$D$12 | P29: =SUM(D29:O29) | Q29: =(Q30+Q31)
C30: Total COGS | D30: =D27*$E$12 | E30: =E27*$E$12 | F30: =F27*$E$12 | G30: =G27*$E$12 | H30: =H27*$E$12 | I30: =I27*$E$12 | J30: =J27*$E$12 | K30: =K27*$E$12 | ... O30: =O27*$E$12 | P30: =SUM(D30:O30) | Q30: =IF(P29=0,0,P30/P29) | T30: t Additional sales person added to focus on Start ups and Pharma
C31: Total Margin | D31: =D29-D30 | E31: =E29-E30 | F31: =F29-F30 | G31: =G29-G30 | H31: =H29-H30 | I31: =I29-I30 | J31: =J29-J30 | K31: =K29-K30 | ... O31: =O29-O30 | P31: =SUM(D31:O31) | Q31: =IF(P29=0,0,P31/P29)
T32: t Thought library usage is based on 35% of new users purchasing the thought library access
C33: =C13
C34: Licences Sold | D34: 210 | E34: 450 | F34: 465 | G34: 480 | H34: 480 | I34: 500 | J34: 425 | K34: 425 | L34: 450 | M34: 460 | N34: 470 | O34: 470 | P34: =O34 | S34: 0.03 | T34: t Consultancy as a Service based upon 25% of new users
D35: =D34*$S$34 | E35: =E34*$S$34 | F35: =F34*$S$34 | G35: =G34*$S$34 | H35: =H34*$S$34 | I35: =I34*$S$34 | J35: =J34*$S$34 | K35: =K34*$S$34 | ... O35: =O34*$S$34
C36: Total Sales | D36: =(D34-D35)*$D$13 | E36: =(E34-E35)*$D$13 | F36: =(F34-F35)*$D$13 | G36: =(G34-G35)*$D$13 | H36: =(H34-H35)*$D$13 | I36: =(I34-I35)*$D$13 | J36: =(J34-J35)*$D$13 | K36: =(K34-K35)*$D$13 | ... O36: =(O34-O35)*$D$13 | P36: =SUM(D36:O36) | Q36: =(Q37+Q38)
C37: Total COGS | D37: =D34*$E$13 | E37: =E34*$E$13 | F37: =F34*$E$13 | G37: =G34*$E$13 | H37: =H34*$E$13 | I37: =I34*$E$13 | J37: =J34*$E$13 | K37: =K34*$E$13 | ... O37: =O34*$E$13 | P37: =SUM(D37:O37) | Q37: =IF(P36=0,0,P37/P36) | T37: t Sales Person added for Life Sciences / Pharma
C38: Total Margin | D38: =D36-D37 | E38: =E36-E37 | F38: =F36-F37 | G38: =G36-G37 | H38: =H36-H37 | I38: =I36-I37 | J38: =J36-J37 | K38: =K36-K37 | ... O38: =O36-O37 | P38: =SUM(D38:O38) | Q38: =IF(P36=0,0,P38/P36)
T39: t ABM Benefit Realized
B40: Real Estate | C40: =C14
C41: Licences Sold | D41: 400 | E41: 500 | F41: 510 | G41: 530 | H41: 540 | I41: 570 | J41: 580 | K41: 570 | L41: 600 | M41: 625 | N41: 625 | O41: 625 | P41: =O41 | S41: 0.03
D42: =D41*$S$41 | E42: =E41*$S$41 | F42: =F41*$S$41 | G42: =G41*$S$41 | H42: =H41*$S$41 | I42: =I41*$S$41 | J42: =J41*$S$41 | K42: =K41*$S$41 | ... O42: =O41*$S$41
C43: Total Sales | D43: =(D41-D42)*$D$14 | E43: =(E41-E42)*$D$14 | F43: =(F41-F42)*$D$14 | G43: =(G41-G42)*$D$14 | H43: =(H41-H42)*$D$14 | I43: =(I41-I42)*$D$14 | J43: =(J41-J42)*$D$14 | K43: =(K41-K42)*$D$14 | ... O43: =(O41-O42)*$D$14 | P43: =SUM(D43:O43) | Q43: =(Q44+Q45)
C44: Total COGS | D44: =D41*$E$14 | E44: =E41*$E$14 | F44: =F41*$E$14 | G44: =G41*$E$14 | H44: =H41*$E$14 | I44: =I41*$E$14 | J44: =J41*$E$14 | K44: =K41*$E$14 | ... O44: =O41*$E$14 | P44: =SUM(D44:O44) | Q44: =IF(P43=0,0,P44/P43)
C45: Total Margin | D45: =D43-D44 | E45: =E43-E44 | F45: =F43-F44 | G45: =G43-G44 | H45: =H43-H44 | I45: =I43-I44 | J45: =J43-J44 | K45: =K43-K44 | ... O45: =O43-O44 | P45: =SUM(D45:O45) | Q45: =IF(P43=0,0,P45/P43)
C47: =C15
C48: Licences Sold | D48: 150 | E48: 150 | F48: 170 | G48: 180 | H48: 190 | I48: 200 | J48: 210 | K48: 215 | L48: 215 | M48: 225 | N48: 225 | O48: 225 | P48: =O48 | S48: 0.03
D49: =D48*$S$48 | E49: =E48*$S$48 | F49: =F48*$S$48 | G49: =G48*$S$48 | H49: =H48*$S$48 | I49: =I48*$S$48 | J49: =J48*$S$48 | K49: =K48*$S$48 | ... O49: =O48*$S$48
C50: Total Sales | D50: =(D48-D49)*$D$15 | E50: =(E48-E49)*$D$15 | F50: =(F48-F49)*$D$15 | G50: =(G48-G49)*$D$15 | H50: =(H48-H49)*$D$15 | I50: =(I48-I49)*$D$15 | J50: =(J48-J49)*$D$15 | K50: =(K48-K49)*$D$15 | ... O50: =(O48-O49)*$D$15 | P50: =SUM(D50:O50) | Q50: =(Q51+Q52)
C51: Total COGS | D51: =D48*$E$15 | E51: =E48*$E$15 | F51: =F48*$E$15 | G51: =G48*$E$15 | H51: =H48*$E$15 | I51: =I48*$E$15 | J51: =J48*$E$15 | K51: =K48*$E$15 | ... O51: =O48*$E$15 | P51: =SUM(D51:O51) | Q51: =IF(P50=0,0,P51/P50)
C52: Total Margin | D52: =D50-D51 | E52: =E50-E51 | F52: =F50-F51 | G52: =G50-G51 | H52: =H50-H51 | I52: =I50-I51 | J52: =J50-J51 | K52: =K50-K51 | ... O52: =O50-O51 | P52: =SUM(D52:O52) | Q52: =IF(P50=0,0,P52/P50)
B54: Pharma | C54: =C16
C55: Licences Sold | D55: 40 | E55: 100 | F55: 120 | G55: 150 | H55: 150 | I55: 150 | J55: 150 | K55: 150 | L55: 200 | M55: 200 | N55: 200 | O55: 200 | P55: =O55 | S55: 0.03
D56: =D55*$S$55 | E56: =E55*$S$55 | F56: =F55*$S$55 | G56: =G55*$S$55 | H56: =H55*$S$55 | I56: =I55*$S$55 | J56: =J55*$S$55 | K56: =K55*$S$55 | ... O56: =O55*$S$55
C57: Total Sales | D57: =(D55-D56)*$D$16 | E57: =(E55-E56)*$D$16 | F57: =(F55-F56)*$D$16 | G57: =(G55-G56)*$D$16 | H57: =(H55-H56)*$D$16 | I57: =(I55-I56)*$D$16 | J57: =(J55-J56)*$D$16 | K57: =(K55-K56)*$D$16 | ... O57: =(O55-O56)*$D$16 | P57: =SUM(D57:O57) | Q57: =(Q58+Q59)
C58: Total COGS | D58: =D55*$E$16 | E58: =E55*$E$16 | F58: =F55*$E$16 | G58: =G55*$E$16 | H58: =H55*$E$16 | I58: =I55*$E$16 | J58: =J55*$E$16 | K58: =K55*$E$16 | ... O58: =O55*$E$16 | P58: =SUM(D58:O58) | Q58: =IF(P57=0,0,P58/P57)
C59: Total Margin | D59: =D57-D58 | E59: =E57-E58 | F59: =F57-F58 | G59: =G57-G58 | H59: =H57-H58 | I59: =I57-I58 | J59: =J57-J58 | K59: =K57-K58 | ... O59: =O57-O58 | P59: =SUM(D59:O59) | Q59: =IF(P57=0,0,P59/P57)
C61: =C17
C62: Licences Sold | D62: 0 | E62: 0 | F62: 0 | G62: 0 | H62: 0 | I62: 0 | J62: 0 | K62: 0 | L62: 0 | M62: 0 | N62: 0 | O62: 0 | P62: =O62 | S62: 0.03
D63: =D62*$S$62 | E63: =E62*$S$62 | F63: =F62*$S$62 | G63: =G62*$S$62 | H63: =H62*$S$62 | I63: =I62*$S$62 | J63: =J62*$S$62 | K63: =K62*$S$62 | ... O63: =O62*$S$62
C64: Total Sales | D64: =(D62-D63*$D$17) | E64: =(E62-E63*$D$17) | F64: =(F62-F63*$D$17) | G64: =(G62-G63*$D$17) | H64: =(H62-H63*$D$17) | I64: =(I62-I63*$D$17) | J64: =(J62-J63*$D$17) | K64: =(K62-K63*$D$17) | ... O64: =(O62-O63*$D$17) | P64: =SUM(D64:O64) | Q64: =(Q65+Q66)
C65: Total COGS | D65: =D62*$E$17 | E65: =E62*$E$17 | F65: =F62*$E$17 | G65: =G62*$E$17 | H65: =H62*$E$17 | I65: =I62*$E$17 | J65: =J62*$E$17 | K65: =K62*$E$17 | ... O65: =O62*$E$17 | P65: =SUM(D65:O65) | Q65: =IF(P64=0,0,P65/P64)
C66: Total Margin | D66: =D64-D65 | E66: =E64-E65 | F66: =F64-F65 | G66: =G64-G65 | H66: =H64-H65 | I66: =I64-I65 | J66: =J64-J65 | K66: =K64-K65 | ... O66: =O64-O65 | P66: =SUM(D66:O66) | Q66: =IF(P64=0,0,P66/P64)
B68: Start ups | C68: =C18
C69: Licences Sold | D69: 325 | E69: 330 | F69: 335 | G69: 340 | H69: 350 | I69: 360 | J69: 370 | K69: 380 | L69: 390 | M69: 310 | N69: 320 | O69: 320 | P69: =O69 | S69: 0.05
D70: =D69*$S$69 | E70: =E69*$S$69 | F70: =F69*$S$69 | G70: =G69*$S$69 | H70: =H69*$S$69 | I70: =I69*$S$69 | J70: =J69*$S$69 | K70: =K69*$S$69 | ... O70: =O69*$S$69
C71: Total Sales | D71: =(D69-D70)*$D$18 | E71: =(E69-E70)*$D$18 | F71: =(F69-F70)*$D$18 | G71: =(G69-G70)*$D$18 | H71: =(H69-H70)*$D$18 | I71: =(I69-I70)*$D$18 | J71: =(J69-J70)*$D$18 | K71: =(K69-K70)*$D$18 | ... O71: =(O69-O70)*$D$18 | P71: =SUM(D71:O71) | Q71: =(Q72+Q73)
C72: Total COGS | D72: =D69*$E$18 | E72: =E69*$E$18 | F72: =F69*$E$18 | G72: =G69*$E$18 | H72: =H69*$E$18 | I72: =I69*$E$18 | J72: =J69*$E$18 | K72: =K69*$E$18 | ... O72: =O69*$E$18 | P72: =SUM(D72:O72) | Q72: =IF(P71=0,0,P72/P71)
C73: Total Margin | D73: =D71-D72 | E73: =E71-E72 | F73: =F71-F72 | G73: =G71-G72 | H73: =H71-H72 | I73: =I71-I72 | J73: =J71-J72 | K73: =K71-K72 | ... O73: =O71-O72 | P73: =SUM(D73:O73) | Q73: =IF(P71=0,0,P73/P71)
C75: =C19
C76: Licences Sold | D76: 0 | E76: 0 | F76: 0 | G76: 0 | H76: 0 | I76: 0 | J76: 0 | K76: 0 | L76: 0 | M76: 0 | N76: 0 | O76: 0 | P76: =O76 | S76: 0.05
D77: =D76*S76 | E77: =E76*T76 | F77: =F76*U76 | G77: =G76*V76 | H77: =H76*W76 | I77: =I76*X76 | J77: =J76*Y76 | K77: =K76*Z76 | ... O77: =O76*AD76
C78: Total Sales | D78: =(D76-D77)*$D$19 | E78: =(E76-E77)*$D$19 | F78: =(F76-F77)*$D$19 | G78: =(G76-G77)*$D$19 | H78: =(H76-H77)*$D$19 | I78: =(I76-I77)*$D$19 | J78: =(J76-J77)*$D$19 | K78: =(K76-K77)*$D$19 | ... O78: =(O76-O77)*$D$19 | P78: =SUM(D78:O78) | Q78: =(Q79+Q80)
C79: Total COGS | D79: =D76*$E$19 | E79: =E76*$E$19 | F79: =F76*$E$19 | G79: =G76*$E$19 | H79: =H76*$E$19 | I79: =I76*$E$19 | J79: =J76*$E$19 | K79: =K76*$E$19 | ... O79: =O76*$E$19 | P79: =SUM(D79:O79) | Q79: =IF(P78=0,0,P79/P78)
C80: Total Margin | D80: =D78-D79 | E80: =E78-E79 | F80: =F78-F79 | G80: =G78-G79 | H80: =H78-H79 | I80: =I78-I79 | J80: =J78-J79 | K80: =K78-K79 | ... O80: =O78-O79 | P80: =SUM(D80:O80) | Q80: =IF(P78=0,0,P80/P78)
B83: Consultancy / Training | C83: =C21
C84: Access Sold | D84: =D175*0.35 | E84: =E175*0.35 | F84: =F175*0.35 | G84: =G175*0.35 | H84: =H175*0.35 | I84: =I175*0.35 | J84: =J175*0.35 | K84: =K175*0.35 | ... O84: =O175*0.35
C85: Total Sales | D85: =D84*$D$21 | E85: =E84*$D$21 | F85: =F84*$D$21 | G85: =G84*$D$21 | H85: =H84*$D$21 | I85: =I84*$D$21 | J85: =J84*$D$21 | K85: =K84*$D$21 | ... O85: =O84*$D$21 | P85: =SUM(D85:O85) | Q85: =(Q86+Q87)
C86: Total COGS | D86: =D84*$E$21 | E86: =E84*$E$21 | F86: =F84*$E$21 | G86: =G84*$E$21 | H86: =H84*$E$21 | I86: =I84*$E$21 | J86: =J84*$E$21 | K86: =K84*$E$21 | ... O86: =O84*$E$21 | P86: =SUM(D86:O86) | Q86: =IF(P85=0,0,P86/P85)
C87: Total Margin | D87: =D85-D86 | E87: =E85-E86 | F87: =F85-F86 | G87: =G85-G86 | H87: =H85-H86 | I87: =I85-I86 | J87: =J85-J86 | K87: =K85-K86 | ... O87: =O85-O86 | P87: =SUM(D87:O87) | Q87: =IF(P85=0,0,P87/P85)
C89: =C22
C90: Hours Sold | D90: =D175*0.25 | E90: =E175*0.25 | F90: =F175*0.25 | G90: =G175*0.25 | H90: =H175*0.25 | I90: =I175*0.25 | J90: =J175*0.25 | K90: =K175*0.25 | ... O90: =O175*0.25
C91: Total Sales | D91: =D90*$D$22 | E91: =E90*$D$22 | F91: =F90*$D$22 | G91: =G90*$D$22 | H91: =H90*$D$22 | I91: =I90*$D$22 | J91: =J90*$D$22 | K91: =K90*$D$22 | ... O91: =O90*$D$22 | P91: =SUM(D91:O91) | Q91: =(Q92+Q93)
C92: Total COGS | D92: =D90*$E$22 | E92: =E90*$E$22 | F92: =F90*$E$22 | G92: =G90*$E$22 | H92: =H90*$E$22 | I92: =I90*$E$22 | J92: =J90*$E$22 | K92: =K90*$E$22 | ... O92: =O90*$E$22 | P92: =SUM(D92:O92) | Q92: =IF(P91=0,0,P92/P91)
C93: Total Margin | D93: =D91-D92 | E93: =E91-E92 | F93: =F91-F92 | G93: =G91-G92 | H93: =H91-H92 | I93: =I91-I92 | J93: =J91-J92 | K93: =K91-K92 | ... O93: =O91-O92 | P93: =SUM(D93:O93) | Q93: =IF(P91=0,0,P93/P91)
C95: Total Training Consultancy
C96: Total Sales | D96: =D91+D85 | E96: =E91+E85 | F96: =F91+F85 | G96: =G91+G85 | H96: =H91+H85 | I96: =I91+I85 | J96: =J91+J85 | K96: =K91+K85 | ... O96: =O91+O85 | P96: =SUM(D96:O96) | Q96: =(Q97+Q98)
C97: Total COGS | D97: =D92+D86 | E97: =E92+E86 | F97: =F92+F86 | G97: =G92+G86 | H97: =H92+H86 | I97: =I92+I86 | J97: =J92+J86 | K97: =K92+K86 | ... O97: =O92+O86 | P97: =SUM(D97:O97) | Q97: =IF(P96=0,0,P97/P96)
C98: Total Margin | D98: =D96-D97 | E98: =E96-E97 | F98: =F96-F97 | G98: =G96-G97 | H98: =H96-H97 | I98: =I96-I97 | J98: =J96-J97 | K98: =K96-K97 | ... O98: =O96-O97 | P98: =SUM(D98:O98) | Q98: =IF(P96=0,0,P98/P96)
D99: =D76+D69+D62+D55+D48+D41+D34+D27 | E99: =E76+E69+E62+E55+E48+E41+E34+E27 | F99: =F76+F69+F62+F55+F48+F41+F34+F27 | G99: =G76+G69+G62+G55+G48+G41+G34+G27 | H99: =H76+H69+H62+H55+H48+H41+H34+H27 | I99: =I76+I69+I62+I55+I48+I41+I34+I27 | J99: =J76+J69+J62+J55+J48+J41+J34+J27 | K99: =K76+K69+K62+K55+K48+K41+K34+K27 | ... O99: =O76+O69+O62+O55+O48+O41+O34+O27 | T99: Assumptions
C100: Net New | D100: ='Revenue 2026'!O99-D99 | E100: =E99-D99 | F100: =F99-E99 | G100: =G99-F99 | H100: =H99-G99 | I100: =I99-H99 | J100: =J99-I99 | K100: =K99-J99 | L100: =L99-K99 | ... O100: =O99-N99 | T100: work hours
B101: Administrative | C101: =C6 | T101: per new acct
C102: Net New Licences Sold | D102: =D100*$T$102 | E102: =E100*$T$102 | F102: =F100*$T$102 | G102: =G100*$T$102 | H102: =H100*$T$102 | I102: =I100*$T$102 | J102: =J100*$T$102 | K102: =K100*$T$102 | ... O102: =O100*$T$102 | T102: 1
C103: Total Sales | D103: =D102*$D$6 | E103: =E102*$D$6 | F103: =F102*$D$6 | G103: =G102*$D$6 | H103: =H102*$D$6 | I103: =I102*$D$6 | J103: =J102*$D$6 | K103: =K102*$D$6 | ... O103: =O102*$D$6 | P103: =SUM(D103:O103) | Q103: =(Q104+Q105)
C104: Total COGS | D104: =D102*$E$6 | E104: =E102*$E$6 | F104: =F102*$E$6 | G104: =G102*$E$6 | H104: =H102*$E$6 | I104: =I102*$E$6 | J104: =J102*$E$6 | K104: =K102*$E$6 | ... O104: =O102*$E$6 | P104: =SUM(D104:O104) | Q104: =IF(P103=0,0,P104/P103)
C105: Total Margin | D105: =D103-D104 | E105: =E103-E104 | F105: =F103-F104 | G105: =G103-G104 | H105: =H103-H104 | I105: =I103-I104 | J105: =J103-J104 | K105: =K103-K104 | ... O105: =O103-O104 | P105: =SUM(D105:O105) | Q105: =IF(P103=0,0,P105/P103)
C107: =C7
C108: Net New Licences Sold | D108: =D100*$T$108 | E108: =E100*$T$108 | F108: =F100*$T$108 | G108: =G100*$T$108 | H108: =H100*$T$108 | I108: =I100*$T$108 | J108: =J100*$T$108 | K108: =K100*$T$108 | ... O108: =O100*$T$108 | T108: 1
C109: Total Sales | D109: =D108*$D$7 | E109: =E108*$D$7 | F109: =F108*$D$7 | G109: =G108*$D$7 | H109: =H108*$D$7 | I109: =I108*$D$7 | J109: =J108*$D$7 | K109: =K108*$D$7 | ... O109: =O108*$D$7 | P109: =SUM(D109:O109) | Q109: =(Q110+Q111)
C110: Total COGS | D110: =D108*$E$7 | E110: =E108*$E$7 | F110: =F108*$E$7 | G110: =G108*$E$7 | H110: =H108*$E$7 | I110: =I108*$E$7 | J110: =J108*$E$7 | K110: =K108*$E$7 | ... O110: =O108*$E$7 | P110: =SUM(D110:O110) | Q110: =IF(P109=0,0,P110/P109)
C111: Total Margin | D111: =D109-D110 | E111: =E109-E110 | F111: =F109-F110 | G111: =G109-G110 | H111: =H109-H110 | I111: =I109-I110 | J111: =J109-J110 | K111: =K109-K110 | ... O111: =O109-O110 | P111: =SUM(D111:O111) | Q111: =IF(P109=0,0,P111/P109)
C113: =C8
C114: Net New Licences Sold | D114: =D100*$T$114 | E114: =E100*$T$114 | F114: =F100*$T$114 | G114: =G100*$T$114 | H114: =H100*$T$114 | I114: =I100*$T$114 | J114: =J100*$T$114 | K114: =K100*$T$114 | ... O114: =O100*$T$114 | T114: 2
C115: Total Sales | D115: =D114*$D$8 | E115: =E114*$D$8 | F115: =F114*$D$8 | G115: =G114*$D$8 | H115: =H114*$D$8 | I115: =I114*$D$8 | J115: =J114*$D$8 | K115: =K114*$D$8 | ... O115: =O114*$D$8 | P115: =SUM(D115:O115) | Q115: =(Q116+Q117)
...

Sheet Revenue 2028
C3: 2028 | D3: Pricing
C4: Offerings and Distribution | D4: Price | E4: COGS | F4: Margin Per Subscription
C5: Administrative
C6: Configuration | D6: 250 | E6: 50 | F6: =D6-E6
C7: On-Boarding- Administrator | D7: 500 | E7: 100 | F7: =D7-E7
C8: On-Boarding Users | D8: 500 | E8: 100 | F8: =D8-E8
C9: Import | D9: ='Pricing Calcuator'!D86 | E9: 600 | F9: =D9-E9
C10: Support | D10: 100 | E10: 50 | F10: =D10-E10
C11: Industry Break Down | E11: ='COGS Analysis'!D18
C12: Hospitality | D12: 250 | E12: ='Revenue 2030'!$Q$210 | F12: =D12-E12
C13: Hospitality- Reseller | D13: 100 | E13: ='Revenue 2030'!$Q$210 | F13: =D13-E13
C14: Real Estate Development | D14: 450 | E14: ='Revenue 2030'!$Q$210 | F14: =D14-E14
C15: Real Estate Development- Reseller | D15: 250 | E15: ='Revenue 2030'!$Q$210 | F15: =D15-E15
C16: Pharma | D16: 400 | E16: ='Revenue 2030'!$Q$210 | F16: =D16-E16
C17: Pharma- Reseller | D17: 250 | E17: ='Revenue 2030'!$Q$210 | F17: =D17-E17
C18: Start up - Small Firms | D18: 200 | E18: ='Revenue 2030'!$Q$210 | F18: =D18-E18
C19: Start up Reseller | D19: 100 | E19: ='Revenue 2030'!$Q$210 | F19: =D19-E19
C20: Training / Consultancy Training as a Service
C21: Thought Library | D21: 50 | E21: 25 | F21: =D21-E21
C22: Consultancy Services | D22: 225 | E22: 125 | F22: =D22-E22
C24: Segments | D24: January | E24: February | F24: March | G24: April | H24: May | I24: June | J24: July | K24: August | L24: September | M24: October | N24: November | O24: December | P24: Annual Totals | Q24: Profit Margin | R24: Profit margin comparison | S24: CHURN
B26: Hospitality | C26: =C12 | T26: Assumptions
C27: Licences Sold | D27: 750 | E27: 770 | F27: 790 | G27: 800 | H27: 1000 | I27: 1000 | J27: 1100 | K27: 1200 | L27: 1225 | M27: 1250 | N27: 1250 | O27: 1250 | P27: =O27 | S27: 0.03
D28: =D27*$S$27 | E28: =E27*$S$27 | F28: =F27*$S$27 | G28: =G27*$S$27 | H28: =H27*$S$27 | I28: =I27*$S$27 | J28: =J27*$S$27 | K28: =K27*$S$27 | ... O28: =O27*$S$27
C29: Total Sales | D29: =(D27-D28)*$D$12 | E29: =(E27-E28)*$D$12 | F29: =(F27-F28)*$D$12 | G29: =(G27-G28)*$D$12 | H29: =(H27-H28)*$D$12 | I29: =(I27-I28)*$D$12 | J29: =(J27-J28)*$D$12 | K29: =(K27-K28)*$D$12 | ... O29: =(O27-O28)*$D$12 | P29: =SUM(D29:O29) | Q29: =(Q30+Q31)
C30: Total COGS | D30: =D27*$E$12 | E30: =E27*$E$12 | F30: =F27*$E$12 | G30: =G27*$E$12 | H30: =H27*$E$12 | I30: =I27*$E$12 | J30: =J27*$E$12 | K30: =K27*$E$12 | ... O30: =O27*$E$12 | P30: =SUM(D30:O30) | Q30: =IF(P29=0,0,P30/P29)
C31: Total Margin | D31: =D29-D30 | E31: =E29-E30 | F31: =F29-F30 | G31: =G29-G30 | H31: =H29-H30 | I31: =I29-I30 | J31: =J29-J30 | K31: =K29-K30 | ... O31: =O29-O30 | P31: =SUM(D31:O31) | Q31: =IF(P29=0,0,P31/P29)
C33: =C13
C34: Licences Sold | D34: 470 | E34: 500 | F34: 525 | G34: 530 | H34: 535 | I34: 540 | J34: 550 | K34: 560 | L34: 570 | M34: 590 | N34: 600 | O34: 600 | P34: =O34 | S34: 0.03
D35: =D34*$S$34 | E35: =E34*$S$34 | F35: =F34*$S$34 | G35: =G34*$S$34 | H35: =H34*$S$34 | I35: =I34*$S$34 | J35: =J34*$S$34 | K35: =K34*$S$34 | ... O35: =O34*$S$34
C36: Total Sales | D36: =(D34-D35)*$D$13 | E36: =(E34-E35)*$D$13 | F36: =(F34-F35)*$D$13 | G36: =(G34-G35)*$D$13 | H36: =(H34-H35)*$D$13 | I36: =(I34-I35)*$D$13 | J36: =(J34-J35)*$D$13 | K36: =(K34-K35)*$D$13 | ... O36: =(O34-O35)*$D$13 | P36: =SUM(D36:O36) | Q36: =(Q37+Q38)
C37: Total COGS | D37: =D34*$E$13 | E37: =E34*$E$13 | F37: =F34*$E$13 | G37: =G34*$E$13 | H37: =H34*$E$13 | I37: =I34*$E$13 | J37: =J34*$E$13 | K37: =K34*$E$13 | ... O37: =O34*$E$13 | P37: =SUM(D37:O37) | Q37: =IF(P36=0,0,P37/P36)
C38: Total Margin | D38: =D36-D37 | E38: =E36-E37 | F38: =F36-F37 | G38: =G36-G37 | H38: =H36-H37 | I38: =I36-I37 | J38: =J36-J37 | K38: =K36-K37 | ... O38: =O36-O37 | P38: =SUM(D38:O38) | Q38: =IF(P36=0,0,P38/P36)
B40: Real Estate | C40: =C14
C41: Licences Sold | D41: 625 | E41: 625 | F41: 630 | G41: 630 | H41: 630 | I41: 630 | J41: 650 | K41: 650 | L41: 660 | M41: 660 | N41: 660 | O41: 660 | P41: =O41 | S41: 0.03
D42: =D41*$S$41 | E42: =E41*$S$41 | F42: =F41*$S$41 | G42: =G41*$S$41 | H42: =H41*$S$41 | I42: =I41*$S$41 | J42: =J41*$S$41 | K42: =K41*$S$41 | ... O42: =O41*$S$41
C43: Total Sales | D43: =(D41-D42)*$D$14 | E43: =(E41-E42)*$D$14 | F43: =(F41-F42)*$D$14 | G43: =(G41-G42)*$D$14 | H43: =(H41-H42)*$D$14 | I43: =(I41-I42)*$D$14 | J43: =(J41-J42)*$D$14 | K43: =(K41-K42)*$D$14 | ... O43: =(O41-O42)*$D$14 | P43: =SUM(D43:O43) | Q43: =(Q44+Q45)
C44: Total COGS | D44: =D41*$E$14 | E44: =E41*$E$14 | F44: =F41*$E$14 | G44: =G41*$E$14 | H44: =H41*$E$14 | I44: =I41*$E$14 | J44: =J41*$E$14 | K44: =K41*$E$14 | ... O44: =O41*$E$14 | P44: =SUM(D44:O44) | Q44: =IF(P43=0,0,P44/P43)
C45: Total Margin | D45: =D43-D44 | E45: =E43-E44 | F45: =F43-F44 | G45: =G43-G44 | H45: =H43-H44 | I45: =I43-I44 | J45: =J43-J44 | K45: =K43-K44 | ... O45: =O43-O44 | P45: =SUM(D45:O45) | Q45: =IF(P43=0,0,P45/P43)
C47: =C15
C48: Licences Sold | D48: 225 | E48: 230 | F48: 235 | G48: 240 | H48: 240 | I48: 250 | J48: 260 | K48: 270 | L48: 275 | M48: 280 | N48: 280 | O48: 280 | P48: =O48 | S48: 0.03
D49: =D48*$S$48 | E49: =E48*$S$48 | F49: =F48*$S$48 | G49: =G48*$S$48 | H49: =H48*$S$48 | I49: =I48*$S$48 | J49: =J48*$S$48 | K49: =K48*$S$48 | ... O49: =O48*$S$48
C50: Total Sales | D50: =(D48-D49)*$D$15 | E50: =(E48-E49)*$D$15 | F50: =(F48-F49)*$D$15 | G50: =(G48-G49)*$D$15 | H50: =(H48-H49)*$D$15 | I50: =(I48-I49)*$D$15 | J50: =(J48-J49)*$D$15 | K50: =(K48-K49)*$D$15 | ... O50: =(O48-O49)*$D$15 | P50: =SUM(D50:O50) | Q50: =(Q51+Q52)
C51: Total COGS | D51: =D48*$E$15 | E51: =E48*$E$15 | F51: =F48*$E$15 | G51: =G48*$E$15 | H51: =H48*$E$15 | I51: =I48*$E$15 | J51: =J48*$E$15 | K51: =K48*$E$15 | ... O51: =O48*$E$15 | P51: =SUM(D51:O51) | Q51: =IF(P50=0,0,P51/P50)
C52: Total Margin | D52: =D50-D51 | E52: =E50-E51 | F52: =F50-F51 | G52: =G50-G51 | H52: =H50-H51 | I52: =I50-I51 | J52: =J50-J51 | K52: =K50-K51 | ... O52: =O50-O51 | P52: =SUM(D52:O52) | Q52: =IF(P50=0,0,P52/P50)
B54: Pharma | C54: =C16
C55: Licences Sold | D55: 200 | E55: 225 | F55: 230 | G55: 240 | H55: 245 | I55: 250 | J55: 255 | K55: 260 | L55: 265 | M55: 275 | N55: 280 | O55: 285 | P55: =O55 | S55: 0.03
D56: =D55*$S$55 | E56: =E55*$S$55 | F56: =F55*$S$55 | G56: =G55*$S$55 | H56: =H55*$S$55 | I56: =I55*$S$55 | J56: =J55*$S$55 | K56: =K55*$S$55 | ... O56: =O55*$S$55
C57: Total Sales | D57: =(D55-D56)*$D$16 | E57: =(E55-E56)*$D$16 | F57: =(F55-F56)*$D$16 | G57: =(G55-G56)*$D$16 | H57: =(H55-H56)*$D$16 | I57: =(I55-I56)*$D$16 | J57: =(J55-J56)*$D$16 | K57: =(K55-K56)*$D$16 | ... O57: =(O55-O56)*$D$16 | P57: =SUM(D57:O57) | Q57: =(Q58+Q59)
C58: Total COGS | D58: =D55*$E$16 | E58: =E55*$E$16 | F58: =F55*$E$16 | G58: =G55*$E$16 | H58: =H55*$E$16 | I58: =I55*$E$16 | J58: =J55*$E$16 | K58: =K55*$E$16 | ... O58: =O55*$E$16 | P58: =SUM(D58:O58) | Q58: =IF(P57=0,0,P58/P57)
C59: Total Margin | D59: =D57-D58 | E59: =E57-E58 | F59: =F57-F58 | G59: =G57-G58 | H59: =H57-H58 | I59: =I57-I58 | J59: =J57-J58 | K59: =K57-K58 | ... O59: =O57-O58 | P59: =SUM(D59:O59) | Q59: =IF(P57=0,0,P59/P57)
C61: =C17
C62: Licences Sold | D62: 10 | E62: 10 | F62: 25 | G62: 30 | H62: 35 | I62: 40 | J62: 40 | K62: 40 | L62: 40 | M62: 45 | N62: 50 | O62: 50 | P62: =O62 | S62: 0.03
D63: =D62*$S$62 | E63: =E62*$S$62 | F63: =F62*$S$62 | G63: =G62*$S$62 | H63: =H62*$S$62 | I63: =I62*$S$62 | J63: =J62*$S$62 | K63: =K62*$S$62 | ... O63: =O62*$S$62
C64: Total Sales | D64: =(D62-D63)*$D$17 | E64: =(E62-E63)*$D$17 | F64: =(F62-F63)*$D$17 | G64: =(G62-G63)*$D$17 | H64: =(H62-H63)*$D$17 | I64: =(I62-I63)*$D$17 | J64: =(J62-J63)*$D$17 | K64: =(K62-K63)*$D$17 | ... O64: =(O62-O63)*$D$17 | P64: =SUM(D64:O64) | Q64: =(Q65+Q66)
C65: Total COGS | D65: =D62*$E$17 | E65: =E62*$E$17 | F65: =F62*$E$17 | G65: =G62*$E$17 | H65: =H62*$E$17 | I65: =I62*$E$17 | J65: =J62*$E$17 | K65: =K62*$E$17 | ... O65: =O62*$E$17 | P65: =SUM(D65:O65) | Q65: =IF(P64=0,0,P65/P64)
C66: Total Margin | D66: =D64-D65 | E66: =E64-E65 | F66: =F64-F65 | G66: =G64-G65 | H66: =H64-H65 | I66: =I64-I65 | J66: =J64-J65 | K66: =K64-K65 | ... O66: =O64-O65 | P66: =SUM(D66:O66) | Q66: =IF(P64=0,0,P66/P64)
B68: Start ups | C68: =C18
C69: Licences Sold | D69: 320 | E69: 325 | F69: 330 | G69: 335 | H69: 340 | I69: 350 | J69: 360 | K69: 375 | L69: 380 | M69: 390 | N69: 400 | O69: 410 | P69: =O69 | S69: 0.05
D70: =D69*$S$69 | E70: =E69*$S$69 | F70: =F69*$S$69 | G70: =G69*$S$69 | H70: =H69*$S$69 | I70: =I69*$S$69 | J70: =J69*$S$69 | K70: =K69*$S$69 | ... O70: =O69*$S$69
C71: Total Sales | D71: =(D69-D70)*$D$18 | E71: =(E69-E70)*$D$18 | F71: =(F69-F70)*$D$18 | G71: =(G69-G70)*$D$18 | H71: =(H69-H70)*$D$18 | I71: =(I69-I70)*$D$18 | J71: =(J69-J70)*$D$18 | K71: =(K69-K70)*$D$18 | ... O71: =(O69-O70)*$D$18 | P71: =SUM(D71:O71) | Q71: =(Q72+Q73)
C72: Total COGS | D72: =D69*$E$18 | E72: =E69*$E$18 | F72: =F69*$E$18 | G72: =G69*$E$18 | H72: =H69*$E$18 | I72: =I69*$E$18 | J72: =J69*$E$18 | K72: =K69*$E$18 | ... O72: =O69*$E$18 | P72: =SUM(D72:O72) | Q72: =IF(P71=0,0,P72/P71)
C73: Total Margin | D73: =D71-D72 | E73: =E71-E72 | F73: =F71-F72 | G73: =G71-G72 | H73: =H71-H72 | I73: =I71-I72 | J73: =J71-J72 | K73: =K71-K72 | ... O73: =O71-O72 | P73: =SUM(D73:O73) | Q73: =IF(P71=0,0,P73/P71)
C75: =C19
C76: Licences Sold | D76: 0 | E76: 0 | F76: 0 | G76: 0 | H76: 0 | I76: 0 | J76: 0 | K76: 0 | L76: 0 | M76: 0 | N76: 0 | O76: 0 | P76: =O76 | S76: 0.05
D77: =D76*$S$76 | E77: =E76*$S$76 | F77: =F76*$S$76 | G77: =G76*$S$76 | H77: =H76*$S$76 | I77: =I76*$S$76 | J77: =J76*$S$76 | K77: =K76*$S$76 | ... O77: =O76*$S$76
C78: Total Sales | D78: =(D76-D77)*$D$19 | E78: =(E76-E77)*$D$19 | F78: =(F76-F77)*$D$19 | G78: =(G76-G77)*$D$19 | H78: =(H76-H77)*$D$19 | I78: =(I76-I77)*$D$19 | J78: =(J76-J77)*$D$19 | K78: =(K76-K77)*$D$19 | ... O78: =(O76-O77)*$D$19 | P78: =SUM(D78:O78) | Q78: =(Q79+Q80)
C79: Total COGS | D79: =D76*$E$19 | E79: =E76*$E$19 | F79: =F76*$E$19 | G79: =G76*$E$19 | H79: =H76*$E$19 | I79: =I76*$E$19 | J79: =J76*$E$19 | K79: =K76*$E$19 | ... O79: =O76*$E$19 | P79: =SUM(D79:O79) | Q79: =IF(P78=0,0,P79/P78)
C80: Total Margin | D80: =D78-D79 | E80: =E78-E79 | F80: =F78-F79 | G80: =G78-G79 | H80: =H78-H79 | I80: =I78-I79 | J80: =J78-J79 | K80: =K78-K79 | ... O80: =O78-O79 | P80: =SUM(D80:O80) | Q80: =IF(P78=0,0,P80/P78)
B83: Consultancy / Training | C83: =C21
C84: Access Sold | D84: =D174*0.35 | E84: =E174*0.35 | F84: =F174*0.35 | G84: =G174*0.35 | H84: =H174*0.35 | I84: =I174*0.35 | J84: =J174*0.35 | K84: =K174*0.35 | ... O84: =O174*0.35
C85: Total Sales | D85: =D84*$D$21 | E85: =E84*$D$21 | F85: =F84*$D$21 | G85: =G84*$D$21 | H85: =H84*$D$21 | I85: =I84*$D$21 | J85: =J84*$D$21 | K85: =K84*$D$21 | ... O85: =O84*$D$21 | P85: =SUM(D85:O85) | Q85: =(Q86+Q87)
C86: Total COGS | D86: =D84*$E$21 | E86: =E84*$E$21 | F86: =F84*$E$21 | G86: =G84*$E$21 | H86: =H84*$E$21 | I86: =I84*$E$21 | J86: =J84*$E$21 | K86: =K84*$E$21 | ... O86: =O84*$E$21 | P86: =SUM(D86:O86) | Q86: =IF(P85=0,0,P86/P85)
C87: Total Margin | D87: =D85-D86 | E87: =E85-E86 | F87: =F85-F86 | G87: =G85-G86 | H87: =H85-H86 | I87: =I85-I86 | J87: =J85-J86 | K87: =K85-K86 | ... O87: =O85-O86 | P87: =SUM(D87:O87) | Q87: =IF(P85=0,0,P87/P85)
C89: =C22
C90: Hours Sold | D90: =D174*0.25 | E90: =E174*0.25 | F90: =F174*0.25 | G90: =G174*0.25 | H90: =H174*0.25 | I90: =I174*0.25 | J90: =J174*0.25 | K90: =K174*0.25 | ... O90: =O174*0.25
C91: Total Sales | D91: =D90*$D$22 | E91: =E90*$D$22 | F91: =F90*$D$22 | G91: =G90*$D$22 | H91: =H90*$D$22 | I91: =I90*$D$22 | J91: =J90*$D$22 | K91: =K90*$D$22 | ... O91: =O90*$D$22 | P91: =SUM(D91:O91) | Q91: =(Q92+Q93)
C92: Total COGS | D92: =D90*$E$22 | E92: =E90*$E$22 | F92: =F90*$E$22 | G92: =G90*$E$22 | H92: =H90*$E$22 | I92: =I90*$E$22 | J92: =J90*$E$22 | K92: =K90*$E$22 | ... O92: =O90*$E$22 | P92: =SUM(D92:O92) | Q92: =IF(P91=0,0,P92/P91)
C93: Total Margin | D93: =D91-D92 | E93: =E91-E92 | F93: =F91-F92 | G93: =G91-G92 | H93: =H91-H92 | I93: =I91-I92 | J93: =J91-J92 | K93: =K91-K92 | ... O93: =O91-O92 | P93: =SUM(D93:O93) | Q93: =IF(P91=0,0,P93/P91)
C95: Total Training Consultancy
C96: Total Sales | D96: =D91+D85 | E96: =E91+E85 | F96: =F91+F85 | G96: =G91+G85 | H96: =H91+H85 | I96: =I91+I85 | J96: =J91+J85 | K96: =K91+K85 | ... O96: =O91+O85 | P96: =SUM(D96:O96) | Q96: =(Q97+Q98)
C97: Total COGS | D97: =D92+D86 | E97: =E92+E86 | F97: =F92+F86 | G97: =G92+G86 | H97: =H92+H86 | I97: =I92+I86 | J97: =J92+J86 | K97: =K92+K86 | ... O97: =O92+O86 | P97: =SUM(D97:O97) | Q97: =IF(P96=0,0,P97/P96)
C98: Total Margin | D98: =D96-D97 | E98: =E96-E97 | F98: =F96-F97 | G98: =G96-G97 | H98: =H96-H97 | I98: =I96-I97 | J98: =J96-J97 | K98: =K96-K97 | ... O98: =O96-O97 | P98: =SUM(D98:O98) | Q98: =IF(P96=0,0,P98/P96)
D99: =D76+D69+D62+D55+D48+D41+D34+D27 | E99: =E76+E69+E62+E55+E48+E41+E34+E27 | F99: =F76+F69+F62+F55+F48+F41+F34+F27 | G99: =G76+G69+G62+G55+G48+G41+G34+G27 | H99: =H76+H69+H62+H55+H48+H41+H34+H27 | I99: =I76+I69+I62+I55+I48+I41+I34+I27 | J99: =J76+J69+J62+J55+J48+J41+J34+J27 | K99: =K76+K69+K62+K55+K48+K41+K34+K27 | ... O99: =O76+O69+O62+O55+O48+O41+O34+O27 | T99: Assumptions
C100: Net New | D100: =D99-'Revenue 2027'!O99 | E100: =E99-D99 | F100: =F99-E99 | G100: =G99-F99 | H100: =H99-G99 | I100: =I99-H99 | J100: =J99-I99 | K100: =K99-J99 | L100: =L99-K99 | ... O100: =O99-N99 | T100: work hours
B101: Administrative | C101: Net New Licences Sold | D101: =D100*$T$102 | E101: =E100*$T$102 | F101: =F100*$T$102 | G101: =G100*$T$102 | H101: =H100*$T$102 | I101: =I100*$T$102 | J101: =J100*$T$102 | K101: =K100*$T$102 | ... O101: =O100*$T$102 | T101: per new acct
C102: Total Sales | D102: =D101*$D$6 | E102: =E101*$D$6 | F102: =F101*$D$6 | G102: =G101*$D$6 | H102: =H101*$D$6 | I102: =I101*$D$6 | J102: =J101*$D$6 | K102: =K101*$D$6 | ... O102: =O101*$D$6 | P102: =SUM(D102:O102) | Q102: =(Q103+Q104) | T102: 1
C103: Total COGS | D103: =D101*$E$6 | E103: =E101*$E$6 | F103: =F101*$E$6 | G103: =G101*$E$6 | H103: =H101*$E$6 | I103: =I101*$E$6 | J103: =J101*$E$6 | K103: =K101*$E$6 | ... O103: =O101*$E$6 | P103: =SUM(D103:O103) | Q103: =IF(P102=0,0,P103/P102)
C104: Total Margin | D104: =D102-D103 | E104: =E102-E103 | F104: =F102-F103 | G104: =G102-G103 | H104: =H102-H103 | I104: =I102-I103 | J104: =J102-J103 | K104: =K102-K103 | ... O104: =O102-O103 | P104: =SUM(D104:O104) | Q104: =IF(P102=0,0,P104/P102)
C106: =C6
C107: Net New Licences Sold | D107: =D100*$T$108 | E107: =E100*$T$108 | F107: =F100*$T$108 | G107: =G100*$T$108 | H107: =H100*$T$108 | I107: =I100*$T$108 | J107: =J100*$T$108 | K107: =K100*$T$108 | ... O107: =O100*$T$108
C108: Total Sales | D108: =D107*$D$7 | E108: =E107*$D$7 | F108: =F107*$D$7 | G108: =G107*$D$7 | H108: =H107*$D$7 | I108: =I107*$D$7 | J108: =J107*$D$7 | K108: =K107*$D$7 | ... O108: =O107*$D$7 | P108: =SUM(D108:O108) | Q108: =(Q109+Q110) | T108: 1
C109: Total COGS | D109: =D107*$E$7 | E109: =E107*$E$7 | F109: =F107*$E$7 | G109: =G107*$E$7 | H109: =H107*$E$7 | I109: =I107*$E$7 | J109: =J107*$E$7 | K109: =K107*$E$7 | ... O109: =O107*$E$7 | P109: =SUM(D109:O109) | Q109: =IF(P108=0,0,P109/P108)
C110: Total Margin | D110: =D108-D109 | E110: =E108-E109 | F110: =F108-F109 | G110: =G108-G109 | H110: =H108-H109 | I110: =I108-I109 | J110: =J108-J109 | K110: =K108-K109 | ... O110: =O108-O109 | P110: =SUM(D110:O110) | Q110: =IF(P108=0,0,P110/P108)
C112: =C7
C113: Net New Licences Sold | D113: =D100*$T$114 | E113: =E100*$T$114 | F113: =F100*$T$114 | G113: =G100*$T$114 | H113: =H100*$T$114 | I113: =I100*$T$114 | J113: =J100*$T$114 | K113: =K100*$T$114 | ... O113: =O100*$T$114
C114: Total Sales | D114: =D113*$D$8 | E114: =E113*$D$8 | F114: =F113*$D$8 | G114: =G113*$D$8 | H114: =H113*$D$8 | I114: =I113*$D$8 | J114: =J113*$D$8 | K114: =K113*$D$8 | ... O114: =O113*$D$8 | P114: =SUM(D114:O114) | Q114: =(Q115+Q116) | T114: 2
C115: Total COGS | D115: =D113*$E$8 | E115: =E113*$E$8 | F115: =F113*$E$8 | G115: =G113*$E$8 | H115: =H113*$E$8 | I115: =I113*$E$8 | J115: =J113*$E$8 | K115: =K113*$E$8 | ... O115: =O113*$E$8 | P115: =SUM(D115:O115) | Q115: =IF(P114=0,0,P115/P114)
C116: Total Margin | D116: =D114-D115 | E116: =E114-E115 | F116: =F114-F115 | G116: =G114-G115 | H116: =H114-H115 | I116: =I114-I115 | J116: =J114-J115 | K116: =K114-K115 | ... O116: =O114-O115 | P116: =SUM(D116:O116) | Q116: =IF(P114=0,0,P116/P114)
C118: =C8
...

Sheet Revenue 2029
C3: 2029 | D3: Pricing
C4: Offerings and Distribution | D4: Price | E4: COGS | F4: Margin Per Subscription
C5: Administrative
C6: Configuration | D6: 250 | E6: 50 | F6: =D6-E6
C7: On-Boarding- Administrator | D7: ='Pricing Calcuator'!D79 | E7: 100 | F7: =D7-E7
C8: On-Boarding Users | D8: ='Pricing Calcuator'!D82 | E8: 100 | F8: =D8-E8
C9: Import | D9: ='Pricing Calcuator'!D86 | E9: 600 | F9: =D9-E9
C10: Support | D10: 100 | E10: ='COGS Analysis'!D18 | F10: =D10-E10
C11: Industry Break Down | E11: ='COGS Analysis'!D18
C12: ='Pricing Calcuator'!C7 | D12: ='Pricing Calcuator'!D7 | E12: ='Revenue 2030'!$Q$210 | F12: =D12-E12
C13: ='Pricing Calcuator'!C8 | D13: 200 | E13: ='Revenue 2030'!$Q$210 | F13: =D13-E13
C14: ='Pricing Calcuator'!C9 | D14: ='Pricing Calcuator'!D9 | E14: ='Revenue 2030'!$Q$210 | F14: =D14-E14
C15: ='Pricing Calcuator'!C10 | D15: ='Pricing Calcuator'!D10 | E15: ='Revenue 2030'!$Q$210 | F15: =D15-E15
C16: ='Pricing Calcuator'!C11 | D16: ='Pricing Calcuator'!D11 | E16: ='Revenue 2030'!$Q$210 | F16: =D16-E16
C17: ='Pricing Calcuator'!C12 | D17: ='Pricing Calcuator'!D12 | E17: ='Revenue 2030'!$Q$210 | F17: =D17-E17
C18: ='Pricing Calcuator'!C13 | D18: ='Pricing Calcuator'!D13 | E18: ='Revenue 2030'!$Q$210 | F18: =D18-E18
C19: ='Pricing Calcuator'!C14 | D19: ='Pricing Calcuator'!D14 | E19: ='Revenue 2030'!$Q$210 | F19: =D19-E19
C20: Training / Consultancy Training as a Service
C21: Thought Library | D21: ='Pricing Calcuator'!D90 | E21: 25 | F21: =D21-E21
C22: Consultancy Services | D22: ='Pricing Calcuator'!D93 | E22: 125 | F22: =D22-E22
C24: Segments | D24: January | E24: February | F24: March | G24: April | H24: May | I24: June | J24: July | K24: August | L24: September | M24: October | N24: November | O24: December | P24: Annual Totals | Q24: Profit Margin | R24: Profit margin comparison | S24: CHURN
B26: Hospitality | C26: =C12
C27: Licenses Sold | D27: 1250 | E27: 1280 | F27: 1325 | G27: 1378 | H27: 1400 | I27: 1450 | J27: 1475 | K27: 1500 | L27: 1525 | M27: 1530 | N27: 1550 | O27: 1560 | P27: =O27 | S27: 0.03 | T27: Assumptions
D28: =D27*$S$27 | E28: =E27*$S$27 | F28: =F27*$S$27 | G28: =G27*$S$27 | H28: =H27*$S$27 | I28: =I27*$S$27 | J28: =J27*$S$27 | K28: =K27*$S$27 | ... O28: =O27*$S$27
C29: Total Sales | D29: =(D27-D28)*$D$12 | E29: =(E27-E28)*$D$12 | F29: =(F27-F28)*$D$12 | G29: =(G27-G28)*$D$12 | H29: =(H27-H28)*$D$12 | I29: =(I27-I28)*$D$12 | J29: =(J27-J28)*$D$12 | K29: =(K27-K28)*$D$12 | ... O29: =(O27-O28)*$D$12 | P29: =SUM(D29:O29) | Q29: =(Q30+Q31)
C30: Total COGS | D30: =D27*$E$12 | E30: =E27*$E$12 | F30: =F27*$E$12 | G30: =G27*$E$12 | H30: =H27*$E$12 | I30: =I27*$E$12 | J30: =J27*$E$12 | K30: =K27*$E$12 | ... O30: =O27*$E$12 | P30: =SUM(D30:O30) | Q30: =IF(P29=0,0,P30/P29) | T30: t Additonal Sales person for flex
C31: Total Margin | D31: =D29-D30 | E31: =E29-E30 | F31: =F29-F30 | G31: =G29-G30 | H31: =H29-H30 | I31: =I29-I30 | J31: =J29-J30 | K31: =K29-K30 | ... O31: =O29-O30 | P31: =SUM(D31:O31) | Q31: =IF(P29=0,0,P31/P29)
C33: =C13
C34: Licences Sold | D34: 600 | E34: 610 | F34: 625 | G34: 675 | H34: 685 | I34: 690 | J34: 700 | K34: 715 | L34: 725 | M34: 735 | N34: 745 | O34: 750 | P34: =O34 | S34: 0.03
D35: =D34*$S$27 | E35: =E34*$S$27 | F35: =F34*$S$27 | G35: =G34*$S$27 | H35: =H34*$S$27 | I35: =I34*$S$27 | J35: =J34*$S$27 | K35: =K34*$S$27 | ... O35: =O34*$S$27
C36: Total Sales | D36: =(D34-D35)*$D$13 | E36: =(E34-E35)*$D$13 | F36: =(F34-F35)*$D$13 | G36: =(G34-G35)*$D$13 | H36: =(H34-H35)*$D$13 | I36: =(I34-I35)*$D$13 | J36: =(J34-J35)*$D$13 | K36: =(K34-K35)*$D$13 | ... O36: =(O34-O35)*$D$13 | P36: =SUM(D36:O36) | Q36: =(Q37+Q38)
C37: Total COGS | D37: =D34*$E$13 | E37: =E34*$E$13 | F37: =F34*$E$13 | G37: =G34*$E$13 | H37: =H34*$E$13 | I37: =I34*$E$13 | J37: =J34*$E$13 | K37: =K34*$E$13 | ... O37: =O34*$E$13 | P37: =SUM(D37:O37) | Q37: =IF(P36=0,0,P37/P36)
C38: Total Margin | D38: =D36-D37 | E38: =E36-E37 | F38: =F36-F37 | G38: =G36-G37 | H38: =H36-H37 | I38: =I36-I37 | J38: =J36-J37 | K38: =K36-K37 | ... O38: =O36-O37 | P38: =SUM(D38:O38) | Q38: =IF(P36=0,0,P38/P36)
B40: Real Estate | C40: =C14
C41: Licences Sold | D41: 660 | E41: 670 | F41: 680 | G41: 690 | H41: 700 | I41: 710 | J41: 720 | K41: 730 | L41: 740 | M41: 750 | N41: 750 | O41: 750 | P41: =O41 | S41: 0.03
D42: =D41*S41 | E42: =E41*$S$41 | F42: =F41*$S$41 | G42: =G41*$S$41 | H42: =H41*$S$41 | I42: =I41*$S$41 | J42: =J41*$S$41 | K42: =K41*$S$41 | L42: =L41*$S$41 | ... O42: =O41*$S$41
C43: Total Sales | D43: =(D41-D42)*$D$14 | E43: =(E41-E42)*$D$14 | F43: =(F41-F42)*$D$14 | G43: =(G41-G42)*$D$14 | H43: =(H41-H42)*$D$14 | I43: =(I41-I42)*$D$14 | J43: =(J41-J42)*$D$14 | K43: =(K41-K42)*$D$14 | ... O43: =(O41-O42)*$D$14 | P43: =SUM(D43:O43) | Q43: =(Q44+Q45)
C44: Total COGS | D44: =D41*$E$14 | E44: =E41*$E$14 | F44: =F41*$E$14 | G44: =G41*$E$14 | H44: =H41*$E$14 | I44: =I41*$E$14 | J44: =J41*$E$14 | K44: =K41*$E$14 | ... O44: =O41*$E$14 | P44: =SUM(D44:O44) | Q44: =IF(P43=0,0,P44/P43)
C45: Total Margin | D45: =D43-D44 | E45: =E43-E44 | F45: =F43-F44 | G45: =G43-G44 | H45: =H43-H44 | I45: =I43-I44 | J45: =J43-J44 | K45: =K43-K44 | ... O45: =O43-O44 | P45: =SUM(D45:O45) | Q45: =IF(P43=0,0,P45/P43)
C47: =C15
C48: Licences Sold | D48: 280 | E48: 280 | F48: 300 | G48: 305 | H48: 310 | I48: 315 | J48: 320 | K48: 325 | L48: 340 | M48: 350 | N48: 305 | O48: 350 | P48: =O48 | S48: 0.03
D49: =D48*$S$48 | E49: =E48*T48 | F49: =F48*U48 | G49: =G48*V48 | H49: =H48*W48 | I49: =I48*X48 | J49: =J48*Y48 | K49: =K48*Z48 | L49: =L48*AA48 | ... O49: =O48*AD48
C50: Total Sales | D50: =(D48-D49)*$D$15 | E50: =(E48-E49)*$D$15 | F50: =(F48-F49)*$D$15 | G50: =(G48-G49)*$D$15 | H50: =(H48-H49)*$D$15 | I50: =(I48-I49)*$D$15 | J50: =(J48-J49)*$D$15 | K50: =(K48-K49)*$D$15 | ... O50: =(O48-O49)*$D$15 | P50: =SUM(D50:O50) | Q50: =(Q51+Q52)
C51: Total COGS | D51: =D48*$E$15 | E51: =E48*$E$15 | F51: =F48*$E$15 | G51: =G48*$E$15 | H51: =H48*$E$15 | I51: =I48*$E$15 | J51: =J48*$E$15 | K51: =K48*$E$15 | ... O51: =O48*$E$15 | P51: =SUM(D51:O51) | Q51: =IF(P50=0,0,P51/P50)
C52: Total Margin | D52: =D50-D51 | E52: =E50-E51 | F52: =F50-F51 | G52: =G50-G51 | H52: =H50-H51 | I52: =I50-I51 | J52: =J50-J51 | K52: =K50-K51 | ... O52: =O50-O51 | P52: =SUM(D52:O52) | Q52: =IF(P50=0,0,P52/P50)
B54: Pharma | C54: =C16
C55: Licences Sold | D55: 285 | E55: 310 | F55: 325 | G55: 360 | H55: 375 | I55: 380 | J55: 390 | K55: 400 | L55: 410 | M55: 425 | N55: 435 | O55: 445 | P55: =O55 | S55: 0.03
D56: =D55*$S$55 | E56: =E55*$S$55 | F56: =F55*$S$55 | G56: =G55*$S$55 | H56: =H55*$S$55 | I56: =I55*$S$55 | J56: =J55*$S$55 | K56: =K55*$S$55 | ... O56: =O55*$S$55
C57: Total Sales | D57: =(D55-D56)*$D$16 | E57: =(E55-E56)*$D$16 | F57: =(F55-F56)*$D$16 | G57: =(G55-G56)*$D$16 | H57: =(H55-H56)*$D$16 | I57: =(I55-I56)*$D$16 | J57: =(J55-J56)*$D$16 | K57: =(K55-K56)*$D$16 | ... O57: =(O55-O56)*$D$16 | P57: =SUM(D57:O57) | Q57: =(Q58+Q59)
C58: Total COGS | D58: =D55*$E$16 | E58: =E55*$E$16 | F58: =F55*$E$16 | G58: =G55*$E$16 | H58: =H55*$E$16 | I58: =I55*$E$16 | J58: =J55*$E$16 | K58: =K55*$E$16 | ... O58: =O55*$E$16 | P58: =SUM(D58:O58) | Q58: =IF(P57=0,0,P58/P57)
C59: Total Margin | D59: =D57-D58 | E59: =E57-E58 | F59: =F57-F58 | G59: =G57-G58 | H59: =H57-H58 | I59: =I57-I58 | J59: =J57-J58 | K59: =K57-K58 | ... O59: =O57-O58 | P59: =SUM(D59:O59) | Q59: =IF(P57=0,0,P59/P57)
C61: =C17
C62: Licences Sold | D62: 50 | E62: 50 | F62: 60 | G62: 65 | H62: 70 | I62: 75 | J62: 80 | K62: 85 | L62: 90 | M62: 95 | N62: 100 | O62: 110 | P62: =O62 | S62: 0.03
D63: =D62*$S$62 | E63: =E62*$S$62 | F63: =F62*$S$62 | G63: =G62*$S$62 | H63: =H62*$S$62 | I63: =I62*$S$62 | J63: =J62*$S$62 | K63: =K62*$S$62 | ... O63: =O62*$S$62
C64: Total Sales | D64: =(D62-D63)*$D$17 | E64: =(E62-E63)*$D$17 | F64: =(F62-F63)*$D$17 | G64: =(G62-G63)*$D$17 | H64: =(H62-H63)*$D$17 | I64: =(I62-I63)*$D$17 | J64: =(J62-J63)*$D$17 | K64: =(K62-K63)*$D$17 | ... O64: =(O62-O63)*$D$17 | P64: =SUM(D64:O64) | Q64: =(Q65+Q66)
C65: Total COGS | D65: =D62*$E$17 | E65: =E62*$E$17 | F65: =F62*$E$17 | G65: =G62*$E$17 | H65: =H62*$E$17 | I65: =I62*$E$17 | J65: =J62*$E$17 | K65: =K62*$E$17 | ... O65: =O62*$E$17 | P65: =SUM(D65:O65) | Q65: =IF(P64=0,0,P65/P64)
C66: Total Margin | D66: =D64-D65 | E66: =E64-E65 | F66: =F64-F65 | G66: =G64-G65 | H66: =H64-H65 | I66: =I64-I65 | J66: =J64-J65 | K66: =K64-K65 | ... O66: =O64-O65 | P66: =SUM(D66:O66) | Q66: =IF(P64=0,0,P66/P64)
B68: Start ups | C68: =C18
C69: Licences Sold | D69: 410 | E69: 420 | F69: 425 | G69: 435 | H69: 440 | I69: 445 | J69: 450 | K69: 460 | L69: 465 | M69: 470 | N69: 480 | O69: 490 | P69: =O69 | S69: 0.05
D70: =D69*$S$69 | E70: =E69*$S$69 | F70: =F69*$S$69 | G70: =G69*$S$69 | H70: =H69*$S$69 | I70: =I69*$S$69 | J70: =J69*$S$69 | K70: =K69*$S$69 | ... O70: =O69*$S$69
C71: Total Sales | D71: =(D69-D70)*$D$18 | E71: =(E69-E70)*$D$18 | F71: =(F69-F70)*$D$18 | G71: =(G69-G70)*$D$18 | H71: =(H69-H70)*$D$18 | I71: =(I69-I70)*$D$18 | J71: =(J69-J70)*$D$18 | K71: =(K69-K70)*$D$18 | ... O71: =(O69-O70)*$D$18 | P71: =SUM(D71:O71) | Q71: =(Q72+Q73)
C72: Total COGS | D72: =D69*$E$18 | E72: =E69*$E$18 | F72: =F69*$E$18 | G72: =G69*$E$18 | H72: =H69*$E$18 | I72: =I69*$E$18 | J72: =J69*$E$18 | K72: =K69*$E$18 | ... O72: =O69*$E$18 | P72: =SUM(D72:O72) | Q72: =IF(P71=0,0,P72/P71)
C73: Total Margin | D73: =D71-D72 | E73: =E71-E72 | F73: =F71-F72 | G73: =G71-G72 | H73: =H71-H72 | I73: =I71-I72 | J73: =J71-J72 | K73: =K71-K72 | ... O73: =O71-O72 | P73: =SUM(D73:O73) | Q73: =IF(P71=0,0,P73/P71)
C75: =C19
C76: Licences Sold | K76: 0 | L76: 0 | M76: 0 | N76: 0 | O76: 0 | P76: =O76 | S76: 0.05
D77: =D76*$S$76 | E77: =E76*$S$76 | F77: =F76*$S$76 | G77: =G76*$S$76 | H77: =H76*$S$76 | I77: =I76*$S$76 | J77: =J76*$S$76 | K77: =K76*$S$76 | ... O77: =O76*$S$76
C78: Total Sales | D78: =(D76-D77)*$D$19 | E78: =(E76-E77)*$D$19 | F78: =(F76-F77)*$D$19 | G78: =(G76-G77)*$D$19 | H78: =(H76-H77)*$D$19 | I78: =(I76-I77)*$D$19 | J78: =(J76-J77)*$D$19 | K78: =(K76-K77)*$D$19 | ... O78: =(O76-O77)*$D$19 | P78: =SUM(D78:O78) | Q78: =(Q79+Q80)
C79: Total COGS | D79: =D76*$E$19 | E79: =E76*$E$19 | F79: =F76*$E$19 | G79: =G76*$E$19 | H79: =H76*$E$19 | I79: =I76*$E$19 | J79: =J76*$E$19 | K79: =K76*$E$19 | ... O79: =O76*$E$19 | P79: =SUM(D79:O79) | Q79: =IF(P78=0,0,P79/P78)
C80: Total Margin | D80: =D78-D79 | E80: =E78-E79 | F80: =F78-F79 | G80: =G78-G79 | H80: =H78-H79 | I80: =I78-I79 | J80: =J78-J79 | K80: =K78-K79 | ... O80: =O78-O79 | P80: =SUM(D80:O80) | Q80: =IF(P78=0,0,P80/P78)
B83: Consultancy / Training | C83: =C21
C84: Access sold | D84: =D175*0.35 | E84: =E175*0.35 | F84: =F175*0.35 | G84: =G175*0.35 | H84: =H175*0.35 | I84: =I175*0.35 | J84: =J175*0.35 | K84: =K175*0.35 | ... O84: =O175*0.35
C85: Total Sales | D85: =D84*$D$21 | E85: =E84*$D$21 | F85: =F84*$D$21 | G85: =G84*$D$21 | H85: =H84*$D$21 | I85: =I84*$D$21 | J85: =J84*$D$21 | K85: =K84*$D$21 | ... O85: =O84*$D$21 | P85: =SUM(D85:O85) | Q85: =(Q86+Q87)
C86: Total COGS | D86: =D84*$E$21 | E86: =E84*$E$21 | F86: =F84*$E$21 | G86: =G84*$E$21 | H86: =H84*$E$21 | I86: =I84*$E$21 | J86: =J84*$E$21 | K86: =K84*$E$21 | ... O86: =O84*$E$21 | P86: =SUM(D86:O86) | Q86: =IF(P85=0,0,P86/P85)
C87: Total Margin | D87: =D85-D86 | E87: =E85-E86 | F87: =F85-F86 | G87: =G85-G86 | H87: =H85-H86 | I87: =I85-I86 | J87: =J85-J86 | K87: =K85-K86 | ... O87: =O85-O86 | P87: =SUM(D87:O87) | Q87: =IF(P85=0,0,P87/P85)
C89: =C22
C90: Hours Sold | D90: =D175*0.25 | E90: =E175*0.25 | F90: =F175*0.25 | G90: =G175*0.25 | H90: =H175*0.25 | I90: =I175*0.25 | J90: =J175*0.25 | K90: =K175*0.25 | ... O90: =O175*0.25
C91: Total Sales | D91: =D90*$D$22 | E91: =E90*$D$22 | F91: =F90*$D$22 | G91: =G90*$D$22 | H91: =H90*$D$22 | I91: =I90*$D$22 | J91: =J90*$D$22 | K91: =K90*$D$22 | ... O91: =O90*$D$22 | P91: =SUM(D91:O91) | Q91: =(Q92+Q93)
C92: Total COGS | D92: =D90*$E$22 | E92: =E90*$E$22 | F92: =F90*$E$22 | G92: =G90*$E$22 | H92: =H90*$E$22 | I92: =I90*$E$22 | J92: =J90*$E$22 | K92: =K90*$E$22 | ... O92: =O90*$E$22 | P92: =SUM(D92:O92) | Q92: =IF(P91=0,0,P92/P91)
C93: Total Margin | D93: =D91-D92 | E93: =E91-E92 | F93: =F91-F92 | G93: =G91-G92 | H93: =H91-H92 | I93: =I91-I92 | J93: =J91-J92 | K93: =K91-K92 | ... O93: =O91-O92 | P93: =SUM(D93:O93) | Q93: =IF(P91=0,0,P93/P91)
C95: Total Training Consultancy
C96: Total Sales | D96: =D91+D85 | E96: =E91+E85 | F96: =F91+F85 | G96: =G91+G85 | H96: =H91+H85 | I96: =I91+I85 | J96: =J91+J85 | K96: =K91+K85 | ... O96: =O91+O85 | P96: =SUM(D96:O96) | Q96: =(Q97+Q98)
C97: Total COGS | D97: =D92+D86 | E97: =E92+E86 | F97: =F92+F86 | G97: =G92+G86 | H97: =H92+H86 | I97: =I92+I86 | J97: =J92+J86 | K97: =K92+K86 | ... O97: =O92+O86 | P97: =SUM(D97:O97) | Q97: =IF(P96=0,0,P97/P96)
C98: Total Margin | D98: =D96-D97 | E98: =E96-E97 | F98: =F96-F97 | G98: =G96-G97 | H98: =H96-H97 | I98: =I96-I97 | J98: =J96-J97 | K98: =K96-K97 | ... O98: =O96-O97 | P98: =SUM(D98:O98) | Q98: =IF(P96=0,0,P98/P96)
D99: =D76+D69+D62+D55+D48+D41+D34+D27 | E99: =E76+E69+E62+E55+E48+E41+E34+E27 | F99: =F76+F69+F62+F55+F48+F41+F34+F27 | G99: =G76+G69+G62+G55+G48+G41+G34+G27 | H99: =H76+H69+H62+H55+H48+H41+H34+H27 | I99: =I76+I69+I62+I55+I48+I41+I34+I27 | J99: =J76+J69+J62+J55+J48+J41+J34+J27 | K99: =K76+K69+K62+K55+K48+K41+K34+K27 | ... O99: =O76+O69+O62+O55+O48+O41+O34+O27 | T99: Assumptions
C100: Net New | D100: =(D76+D69+D62+D55+D48+D41+D34+D27)-'Revenue 2028'!O99 | E100: =E99-D99 | F100: =F99-E99 | G100: =G99-F99 | H100: =H99-G99 | I100: =I99-H99 | J100: =J99-I99 | K100: =K99-J99 | L100: =L99-K99 | ... O100: =O99-N99 | T100: work hours
B101: Administrative | C101: =C6 | T101: per new acct
C102: Net New Licences Sold | D102: =D100*$T$102 | E102: =E100*$T$102 | F102: =F100*$T$102 | G102: =G100*$T$102 | H102: =H100*$T$102 | I102: =I100*$T$102 | J102: =J100*$T$102 | K102: =K100*$T$102 | ... O102: =O100*$T$102 | T102: 1
C103: Total Sales | D103: =D102*$D$6 | E103: =E102*$D$6 | F103: =F102*$D$6 | G103: =G102*$D$6 | H103: =H102*$D$6 | I103: =I102*$D$6 | J103: =J102*$D$6 | K103: =K102*$D$6 | ... O103: =O102*$D$6 | P103: =SUM(D103:O103) | Q103: =(Q104+Q105)
C104: Total COGS | D104: =D102*$E$6 | E104: =E102*$E$6 | F104: =F102*$E$6 | G104: =G102*$E$6 | H104: =H102*$E$6 | I104: =I102*$E$6 | J104: =J102*$E$6 | K104: =K102*$E$6 | ... O104: =O102*$E$6 | P104: =SUM(D104:O104) | Q104: =IF(P103=0,0,P104/P103)
C105: Total Margin | D105: =D103-D104 | E105: =E103-E104 | F105: =F103-F104 | G105: =G103-G104 | H105: =H103-H104 | I105: =I103-I104 | J105: =J103-J104 | K105: =K103-K104 | ... O105: =O103-O104 | P105: =SUM(D105:O105) | Q105: =IF(P103=0,0,P105/P103)
C107: =C7
C108: Net New Licences Sold | D108: =D100*$T$108 | E108: =E100*$T$108 | F108: =F100*$T$108 | G108: =G100*$T$108 | H108: =H100*$T$108 | I108: =I100*$T$108 | J108: =J100*$T$108 | K108: =K100*$T$108 | ... O108: =O100*$T$108 | T108: 1
C109: Total Sales | D109: =D108*$D$7 | E109: =E108*$D$7 | F109: =F108*$D$7 | G109: =G108*$D$7 | H109: =H108*$D$7 | I109: =I108*$D$7 | J109: =J108*$D$7 | K109: =K108*$D$7 | ... O109: =O108*$D$7 | P109: =SUM(D109:O109) | Q109: =(Q110+Q111)
C110: Total COGS | D110: =D108*$E$7 | E110: =E108*$E$7 | F110: =F108*$E$7 | G110: =G108*$E$7 | H110: =H108*$E$7 | I110: =I108*$E$7 | J110: =J108*$E$7 | K110: =K108*$E$7 | ... O110: =O108*$E$7 | P110: =SUM(D110:O110) | Q110: =IF(P109=0,0,P110/P109)
C111: Total Margin | D111: =D109-D110 | E111: =E109-E110 | F111: =F109-F110 | G111: =G109-G110 | H111: =H109-H110 | I111: =I109-I110 | J111: =J109-J110 | K111: =K109-K110 | ... O111: =O109-O110 | P111: =SUM(D111:O111) | Q111: =IF(P109=0,0,P111/P109)
C113: =C8
C114: Net New Licences Sold | D114: =D100*$T$114 | E114: =E100*$T$114 | F114: =F100*$T$114 | G114: =G100*$T$114 | H114: =H100*$T$114 | I114: =I100*$T$114 | J114: =J100*$T$114 | K114: =K100*$T$114 | ... O114: =O100*$T$114 | T114: 2
C115: Total Sales | D115: =D114*$D$8 | E115: =E114*$D$8 | F115: =F114*$D$8 | G115: =G114*$D$8 | H115: =H114*$D$8 | I115: =I114*$D$8 | J115: =J114*$D$8 | K115: =K114*$D$8 | ... O115: =O114*$D$8 | P115: =SUM(D115:O115) | Q115: =(Q116+Q117)
C116: Total COGS | D116: =D114*$E$8 | E116: =E114*$E$8 | F116: =F114*$E$8 | G116: =G114*$E$8 | H116: =H114*$E$8 | I116: =I114*$E$8 | J116: =J114*$E$8 | K116: =K114*$E$8 | ... O116: =O114*$E$8 | P116: =SUM(D116:O116) | Q116: =IF(P115=0,0,P116/P115)
C117: Total Margin | D117: =D115-D116 | E117: =E115-E116 | F117: =F115-F116 | G117: =G115-G116 | H117: =H115-H116 | I117: =I115-I116 | J117: =J115-J116 | K117: =K115-K116 | ... O117: =O115-O116 | P117: =SUM(D117:O117) | Q117: =IF(P115=0,0,P117/P115)
...

Sheet Revenue 2030
C3: 2030 | D3: Pricing
C4: Offerings and Distribution | D4: Price | E4: COGS | F4: Margin Per Subscription
C5: Administrative
C6: Configuration | D6: 250 | E6: 50 | F6: =D6-E6
C7: On-Boarding- Administrator | D7: 500 | E7: 100 | F7: =D7-E7
C8: On-Boarding Users | D8: 500 | E8: 100 | F8: =D8-E8
C9: Import | D9: ='Pricing Calcuator'!D86 | E9: 600 | F9: =D9-E9
C10: Support | D10: 100 | E10: 50 | F10: =D10-E10
C11: Industry Break Down | E11: ='COGS Analysis'!D18
C12: Hospitality | D12: 250 | E12: =$Q$210 | F12: =D12-E12
C13: Hospitality- Reseller | D13: 100 | E13: =$Q$210 | F13: =D13-E13
C14: Real Estate Development | D14: 400 | E14: =$Q$210 | F14: =D14-E14
C15: Real Estate Development- Reseller | D15: 200 | E15: =$Q$210 | F15: =D15-E15
C16: Pharma | D16: 450 | E16: =$Q$210 | F16: =D16-E16
C17: Pharma- Reseller | D17: 200 | E17: =$Q$210 | F17: =D17-E17
C18: Start up - Small Firms | D18: 200 | E18: =$Q$210 | F18: =D18-E18
C19: Start up Reseller | D19: 100 | E19: =$Q$210 | F19: =D19-E19
C20: Training / Consultancy Training as a Service
C21: Thought Library | D21: 50 | E21: 25 | F21: =D21-E21
C22: Consultancy Services | D22: 225 | E22: 125 | F22: =D22-E22
C24: Segments | D24: January | E24: February | F24: March | G24: April | H24: May | I24: June | J24: July | K24: August | L24: September | M24: October | N24: November | O24: December | P24: Annual Totals | Q24: Profit Margin | R24: Profit margin comparison | S24: Churn | T24: Assumptions
B26: Hospitality | C26: =C12
C27: Licences Sold | D27: 1580 | E27: 1600 | F27: 1630 | G27: 1650 | H27: 1680 | I27: 1725 | J27: 1775 | K27: 2000 | L27: 2125 | M27: 2180 | N27: 2200 | O27: 2235 | P27: =O27 | S27: 0.03
D28: =D27*$S$27 | E28: =E27*$S$27 | F28: =F27*$S$27 | G28: =G27*$S$27 | H28: =H27*$S$27 | I28: =I27*$S$27 | J28: =J27*$S$27 | K28: =K27*$S$27 | ... O28: =O27*$S$27
C29: Total Sales | D29: =(D27-D28)*$D$12 | E29: =(E27-E28)*$D$12 | F29: =(F27-F28)*$D$12 | G29: =(G27-G28)*$D$12 | H29: =(H27-H28)*$D$12 | I29: =(I27-I28)*$D$12 | J29: =(J27-J28)*$D$12 | K29: =(K27-K28)*$D$12 | ... O29: =(O27-O28)*$D$12 | P29: =SUM(D29:O29) | Q29: =(Q30+Q31)
C30: Total COGS | D30: =D27*$E$12 | E30: =E27*$E$12 | F30: =F27*$E$12 | G30: =G27*$E$12 | H30: =H27*$E$12 | I30: =I27*$E$12 | J30: =J27*$E$12 | K30: =K27*$E$12 | ... O30: =O27*$E$12 | P30: =SUM(D30:O30) | Q30: =IF(P29=0,0,P30/P29)
C31: Total Margin | D31: =D29-D30 | E31: =E29-E30 | F31: =F29-F30 | G31: =G29-G30 | H31: =H29-H30 | I31: =I29-I30 | J31: =J29-J30 | K31: =K29-K30 | ... O31: =O29-O30 | P31: =SUM(D31:O31) | Q31: =IF(P29=0,0,P31/P29)
C33: =C13
C34: Licences Sold | D34: 765 | E34: 765 | F34: 770 | G34: 775 | H34: 780 | I34: 785 | J34: 790 | K34: 795 | L34: 800 | M34: 810 | N34: 810 | O34: 810 | P34: =O34 | S34: 0.03
D35: =D34*$S$34 | E35: =E34*$S$34 | F35: =F34*$S$34 | G35: =G34*$S$34 | H35: =H34*$S$34 | I35: =I34*$S$34 | J35: =J34*$S$34 | K35: =K34*$S$34 | ... O35: =O34*$S$34
C36: Total Sales | D36: =(D34-D35)*$D$13 | E36: =(E34-E35)*$D$13 | F36: =(F34-F35)*$D$13 | G36: =(G34-G35)*$D$13 | H36: =(H34-H35)*$D$13 | I36: =(I34-I35)*$D$13 | J36: =(J34-J35)*$D$13 | K36: =(K34-K35)*$D$13 | ... O36: =(O34-O35)*$D$13 | P36: =SUM(D36:O36) | Q36: =(Q37+Q38)
C37: Total COGS | D37: =D34*$E$13 | E37: =E34*$E$13 | F37: =F34*$E$13 | G37: =G34*$E$13 | H37: =H34*$E$13 | I37: =I34*$E$13 | J37: =J34*$E$13 | K37: =K34*$E$13 | ... O37: =O34*$E$13 | P37: =SUM(D37:O37) | Q37: =IF(P36=0,0,P37/P36)
C38: Total Margin | D38: =D36-D37 | E38: =E36-E37 | F38: =F36-F37 | G38: =G36-G37 | H38: =H36-H37 | I38: =I36-I37 | J38: =J36-J37 | K38: =K36-K37 | ... O38: =O36-O37 | P38: =SUM(D38:O38) | Q38: =IF(P36=0,0,P38/P36)
B40: Real Estate | C40: =C14
C41: Licences Sold | D41: 760 | E41: 775 | F41: 780 | G41: 785 | H41: 790 | I41: 800 | J41: 815 | K41: 825 | L41: 830 | M41: 835 | N41: 840 | O41: 845 | P41: =O41 | S41: 0.03
D42: =D41*$S$41 | E42: =E41*$S$41 | F42: =F41*$S$41 | G42: =G41*$S$41 | H42: =H41*$S$41 | I42: =I41*$S$41 | J42: =J41*$S$41 | K42: =K41*$S$41 | ... O42: =O41*$S$41
C43: Total Sales | D43: =(D41-D42)*$D$14 | E43: =(E41-E42)*$D$14 | F43: =(F41-F42)*$D$14 | G43: =(G41-G42)*$D$14 | H43: =(H41-H42)*$D$14 | I43: =(I41-I42)*$D$14 | J43: =(J41-J42)*$D$14 | K43: =(K41-K42)*$D$14 | ... O43: =(O41-O42)*$D$14 | P43: =SUM(D43:O43) | Q43: =(Q44+Q45)
C44: Total COGS | D44: =D41*$E$14 | E44: =E41*$E$14 | F44: =F41*$E$14 | G44: =G41*$E$14 | H44: =H41*$E$14 | I44: =I41*$E$14 | J44: =J41*$E$14 | K44: =K41*$E$14 | ... O44: =O41*$E$14 | P44: =SUM(D44:O44) | Q44: =IF(P43=0,0,P44/P43)
C45: Total Margin | D45: =D43-D44 | E45: =E43-E44 | F45: =F43-F44 | G45: =G43-G44 | H45: =H43-H44 | I45: =I43-I44 | J45: =J43-J44 | K45: =K43-K44 | ... O45: =O43-O44 | P45: =SUM(D45:O45) | Q45: =IF(P43=0,0,P45/P43)
C47: =C15
C48: Licences Sold | D48: 355 | E48: 355 | F48: 355 | G48: 355 | H48: 355 | I48: 355 | J48: 360 | K48: 365 | L48: 370 | M48: 375 | N48: 380 | O48: 395 | P48: =O48 | S48: 0.03
D49: =D48*$S$48 | E49: =E48*$S$48 | F49: =F48*$S$48 | G49: =G48*$S$48 | H49: =H48*$S$48 | I49: =I48*$S$48 | J49: =J48*$S$48 | K49: =K48*$S$48 | ... O49: =O48*$S$48
C50: Total Sales | D50: =(D48-D49)*$D$15 | E50: =(E48-E49)*$D$15 | F50: =(F48-F49)*$D$15 | G50: =(G48-G49)*$D$15 | H50: =(H48-H49)*$D$15 | I50: =(I48-I49)*$D$15 | J50: =(J48-J49)*$D$15 | K50: =(K48-K49)*$D$15 | ... O50: =(O48-O49)*$D$15 | P50: =SUM(D50:O50) | Q50: =(Q51+Q52)
C51: Total COGS | D51: =D48*$E$15 | E51: =E48*$E$15 | F51: =F48*$E$15 | G51: =G48*$E$15 | H51: =H48*$E$15 | I51: =I48*$E$15 | J51: =J48*$E$15 | K51: =K48*$E$15 | ... O51: =O48*$E$15 | P51: =SUM(D51:O51) | Q51: =IF(P50=0,0,P51/P50)
C52: Total Margin | D52: =D50-D51 | E52: =E50-E51 | F52: =F50-F51 | G52: =G50-G51 | H52: =H50-H51 | I52: =I50-I51 | J52: =J50-J51 | K52: =K50-K51 | ... O52: =O50-O51 | P52: =SUM(D52:O52) | Q52: =IF(P50=0,0,P52/P50)
B54: Pharma | C54: =C16
C55: Licences Sold | D55: 445 | E55: 470 | F55: 490 | G55: 510 | H55: 535 | I55: 550 | J55: 575 | K55: 590 | L55: 600 | M55: 610 | N55: 625 | O55: 630 | P55: =O55 | S55: 0.03
D56: =D55*S55 | E56: =E55*T55 | F56: =F55*U55 | G56: =G55*V55 | H56: =H55*W55 | I56: =I55*X55 | J56: =J55*Y55 | K56: =K55*Z55 | ... O56: =O55*AD55
C57: Total Sales | D57: =(D55-D56)*$D$16 | E57: =(E55-E56)*$D$16 | F57: =(F55-F56)*$D$16 | G57: =(G55-G56)*$D$16 | H57: =(H55-H56)*$D$16 | I57: =(I55-I56)*$D$16 | J57: =(J55-J56)*$D$16 | K57: =(K55-K56)*$D$16 | ... O57: =(O55-O56)*$D$16 | P57: =SUM(D57:O57) | Q57: =(Q58+Q59)
C58: Total COGS | D58: =D55*$E$16 | E58: =E55*$E$16 | F58: =F55*$E$16 | G58: =G55*$E$16 | H58: =H55*$E$16 | I58: =I55*$E$16 | J58: =J55*$E$16 | K58: =K55*$E$16 | ... O58: =O55*$E$16 | P58: =SUM(D58:O58) | Q58: =IF(P57=0,0,P58/P57)
C59: Total Margin | D59: =D57-D58 | E59: =E57-E58 | F59: =F57-F58 | G59: =G57-G58 | H59: =H57-H58 | I59: =I57-I58 | J59: =J57-J58 | K59: =K57-K58 | ... O59: =O57-O58 | P59: =SUM(D59:O59) | Q59: =IF(P57=0,0,P59/P57)
C61: =C17
C62: Licences Sold | D62: 110 | E62: 115 | F62: 120 | G62: 125 | H62: 130 | I62: 135 | J62: 145 | K62: 150 | L62: 155 | M62: 165 | N62: 175 | O62: 175 | P62: =O62 | S62: 0.03
D63: =D62*$S$62 | E63: =E62*$S$62 | F63: =F62*$S$62 | G63: =G62*$S$62 | H63: =H62*$S$62 | I63: =I62*$S$62 | J63: =J62*$S$62 | K63: =K62*$S$62 | ... O63: =O62*$S$62
C64: Total Sales | D64: =(D62-D63)*$D$17 | E64: =(E62-E63)*$D$17 | F64: =(F62-F63)*$D$17 | G64: =(G62-G63)*$D$17 | H64: =(H62-H63)*$D$17 | I64: =(I62-I63)*$D$17 | J64: =(J62-J63)*$D$17 | K64: =(K62-K63)*$D$17 | ... O64: =(O62-O63)*$D$17 | P64: =SUM(D64:O64) | Q64: =(Q65+Q66)
C65: Total COGS | D65: =D62*$E$17 | E65: =E62*$E$17 | F65: =F62*$E$17 | G65: =G62*$E$17 | H65: =H62*$E$17 | I65: =I62*$E$17 | J65: =J62*$E$17 | K65: =K62*$E$17 | ... O65: =O62*$E$17 | P65: =SUM(D65:O65) | Q65: =IF(P64=0,0,P65/P64)
C66: Total Margin | D66: =D64-D65 | E66: =E64-E65 | F66: =F64-F65 | G66: =G64-G65 | H66: =H64-H65 | I66: =I64-I65 | J66: =J64-J65 | K66: =K64-K65 | ... O66: =O64-O65 | P66: =SUM(D66:O66) | Q66: =IF(P64=0,0,P66/P64)
B68: Startups | C68: =C18
C69: Licences Sold | D69: 500 | E69: 525 | F69: 560 | G69: 590 | H69: 610 | I69: 625 | J69: 635 | K69: 665 | L69: 700 | M69: 710 | N69: 725 | O69: 750 | P69: =O69 | S69: 0.05
D70: =D69*$S$69 | E70: =E69*$S$69 | F70: =F69*$S$69 | G70: =G69*$S$69 | H70: =H69*$S$69 | I70: =I69*$S$69 | J70: =J69*$S$69 | K70: =K69*$S$69 | ... O70: =O69*$S$69
C71: Total Sales | D71: =(D69-D70)*$D$18 | E71: =(E69-E70)*$D$18 | F71: =(F69-F70)*$D$18 | G71: =(G69-G70)*$D$18 | H71: =(H69-H70)*$D$18 | I71: =(I69-I70)*$D$18 | J71: =(J69-J70)*$D$18 | K71: =(K69-K70)*$D$18 | ... O71: =(O69-O70)*$D$18 | P71: =SUM(D71:O71) | Q71: =(Q72+Q73)
C72: Total COGS | D72: =D69*$E$18 | E72: =E69*$E$18 | F72: =F69*$E$18 | G72: =G69*$E$18 | H72: =H69*$E$18 | I72: =I69*$E$18 | J72: =J69*$E$18 | K72: =K69*$E$18 | ... O72: =O69*$E$18 | P72: =SUM(D72:O72) | Q72: =IF(P71=0,0,P72/P71)
C73: Total Margin | D73: =D71-D72 | E73: =E71-E72 | F73: =F71-F72 | G73: =G71-G72 | H73: =H71-H72 | I73: =I71-I72 | J73: =J71-J72 | K73: =K71-K72 | ... O73: =O71-O72 | P73: =SUM(D73:O73) | Q73: =IF(P71=0,0,P73/P71)
C75: =C19
C76: Licences Sold | D76: 0 | E76: 0 | F76: 0 | G76: 0 | H76: 0 | I76: 0 | J76: 0 | K76: 0 | L76: 0 | M76: 0 | N76: 0 | O76: 0 | P76: =O76 | S76: 0.05
D77: =D76*$S$76 | E77: =E76*$S$76 | F77: =F76*$S$76 | G77: =G76*$S$76 | H77: =H76*$S$76 | I77: =I76*$S$76 | J77: =J76*$S$76 | K77: =K76*$S$76 | ... O77: =O76*$S$76
C78: Total Sales | D78: =(D76-D77)*$D$19 | E78: =(E76-E77)*$D$19 | F78: =(F76-F77)*$D$19 | G78: =(G76-G77)*$D$19 | H78: =(H76-H77)*$D$19 | I78: =(I76-I77)*$D$19 | J78: =(J76-J77)*$D$19 | K78: =(K76-K77)*$D$19 | ... O78: =(O76-O77)*$D$19 | P78: =SUM(D78:O78) | Q78: =(Q79+Q80)
C79: Total COGS | D79: =D76*$E$19 | E79: =E76*$E$19 | F79: =F76*$E$19 | G79: =G76*$E$19 | H79: =H76*$E$19 | I79: =I76*$E$19 | J79: =J76*$E$19 | K79: =K76*$E$19 | ... O79: =O76*$E$19 | P79: =SUM(D79:O79) | Q79: =IF(P78=0,0,P79/P78)
C80: Total Margin | D80: =D78-D79 | E80: =E78-E79 | F80: =F78-F79 | G80: =G78-G79 | H80: =H78-H79 | I80: =I78-I79 | J80: =J78-J79 | K80: =K78-K79 | ... O80: =O78-O79 | P80: =SUM(D80:O80) | Q80: =IF(P78=0,0,P80/P78)
B83: Consultancy / Training | C83: =C21
C84: Access Sold | D84: =D175*0.35 | E84: =E175*0.35 | F84: =F175*0.35 | G84: =G175*0.35 | H84: =H175*0.35 | I84: =I175*0.35 | J84: =J175*0.35 | K84: =K175*0.35 | ... O84: =O175*0.35
C85: Total Sales | D85: =D84*$D$21 | E85: =E84*$D$21 | F85: =F84*$D$21 | G85: =G84*$D$21 | H85: =H84*$D$21 | I85: =I84*$D$21 | J85: =J84*$D$21 | K85: =K84*$D$21 | ... O85: =O84*$D$21 | P85: =SUM(D85:O85) | Q85: =(Q86+Q87)
C86: Total COGS | D86: =D84*$E$21 | E86: =E84*$E$21 | F86: =F84*$E$21 | G86: =G84*$E$21 | H86: =H84*$E$21 | I86: =I84*$E$21 | J86: =J84*$E$21 | K86: =K84*$E$21 | ... O86: =O84*$E$21 | P86: =SUM(D86:O86) | Q86: =IF(P85=0,0,P86/P85)
C87: Total Margin | D87: =D85-D86 | E87: =E85-E86 | F87: =F85-F86 | G87: =G85-G86 | H87: =H85-H86 | I87: =I85-I86 | J87: =J85-J86 | K87: =K85-K86 | ... O87: =O85-O86 | P87: =SUM(D87:O87) | Q87: =IF(P85=0,0,P87/P85)
C89: =C22
C90: Hours Sold | D90: =D175*0.25 | E90: =E175*0.25 | F90: =F175*0.25 | G90: =G175*0.25 | H90: =H175*0.25 | I90: =I175*0.25 | J90: =J175*0.25 | K90: =K175*0.25 | ... O90: =O175*0.25
C91: Total Sales | D91: =D90*$D$22 | E91: =E90*$D$22 | F91: =F90*$D$22 | G91: =G90*$D$22 | H91: =H90*$D$22 | I91: =I90*$D$22 | J91: =J90*$D$22 | K91: =K90*$D$22 | ... O91: =O90*$D$22 | P91: =SUM(D91:O91) | Q91: =(Q92+Q93)
C92: Total COGS | D92: =D90*$E$22 | E92: =E90*$E$22 | F92: =F90*$E$22 | G92: =G90*$E$22 | H92: =H90*$E$22 | I92: =I90*$E$22 | J92: =J90*$E$22 | K92: =K90*$E$22 | ... O92: =O90*$E$22 | P92: =SUM(D92:O92) | Q92: =IF(P91=0,0,P92/P91)
C93: Total Margin | D93: =D91-D92 | E93: =E91-E92 | F93: =F91-F92 | G93: =G91-G92 | H93: =H91-H92 | I93: =I91-I92 | J93: =J91-J92 | K93: =K91-K92 | ... O93: =O91-O92 | P93: =SUM(D93:O93) | Q93: =IF(P91=0,0,P93/P91)
C95: Total Training Consultancy
C96: Total Sales | D96: =D91+D85 | E96: =E91+E85 | F96: =F91+F85 | G96: =G91+G85 | H96: =H91+H85 | I96: =I91+I85 | J96: =J91+J85 | K96: =K91+K85 | ... O96: =O91+O85 | P96: =SUM(D96:O96) | Q96: =(Q97+Q98)
C97: Total COGS | D97: =D92+D86 | E97: =E92+E86 | F97: =F92+F86 | G97: =G92+G86 | H97: =H92+H86 | I97: =I92+I86 | J97: =J92+J86 | K97: =K92+K86 | ... O97: =O92+O86 | P97: =SUM(D97:O97) | Q97: =IF(P96=0,0,P97/P96)
C98: Total Margin | D98: =D96-D97 | E98: =E96-E97 | F98: =F96-F97 | G98: =G96-G97 | H98: =H96-H97 | I98: =I96-I97 | J98: =J96-J97 | K98: =K96-K97 | ... O98: =O96-O97 | P98: =SUM(D98:O98) | Q98: =IF(P96=0,0,P98/P96)
D99: =D76+D69+D62+D55+D48+D41+D34+D27 | E99: =E76+E69+E62+E55+E48+E41+E34+E27 | F99: =F76+F69+F62+F55+F48+F41+F34+F27 | G99: =G76+G69+G62+G55+G48+G41+G34+G27 | H99: =H76+H69+H62+H55+H48+H41+H34+H27 | I99: =I76+I69+I62+I55+I48+I41+I34+I27 | J99: =J76+J69+J62+J55+J48+J41+J34+J27 | K99: =K76+K69+K62+K55+K48+K41+K34+K27 | ... O99: =O76+O69+O62+O55+O48+O41+O34+O27 | T99: Assumptions
C100: Net New | D100: =D76+D69+D62+D55+D48+D41+D34+D27 | E100: =E99-D99 | F100: =F99-E99 | G100: =G99-F99 | H100: =H99-G99 | I100: =I99-H99 | J100: =J99-I99 | K100: =K99-J99 | L100: =L99-K99 | ... O100: =O99-N99 | T100: work hours
B101: Administrative | C101: =C6 | T101: per new acct
C102: Net New Licences Sold | D102: =D100*$T$102 | E102: =E100*$T$102 | F102: =F100*$T$102 | G102: =G100*$T$102 | H102: =H100*$T$102 | I102: =I100*$T$102 | J102: =J100*$T$102 | K102: =K100*$T$102 | ... O102: =O100*$T$102 | T102: 1
C103: Total Sales | D103: =D102*$D$6 | E103: =E102*$D$6 | F103: =F102*$D$6 | G103: =G102*$D$6 | H103: =H102*$D$6 | I103: =I102*$D$6 | J103: =J102*$D$6 | K103: =K102*$D$6 | ... O103: =O102*$D$6 | P103: =SUM(D103:O103) | Q103: =(Q104+Q105)
C104: Total COGS | D104: =D102*$E$6 | E104: =E102*$E$6 | F104: =F102*$E$6 | G104: =G102*$E$6 | H104: =H102*$E$6 | I104: =I102*$E$6 | J104: =J102*$E$6 | K104: =K102*$E$6 | ... O104: =O102*$E$6 | P104: =SUM(D104:O104) | Q104: =IF(P103=0,0,P104/P103)
C105: Total Margin | D105: =D103-D104 | E105: =E103-E104 | F105: =F103-F104 | G105: =G103-G104 | H105: =H103-H104 | I105: =I103-I104 | J105: =J103-J104 | K105: =K103-K104 | ... O105: =O103-O104 | P105: =SUM(D105:O105) | Q105: =IF(P103=0,0,P105/P103)
C107: =C7
C108: Net New Licences Sold | D108: =D100*$T$108 | E108: =E100*$T$108 | F108: =F100*$T$108 | G108: =G100*$T$108 | H108: =H100*$T$108 | I108: =I100*$T$108 | J108: =J100*$T$108 | K108: =K100*$T$108 | ... O108: =O100*$T$108 | T108: 1
C109: Total Sales | D109: =D108*$D$7 | E109: =E108*$D$7 | F109: =F108*$D$7 | G109: =G108*$D$7 | H109: =H108*$D$7 | I109: =I108*$D$7 | J109: =J108*$D$7 | K109: =K108*$D$7 | ... O109: =O108*$D$7 | P109: =SUM(D109:O109) | Q109: =(Q110+Q111)
C110: Total COGS | D110: =D108*$E$7 | E110: =E108*$E$7 | F110: =F108*$E$7 | G110: =G108*$E$7 | H110: =H108*$E$7 | I110: =I108*$E$7 | J110: =J108*$E$7 | K110: =K108*$E$7 | ... O110: =O108*$E$7 | P110: =SUM(D110:O110) | Q110: =IF(P109=0,0,P110/P109)
C111: Total Margin | D111: =D109-D110 | E111: =E109-E110 | F111: =F109-F110 | G111: =G109-G110 | H111: =H109-H110 | I111: =I109-I110 | J111: =J109-J110 | K111: =K109-K110 | ... O111: =O109-O110 | P111: =SUM(D111:O111) | Q111: =IF(P109=0,0,P111/P109)
C113: =C8
C114: Net New Licences Sold | D114: =D100*$T$114 | E114: =E100*$T$114 | F114: =F100*$T$114 | G114: =G100*$T$114 | H114: =H100*$T$114 | I114: =I100*$T$114 | J114: =J100*$T$114 | K114: =K100*$T$114 | ... O114: =O100*$T$114 | T114: 2
C115: Total Sales | D115: =D114*$D$8 | E115: =E114*$D$8 | F115: =F114*$D$8 | G115: =G114*$D$8 | H115: =H114*$D$8 | I115: =I114*$D$8 | J115: =J114*$D$8 | K115: =K114*$D$8 | ... O115: =O114*$D$8 | P115: =SUM(D115:O115) | Q115: =(Q116+Q117)
C116: Total COGS | D116: =D114*$E$8 | E116: =E114*$E$8 | F116: =F114*$E$8 | G116: =G114*$E$8 | H116: =H114*$E$8 | I116: =I114*$E$8 | J116: =J114*$E$8 | K116: =K114*$E$8 | ... O116: =O114*$E$8 | P116: =SUM(D116:O116) | Q116: =IF(P115=0,0,P116/P115)
C117: Total Margin | D117: =D115-D116 | E117: =E115-E116 | F117: =F115-F116 | G117: =G115-G116 | H117: =H115-H116 | I117: =I115-I116 | J117: =J115-J116 | K117: =K115-K116 | ... O117: =O115-O116 | P117: =SUM(D117:O117) | Q117: =IF(P115=0,0,P117/P115)
...

Sheet COGS Analysis
C3: PRODUCT | D3: Vendor | E3: Plan Name | F3: Cost Link | G3: Cost Unit | H3: Cost Unit Number | I3: Cost Per Month | K3: Annual Cost (Unit X Month) | L3: 2
C4: Support | K4: =Table13[[#This Row],[Cost Per Month]]*12*Table13[[#This Row],[Cost Unit Number]]
B5: By Customer Support | C5: E-mail & Chat | D5: FreshWorks | E5: FreshChat - Sprout Plan (free) | F5: Support Desk Pricing | G5: per license; 5000 bot | H5: 1 | I5: 69 | K5: =Table13[[#This Row],[Cost Per Month]]*12*Table13[[#This Row],[Cost Unit Number]]
C6: OMNICHANNEL; Ticketing | D6: FreshWorks | E6: FreshDesk - Estate Omnichannel | F6: Fresh Desk Omni Channel | G6: per user | H6: 1 | I6: 79 | K6: =Table13[[#This Row],[Cost Per Month]]*12*Table13[[#This Row],[Cost Unit Number]]
C7: SUPPORT DESK | D7: Zoom | G7: per user | H7: 3 | I7: 149 | K7: =Table13[[#This Row],[Cost Per Month]]*Table13[[#This Row],[Cost Unit Number]]
D8: phone | F8: Freshworks | G8: per user | H8: 3 | I8: 3 | K8: =Table13[[#This Row],[Cost Per Month]]*12*Table13[[#This Row],[Cost Unit Number]]
B9: BY LICENCE | C9: Data Integration | D9: hConnect | F9: https://hconnect.io/ | G9: per license | H9: 12 | I9: 600 | K9: 0
B10: Back Office | C10: Hosting | D10: AWS | G10: cost per month | H10: 12 | I10: 2000 | K10: =Table13[[#This Row],[Cost Per Month]]*Table13[[#This Row],[Cost Unit Number]]
C11: Billing (SAS recurring management software) | D11: Chargebee | E11: Chargebee | F11: Chargebee Pricing | G11: includes USD 600K/yr revenue 0.6% of overage revenue | H11: 1 | I11: 249 | K11: =Table13[[#This Row],[Cost Per Month]]*12*Table13[[#This Row],[Cost Unit Number]]
C12: Total | K12: =SUBTOTAL(109,Table13[Annual Cost (Unit X Month)])
D14: 1
C15: TOTAL TECHNOLOGY Service & Operations costs annual | D15: =Table13[[#Totals],[Annual Cost (Unit X Month)]]
C16: Cost Per Month | D16: =D15/12

Sheet Salaries & Wages
C4: Forecast | Q4: Forecast | AE4: Forecast | AS4: Forecast | BG4: Forecast | BU4: Forecast
C5: 2025 | O5: 2025 | Q5: 2026 | AC5: 2026 | AE5: 2027 | AQ5: 2027 | AS5: 2028 | BE5: 2028 | BG5: 2029 | BS5: 2029 | BU5: 2030 | CG5: 2030
C6: 45658 | D6: 45689 | E6: 45717 | F6: 45748 | G6: 45778 | H6: 45809 | I6: 45839 | J6: 45870 | K6: 45901 | L6: 45931 | M6: 45962 | N6: 45992 | O6: Total | P6: 2025 Head Count | Q6: 46023 | R6: 46054 | S6: 46082 | T6: 46113 | U6: 46143 | V6: 46174 | W6: 46204 | X6: 46235 | Y6: 46266 | Z6: 46296 | AA6: 46327 | AB6: 46357 | AC6: Total | AD6: 2026 Head Count | AE6: 46388 | AF6: 46419 | AG6: 46447 | AH6: 46478 | AI6: 46508 | AJ6: 46539 | AK6: 46569 | AL6: 46600 | AM6: 46631 | AN6: 46661 | AO6: 46692 | AP6: 46722 | AQ6: Total | AR6: 2027 Head Count | AS6: 46753 | AT6: 46784 | AU6: 46813 | AV6: 46844 | AW6: 5/=2028 | AX6: 46905 | AY6: 46935 | AZ6: 46966 | BA6: 46997 | BB6: 47027 | BC6: 47058 | BD6: 47088 | BE6: Total | BF6: 2028 Head Count | BG6: 47119 | BH6: 47150 | BI6: 47178 | BJ6: 47209 | BK6: 47239 | BL6: 47270 | BM6: 47300 | BN6: 47331 | BO6: 47362 | BP6: 47392 | BQ6: 47423 | BR6: 47453 | BS6: Total | BT6: 2029 Head Count | BU6: 47484 | BV6: 44958 | BW6: 47543 | BX6: 47574 | BY6: 47604 | BZ6: 6/20230 | CA6: 47665 | CB6: 47696 | CC6: 47727 | CD6: 47757 | CE6: 47788 | CF6: 47818 | CG6: Total | CH6: 2030 Head Count
A7: Salaries And Wages :
A8: CEO | C8: 5000 | D8: =$C$8 | E8: =$C$8 | F8: =$C$8 | G8: =$C$8 | H8: =$C$8 | I8: =$C$8 | J8: =$C$8 | K8: =$C$8 | ... N8: =$C$8 | O8: =SUM(C8:N8) | P8: 0.5 | Q8: 6500 | R8: =$Q$8 | S8: =$Q$8 | T8: =$Q$8 | U8: =$Q$8 | V8: =$Q$8 | W8: =$Q$8 | X8: =$Q$8 | Y8: =$Q$8 | ... AB8: =$Q$8 | AC8: =SUM(Q8:AB8) | AD8: 1 | AE8: 10000 | AF8: =$AE$8 | AG8: =$AE$8 | AH8: =$AE$8 | AI8: =$AE$8 | AJ8: =$AE$8 | AK8: =$AE$8 | AL8: =$AE$8 | AM8: =$AE$8 | ... AP8: =$AE$8 | AQ8: =SUM(AE8:AP8) | AR8: 1 | AS8: 10000 | AT8: =$AS$8 | AU8: =$AS$8 | AV8: =$AS$8 | AW8: =$AS$8 | AX8: =$AS$8 | AY8: =$AS$8 | AZ8: =$AS$8 | BA8: =$AS$8 | ... BD8: =$AS$8 | BE8: =SUM(AS8:BD8) | BF8: 1 | BG8: 12000 | BH8: =$BG$8 | BI8: =$BG$8 | BJ8: =$BG$8 | BK8: =$BG$8 | BL8: =$BG$8 | BM8: =$BG$8 | BN8: =$BG$8 | BO8: =$BG$8 | ... BR8: =$BG$8 | BS8: =SUM(BG8:BR8) | BT8: 1 | BU8: 12000 | BV8: =$BG$8 | BW8: =$BG$8 | BX8: =$BG$8 | BY8: =$BG$8 | BZ8: =$BG$8 | CA8: =$BG$8 | CB8: =$BG$8 | CC8: =$BG$8 | ... CF8: =$BG$8 | CG8: =SUM(BU8:CF8) | CH8: 1
A9: CFO Accting | C9: 0 | D9: =$C$9 | E9: =$C$9 | F9: =$C$9 | G9: =$C$9 | H9: =$C$9 | I9: =$C$9 | J9: =$C$9 | K9: =$C$9 | ... N9: =$C$9 | O9: =SUM(J9:N9) | Q9: 0 | R9: 0 | S9: 0 | T9: 0 | U9: 0 | V9: 0 | W9: 0 | X9: 0 | Y9: 0 | Z9: 0 | AA9: 0 | AB9: 0 | AC9: =SUM(Q9:AB9) | AE9: 0 | AF9: =$AE$9 | AG9: =$AE$9 | AH9: =$AE$9 | AI9: =$AE$9 | AJ9: =$AE$9 | AK9: =$AE$9 | AL9: =$AE$9 | AM9: =$AE$9 | ... AP9: =$AE$9 | AQ9: =SUM(AE9:AP9) | AR9: 1 | AS9: 6000 | AT9: 6000 | AU9: 6000 | AV9: 6000 | AW9: 6000 | AX9: 6000 | AY9: 6000 | AZ9: 6000 | BA9: 6000 | BB9: 6000 | BC9: 6000 | BD9: 6000 | BE9: =SUM(AS9:BD9) | BF9: 1 | BG9: 6000 | BH9: =$BG$9 | BI9: =$BG$9 | BJ9: =$BG$9 | BK9: =$BG$9 | BL9: =$BG$9 | BM9: =$BG$9 | BN9: =$BG$9 | BO9: =$BG$9 | ... BR9: =$BG$9 | BS9: =SUM(BG9:BR9) | BT9: 1 | BU9: 6000 | BV9: =$BU$9 | BW9: =$BU$9 | BX9: =$BU$9 | BY9: =$BU$9 | BZ9: =$BU$9 | CA9: =$BU$9 | CB9: =$BU$9 | CC9: =$BU$9 | ... CF9: =$BU$9 | CG9: =SUM(BU9:CF9) | CH9: 1
A10: Product /Technology | C10: 10000 | D10: =C10 | E10: =D10 | F10: =E10 | G10: =F10 | H10: =G10 | I10: =H10 | J10: =I10 | K10: =J10 | ... N10: =M10 | O10: =SUM(C10:N10) | P10: 0.5 | Q10: 6500 | R10: 6500 | S10: 6500 | T10: 6500 | U10: 6500 | V10: 6500 | W10: 6500 | X10: 6500 | Y10: 6500 | Z10: 6500 | AA10: 6500 | AB10: 6500 | AC10: =SUM(Q10:AB10) | AD10: 1 | AE10: 7500 | AF10: =$AE$10 | AG10: 7500 | AH10: 7500 | AI10: 7500 | AJ10: 7500 | AK10: 7500 | AL10: 7500 | AM10: 7500 | AN10: 7500 | AO10: 7500 | AP10: 7500 | AQ10: =SUM(AE10:AP10) | AR10: 1 | AS10: 7000 | AT10: 7000 | AU10: 7000 | AV10: 7000 | AW10: 7000 | AX10: 7000 | AY10: 7000 | AZ10: 7000 | BA10: 7000 | BB10: 7000 | BC10: 7000 | BD10: 7000 | BE10: =SUM(AS10:BD10) | BF10: 1 | BG10: 7000 | BH10: =$BG$10 | BI10: =$BG$10 | BJ10: =$BG$10 | BK10: =$BG$10 | BL10: =$BG$10 | BM10: =$BG$10 | BN10: =$BG$10 | BO10: =$BG$10 | ... BR10: =$BG$10 | BS10: =SUM(BG10:BR10) | BT10: 1 | BU10: 7000 | BV10: =$BU$10 | BW10: =$BU$10 | BX10: =$BU$10 | BY10: =$BU$10 | BZ10: =$BU$10 | CA10: =$BU$10 | CB10: =$BU$10 | CC10: =$BU$10 | ... CF10: =$BU$10 | CG10: =SUM(BU10:CF10) | CH10: 1
A11: Operations | O11: =SUM(C11:N11)
A12: COO | C12: 3500 | D12: =$C$12 | E12: =$C$12 | F12: =$C$12 | G12: =$C$12 | H12: =$C$12 | I12: =$C$12 | J12: =$C$12 | K12: =$C$12 | ... N12: =$C$12 | O12: =SUM(C12:N12) | P12: 0.5 | Q12: 6500 | R12: =$Q$12 | S12: =$Q$12 | T12: =$Q$12 | U12: =$Q$12 | V12: =$Q$12 | W12: =$Q$12 | X12: =$Q$12 | Y12: =$Q$12 | ... AB12: =$Q$12 | AC12: =SUM(Q12:AB12) | AD12: 1 | AE12: 7500 | AF12: =$AE$12 | AG12: =$AE$12 | AH12: =$AE$12 | AI12: =$AE$12 | AJ12: =$AE$12 | AK12: =$AE$12 | AL12: =$AE$12 | AM12: =$AE$12 | ... AP12: =$AE$12 | AQ12: =SUM(AE12:AP12) | AR12: 1 | AS12: 7500 | AT12: =$AS$12 | AU12: =$AS$12 | AV12: =$AS$12 | AW12: =$AS$12 | AX12: =$AS$12 | AY12: =$AS$12 | AZ12: =$AS$12 | BA12: =$AS$12 | ... BD12: =$AS$12 | BE12: =SUM(AS12:BD12) | BF12: 1 | BG12: 6500 | BH12: =$BG$12 | BI12: =$BG$12 | BJ12: =$BG$12 | BK12: =$BG$12 | BL12: =$BG$12 | BM12: =$BG$12 | BN12: =$BG$12 | BO12: =$BG$12 | ... BR12: =$BG$12 | BS12: =SUM(BG12:BR12) | BT12: 1 | BU12: 6500 | BV12: =$BG$12 | BW12: =$BG$12 | BX12: =$BG$12 | BY12: =$BG$12 | BZ12: =$BG$12 | CA12: =$BG$12 | CB12: =$BG$12 | CC12: =$BG$12 | ... CF12: =$BG$12 | CG12: =SUM(BU12:CF12) | CH12: 1
A13: Customer Success | C13: 0 | D13: 0 | E13: 0 | F13: 0 | G13: 0 | H13: 0 | I13: 0 | J13: 0 | K13: 0 | L13: 0 | M13: 0 | N13: 0 | O13: =SUM(C13:N13) | Q13: 3000 | R13: =$Q$13 | S13: =$Q$13 | T13: =$Q$13 | U13: =$Q$13 | V13: =$Q$13 | W13: =$Q$13 | X13: =$Q$13 | Y13: =$Q$13 | ... AB13: =$Q$13 | AC13: =SUM(Q13:AB13) | AD13: 1 | AE13: 6000 | AF13: =$AE$13 | AG13: =$AE$13 | AH13: =$AE$13 | AI13: =$AE$13 | AJ13: =$AE$13 | AK13: =$AE$13 | AL13: =$AE$13 | AM13: =$AE$13 | ... AP13: =$AE$13 | AQ13: =SUM(AE13:AP13) | AR13: 2 | AS13: 6000 | AT13: =$AS$13 | AU13: =$AS$13 | AV13: =$AS$13 | AW13: =$AS$13 | AX13: =$AS$13 | AY13: =$AS$13 | AZ13: =$AS$13 | BA13: =$AS$13 | ... BD13: =$AS$13 | BE13: =SUM(AS13:BD13) | BF13: 2 | BG13: 6000 | BH13: =$BG$13 | BI13: =$BG$13 | BJ13: =$BG$13 | BK13: =$BG$13 | BL13: =$BG$13 | BM13: =$BG$13 | BN13: =$BG$13 | BO13: =$BG$13 | ... BR13: =$BG$13 | BS13: =SUM(BG13:BR13) | BT13: 3 | BU13: 6000 | BV13: =$BG$13 | BW13: =$BG$13 | BX13: =$BG$13 | BY13: =$BG$13 | BZ13: =$BG$13 | CA13: =$BG$13 | CB13: =$BG$13 | CC13: =$BG$13 | ... CF13: =$BG$13 | CG13: =SUM(BU13:CF13) | CH13: 3
A14: Project Management & Deployment | C14: 2000 | D14: =$C$14 | E14: =$C$14 | F14: =$C$14 | G14: =$C$14 | H14: =$C$14 | I14: =$C$14 | J14: =$C$14 | K14: =$C$14 | ... N14: =$C$14 | O14: =SUM(C14:N14) | P14: 0.5 | Q14: 2000 | R14: 2000 | S14: 2000 | T14: 2000 | U14: 2000 | V14: 2000 | W14: 2000 | X14: 2000 | Y14: 2000 | Z14: 2000 | AA14: 2000 | AB14: 2000 | AC14: =SUM(Q14:AB14) | AD14: 1 | AE14: 2000 | AF14: 2000 | AG14: 2000 | AH14: 2000 | AI14: 2000 | AJ14: 2000 | AK14: 2000 | AL14: 2000 | AM14: 2000 | AN14: 2000 | AO14: 2000 | AP14: 2000 | AQ14: =SUM(AE14:AP14) | AR14: 1 | AS14: 2000 | AT14: =$AS$14 | AU14: =$AS$14 | AV14: =$AS$14 | AW14: =$AS$14 | AX14: =$AS$14 | AY14: =$AS$14 | AZ14: =$AS$14 | BA14: =$AS$14 | ... BD14: =$AS$14 | BE14: =SUM(AS14:BD14) | BF14: 1 | BG14: 2000 | BH14: 2000 | BI14: 2000 | BJ14: 2000 | BK14: 2000 | BL14: 2000 | BM14: 2000 | BN14: 2000 | BO14: 2000 | BP14: 2000 | BQ14: 2000 | BR14: 2000 | BS14: =SUM(BG14:BR14) | BT14: 1 | BU14: 2000 | BV14: =$BU$14 | BW14: =$BU$14 | BX14: =$BU$14 | BY14: =$BU$14 | BZ14: =$BU$14 | CA14: =$BU$14 | CB14: =$BU$14 | CC14: =$BU$14 | ... CF14: =$BU$14 | CG14: =SUM(BU14:CF14) | CH14: 1
A15: Marketing / Revenue | U15: =$Q$15 | V15: =$Q$15 | W15: =$Q$15 | X15: =$Q$15 | Y15: =$Q$15 | Z15: =$Q$15 | AA15: =$Q$15 | AB15: =$Q$15 | AH15: =$AE$15 | AI15: =$AE$15 | AJ15: =$AE$15 | AK15: =$AE$15 | AL15: =$AE$15 | AM15: =$AE$15 | AN15: =$AE$15 | AO15: =$AE$15 | AP15: =$AE$15 | AT15: =$AS$15 | AU15: =$AS$15 | AV15: =$AS$15 | AW15: =$AS$15 | AX15: =$AS$15 | AY15: =$AS$15 | AZ15: =$AS$15 | BA15: =$AS$15 | ... BD15: =$AS$15 | BI15: =$BG$15 | BJ15: =$BG$15 | BK15: =$BG$15 | BL15: =$BG$15 | BM15: =$BG$15 | BN15: =$BG$15 | BO15: =$BG$15 | BP15: =$BG$15 | ... BR15: =$BG$15 | BW15: =$BG$15 | BX15: =$BG$15 | BY15: =$BG$15 | BZ15: =$BG$15 | CA15: =$BG$15 | CB15: =$BG$15 | CC15: =$BG$15 | CD15: =$BG$15 | ... CF15: =$BG$15
A16: Head of Commercial | C16: 5000 | D16: =$C$16 | E16: =$C$16 | F16: =$C$16 | G16: =$C$16 | H16: =$C$16 | I16: =$C$16 | J16: =$C$16 | K16: =$C$16 | ... N16: =$C$16 | O16: =SUM(C16:N16) | P16: 0.5 | Q16: 4000 | R16: =$Q$16 | S16: =$Q$16 | T16: =$Q$16 | U16: =$Q$16 | V16: =$Q$16 | W16: =$Q$16 | X16: =$Q$16 | Y16: =$Q$16 | ... AB16: =$Q$16 | AC16: =SUM(Q16:AB16) | AD16: 1 | AE16: 4000 | AF16: =$AE$16 | AG16: =$AE$16 | AH16: =$AE$16 | AI16: =$AE$16 | AJ16: =$AE$16 | AK16: =$AE$16 | AL16: =$AE$16 | AM16: =$AE$16 | ... AP16: =$AE$16 | AQ16: =SUM(AE16:AP16) | AR16: 1 | AS16: 4000 | AT16: =$AS$16 | AU16: =$AS$16 | AV16: =$AS$16 | AW16: =$AS$16 | AX16: =$AS$16 | AY16: =$AS$16 | AZ16: =$AS$16 | BA16: =$AS$16 | ... BD16: =$AS$16 | BE16: =SUM(AS16:BD16) | BF16: 1 | BG16: 3000 | BH16: =$BG$16 | BI16: =$BG$16 | BJ16: =$BG$16 | BK16: =$BG$16 | BL16: =$BG$16 | BM16: =$BG$16 | BN16: =$BG$16 | BO16: =$BG$16 | ... BR16: =$BG$16 | BS16: =SUM(BG16:BR16) | BT16: 1 | BU16: 3000 | BV16: =$BG$16 | BW16: =$BG$16 | BX16: =$BG$16 | BY16: =$BG$16 | BZ16: =$BG$16 | CA16: =$BG$16 | CB16: =$BG$16 | CC16: =$BG$16 | ... CF16: =$BG$16 | CG16: =SUM(BU16:CF16) | CH16: 1
A17: Marketing Director | C17: 0 | D17: 0 | E17: 0 | F17: 0 | G17: 0 | H17: 0 | I17: 0 | J17: 0 | K17: 0 | L17: 0 | M17: 0 | N17: 0 | O17: =SUM(C17:N17) | Q17: 2000 | R17: =$Q$17 | S17: =$Q$17 | T17: =$Q$17 | U17: =$Q$17 | V17: =$Q$17 | W17: =$Q$17 | X17: =$Q$17 | Y17: =$Q$17 | ... AB17: =$Q$17 | AC17: =SUM(Q17:AB17) | AD17: 0.5 | AE17: 2000 | AF17: =$AE$17 | AG17: =$AE$17 | AH17: =$AE$17 | AI17: =$AE$17 | AJ17: =$AE$17 | AK17: =$AE$17 | AL17: =$AE$17 | AM17: =$AE$17 | ... AP17: =$AE$17 | AQ17: =SUM(AE17:AP17) | AR17: 1 | AS17: 2000 | AT17: =$AS$17 | AU17: =$AS$17 | AV17: =$AS$17 | AW17: =$AS$17 | AX17: =$AS$17 | AY17: =$AS$17 | AZ17: =$AS$17 | BA17: =$AS$17 | ... BD17: =$AS$17 | BE17: =SUM(AS17:BD17) | BF17: 1 | BG17: 2000 | BH17: =$BG$17 | BI17: =$BG$17 | BJ17: =$BG$17 | BK17: =$BG$17 | BL17: =$BG$17 | BM17: =$BG$17 | BN17: =$BG$17 | BO17: =$BG$17 | ... BR17: =$BG$17 | BS17: =SUM(BG17:BR17) | BT17: 1 | BU17: 2000 | BV17: =$BG$17 | BW17: =$BG$17 | BX17: =$BG$17 | BY17: =$BG$17 | BZ17: =$BG$17 | CA17: =$BG$17 | CB17: =$BG$17 | CC17: =$BG$17 | ... CF17: =$BG$17 | CG17: =SUM(BU17:CF17) | CH17: 1
A18: Sales- Vertical Specialist- Hospitality | C18: 0 | D18: 0 | E18: 0 | F18: 0 | G18: 0 | H18: 0 | I18: 0 | J18: 0 | K18: 0 | L18: 0 | M18: 0 | N18: 0 | O18: =SUM(C18:N18) | Q18: 4000 | R18: =$Q$18 | S18: =$Q$18 | T18: =$Q$18 | U18: =$Q$18 | V18: =$Q$18 | W18: =$Q$18 | X18: =$Q$18 | Y18: =$Q$18 | ... AB18: =$Q$18 | AC18: =SUM(Q18:AB18) | AD18: 0.5 | AE18: 4000 | AF18: =$AE$18 | AG18: =$AE$18 | AH18: =$AE$18 | AI18: =$AE$18 | AJ18: =$AE$18 | AK18: =$AE$18 | AL18: =$AE$18 | AM18: =$AE$18 | ... AP18: =$AE$18 | AQ18: =SUM(AE18:AP18) | AR18: 0.5 | AS18: 4000 | AT18: =$AS$18 | AU18: =$AS$18 | AV18: =$AS$18 | AW18: =$AS$18 | AX18: =$AS$18 | AY18: =$AS$18 | AZ18: =$AS$18 | BA18: =$AS$18 | ... BD18: =$AS$18 | BE18: =SUM(AS18:BD18) | BF18: 1 | BG18: 4000 | BH18: =$BG$18 | BI18: =$BG$18 | BJ18: =$BG$18 | BK18: =$BG$18 | BL18: =$BG$18 | BM18: =$BG$18 | BN18: =$BG$18 | BO18: =$BG$18 | ... BR18: =$BG$18 | BS18: =SUM(BG18:BR18) | BT18: 1 | BU18: 4000 | BV18: =$BG$18 | BW18: =$BG$18 | BX18: =$BG$18 | BY18: =$BG$18 | BZ18: =$BG$18 | CA18: =$BG$18 | CB18: =$BG$18 | CC18: =$BG$18 | ... CF18: =$BG$18 | CG18: =SUM(BU18:CF18) | CH18: 1
A19: Sales- Vertical Specialist- Real Estate | C19: 0 | D19: 0 | E19: 0 | F19: 0 | G19: 0 | H19: 0 | I19: 0 | J19: 0 | K19: 0 | L19: 0 | M19: 0 | N19: 0 | O19: =SUM(C19:N19) | Q19: 0 | R19: =$Q$20 | S19: =$Q$20 | T19: =$Q$20 | U19: =$Q$20 | V19: =$Q$20 | W19: =$Q$20 | X19: =$Q$20 | Y19: =$Q$20 | ... AB19: =$Q$20 | AC19: =SUM(Q19:AB19) | AE19: 4000 | AF19: 4000 | AG19: 4000 | AH19: 4000 | AI19: 4000 | AJ19: 4000 | AK19: 4000 | AL19: 4000 | AM19: 4000 | AN19: 4000 | AO19: 4000 | AP19: 4000 | AQ19: =SUM(AE19:AP19) | AR19: 1 | AS19: 4000 | AT19: =AS19 | AU19: =AT19 | AV19: =AU19 | AW19: =AV19 | AX19: =AW19 | AY19: =AX19 | AZ19: =AY19 | BA19: =AZ19 | ... BD19: =BC19 | BE19: =SUM(AS19:BD19) | BF19: 1 | BG19: 4000 | BH19: =$BG$20 | BI19: =$BG$20 | BJ19: =$BG$20 | BK19: =$BG$20 | BL19: =$BG$20 | BM19: =$BG$20 | BN19: =$BG$20 | BO19: =$BG$20 | ... BR19: =$BG$20 | BS19: =SUM(BG19:BR19) | BT19: 1 | BU19: 4000 | BV19: =$BG$20 | BW19: =$BG$20 | BX19: =$BG$20 | BY19: =$BG$20 | BZ19: =$BG$20 | CA19: =$BG$20 | CB19: =$BG$20 | CC19: =$BG$20 | ... CF19: =$BG$20 | CG19: =SUM(BU19:CF19) | CH19: 1
A20: Sales- Vertical Specialist- Small Firms | C20: 0 | D20: 0 | E20: 0 | F20: 0 | G20: 0 | H20: 0 | I20: 0 | J20: 0 | K20: 0 | L20: 0 | M20: 0 | N20: 0 | O20: 0 | Q20: 0 | R20: =$Q$20 | S20: =$Q$20 | T20: =$Q$20 | U20: =$Q$20 | V20: =$Q$20 | W20: =$Q$20 | X20: =$Q$20 | Y20: =$Q$20 | ... AB20: =$Q$20 | AC20: =SUM(Q20:AB20) | AE20: 0 | AF20: =$AE$20 | AG20: =$AE$20 | AH20: =$AE$20 | AI20: =$AE$20 | AJ20: =$AE$20 | AK20: =$AE$20 | AL20: =$AE$20 | AM20: =$AE$20 | ... AP20: =$AE$20 | AQ20: =SUM(AE20:AP20) | AS20: 0 | AT20: =AS20 | AU20: =AT20 | AV20: =AU20 | AW20: =AV20 | AX20: =AW20 | AY20: =AX20 | AZ20: =AY20 | BA20: =AZ20 | ... BD20: =BC20 | BE20: =SUM(AS20:BD20) | BF20: 0 | BG20: 4000 | BH20: =BG20 | BI20: =BH20 | BJ20: =BI20 | BK20: =BJ20 | BL20: =BK20 | BM20: =BL20 | BN20: =BM20 | BO20: =BN20 | ... BR20: =BQ20 | BS20: =SUM(BG20:BR20) | BT20: 1 | BU20: 4000 | BV20: =$BU$20 | BW20: =$BU$20 | BX20: =$BU$20 | BY20: =$BU$20 | BZ20: =$BU$20 | CA20: =$BU$20 | CB20: =$BU$20 | CC20: =$BU$20 | ... CF20: =$BU$20 | CG20: =SUM(BU20:CF20) | CH20: 1
A21: Sales- Vertical Specialist- Pharma | C21: 0 | D21: 0 | E21: 0 | F21: 0 | G21: 0 | H21: 0 | I21: 0 | J21: 0 | K21: 0 | L21: 0 | M21: 0 | N21: 0 | O21: =SUM(C21:N21) | Q21: 0 | R21: =$Q$22 | S21: =$Q$22 | T21: =$Q$22 | U21: =$Q$22 | V21: =$Q$22 | W21: =$Q$22 | X21: =$Q$22 | Y21: =$Q$22 | ... AB21: =$Q$22 | AC21: =SUM(Q21:AB21) | AE21: 0 | AF21: =$AE$21 | AG21: =$AE$21 | AH21: =$AE$21 | AI21: =$AE$21 | AJ21: =$AE$21 | AK21: =$AE$21 | AL21: =$AE$21 | AM21: =$AE$21 | ... AP21: =$AE$21 | AQ21: =SUM(AE21:AP21) | AS21: 4000 | AT21: =$AS$21 | AU21: =AT21 | AV21: =AU21 | AW21: =AV21 | AX21: =AW21 | AY21: =AX21 | AZ21: =AY21 | BA21: =AZ21 | BB21: =BA21 | ... BD21: =BC21 | BE21: =SUM(AS21:BD21) | BF21: 1 | BG21: 4000 | BH21: =$BG$21 | BI21: =BH21 | BJ21: =BI21 | BK21: =BJ21 | BL21: =BK21 | BM21: =BL21 | BN21: =BM21 | BO21: =BN21 | BP21: =BO21 | ... BR21: =BQ21 | BS21: =SUM(BG21:BR21) | BT21: 1 | BU21: 4000 | BV21: =$BU$21 | BW21: =$BU$21 | BX21: =$BU$21 | BY21: =$BU$21 | BZ21: =$BU$21 | CA21: =$BU$21 | CB21: =$BU$21 | CC21: =$BU$21 | ... CF21: =$BU$21 | CG21: =SUM(BU21:CF21) | CH21: 1
A22: Trainer | C22: 0 | D22: 0 | E22: 0 | F22: 0 | G22: 0 | H22: 0 | I22: 0 | J22: 0 | K22: 0 | L22: 0 | M22: 0 | N22: 0 | O22: =SUM(C22:N22) | Q22: 0 | R22: =$Q$22 | S22: =$Q$22 | T22: =$Q$22 | U22: =$Q$22 | V22: =$Q$22 | W22: =$Q$22 | X22: =$Q$22 | Y22: =$Q$22 | ... AB22: =$Q$22 | AC22: =SUM(Q22:AB22) | AE22: 4000 | AF22: =$AE$22 | AG22: =$AE$22 | AH22: =$AE$22 | AI22: =$AE$22 | AJ22: =$AE$22 | AK22: =$AE$22 | AL22: =$AE$22 | AM22: =$AE$22 | ... AP22: =$AE$22 | AQ22: =SUM(AE22:AP22) | AS22: 4000 | AT22: =$AS$22 | AU22: =$AS$22 | AV22: =$AS$22 | AW22: =$AS$22 | AX22: =$AS$22 | AY22: =$AS$22 | AZ22: =$AS$22 | BA22: =$AS$22 | ... BD22: =$AS$22 | BE22: =SUM(AS22:BD22) | BF22: 1 | BG22: 4000 | BH22: =$BG$22 | BI22: =$BG$22 | BJ22: =$BG$22 | BK22: =$BG$22 | BL22: =$BG$22 | BM22: =$BG$22 | BN22: =$BG$22 | BO22: =$BG$22 | ... BR22: =$BG$22 | BS22: =SUM(BG22:BR22) | BT22: 1 | BU22: 4000 | BV22: =$BG$22 | BW22: =$BG$22 | BX22: =$BG$22 | BY22: =$BG$22 | BZ22: =$BG$22 | CA22: =$BG$22 | CB22: =$BG$22 | CC22: =$BG$22 | ... CF22: =$BG$22 | CG22: =SUM(BU22:CF22) | CH22: 1
A23: Accting / Bookkeeping | C23: 3000 | D23: =$C$23 | E23: =$C$23 | F23: =$C$23 | G23: =$C$23 | H23: =$C$23 | I23: =$C$23 | J23: =$C$23 | K23: =$C$23 | ... N23: =$C$23 | O23: =SUM(C23:N23) | P23: 0.5 | Q23: 2500 | R23: =$Q$23 | S23: =$Q$23 | T23: =$Q$23 | U23: =$Q$23 | V23: =$Q$23 | W23: =$Q$23 | X23: =$Q$23 | Y23: =$Q$23 | ... AB23: =$Q$23 | AC23: =SUM(Q23:AB23) | AD23: 0.5 | AE23: 2500 | AF23: =$AE$23 | AG23: =$AE$23 | AH23: =$AE$23 | AI23: =$AE$23 | AJ23: =$AE$23 | AK23: =$AE$23 | AL23: =$AE$23 | AM23: =$AE$23 | ... AP23: =$AE$23 | AQ23: =SUM(AE23:AP23) | AR23: 0.5 | AS23: 2500 | AT23: =$AS$23 | AU23: =$AS$23 | AV23: =$AS$23 | AW23: =$AS$23 | AX23: =$AS$23 | AY23: =$AS$23 | AZ23: =$AS$23 | BA23: =$AS$23 | ... BD23: =$AS$23 | BE23: =SUM(AS23:BD23) | BF23: 1 | BG23: 2500 | BH23: =$BG$23 | BI23: =$BG$23 | BJ23: =$BG$23 | BK23: =$BG$23 | BL23: =$BG$23 | BM23: =$BG$23 | BN23: =$BG$23 | BO23: =$BG$23 | ... BR23: =$BG$23 | BS23: =SUM(BG23:BR23) | BT23: 1 | BU23: 2500 | BV23: =$BG$23 | BW23: =$BG$23 | BX23: =$BG$23 | BY23: =$BG$23 | BZ23: =$BG$23 | CA23: =$BG$23 | CB23: =$BG$23 | CC23: =$BG$23 | ... CF23: =$BG$23 | CG23: =SUM(BU23:CF23) | CH23: 1
A24: Business Analyst | C24: 0 | D24: =$C$24 | E24: =$C$24 | F24: =$C$24 | G24: =$C$24 | H24: =$C$24 | I24: =$C$24 | J24: =$C$24 | K24: =$C$24 | ... N24: =$C$24 | O24: =SUM(C24:N24) | Q24: 1000 | R24: =$Q$24 | S24: =$Q$24 | T24: =$Q$24 | U24: =$Q$24 | V24: =$Q$24 | W24: =$Q$24 | X24: =$Q$24 | Y24: =$Q$24 | ... AB24: =$Q$24 | AC24: =SUM(Q24:AB24) | AD24: 1 | AE24: 2500 | AF24: =$AE$24 | AG24: =$AE$24 | AH24: =$AE$24 | AI24: =$AE$24 | AJ24: =$AE$24 | AK24: =$AE$24 | AL24: =$AE$24 | AM24: =$AE$24 | ... AP24: =$AE$24 | AQ24: 2500 | AR24: 1 | AS24: 2500 | AT24: =$AS$24 | AU24: =$AS$24 | AV24: =$AS$24 | AW24: =$AS$24 | AX24: =$AS$24 | AY24: =$AS$24 | AZ24: =$AS$24 | BA24: =$AS$24 | ... BD24: =$AS$24 | BE24: 2500 | BF24: 1 | BG24: 2500 | BH24: =$BG$24 | BI24: =$BG$24 | BJ24: =$BG$24 | BK24: =$BG$24 | BL24: =$BG$24 | BM24: =$BG$24 | BN24: =$BG$24 | BO24: =$BG$24 | ... BR24: =$BG$24 | BS24: 2500 | BT24: 1 | BU24: 2500 | BV24: =$BG$24 | BW24: =$BG$24 | BX24: =$BG$24 | BY24: =$BG$24 | BZ24: =$BG$24 | CA24: =$BG$24 | CB24: =$BG$24 | CC24: =$BG$24 | ... CF24: =$BG$24 | CG24: 2500 | CH24: 0.5
A25: Other- Virtual Assistant | C25: 500 | D25: =$C$25 | E25: =$C$25 | F25: =$C$25 | G25: =$C$25 | H25: =$C$25 | I25: =$C$25 | J25: =$C$25 | K25: =$C$25 | ... N25: =$C$25 | O25: =SUM(C25:N25) | P25: 0.5 | Q25: 500 | R25: =$Q$25 | S25: =$Q$25 | T25: =$Q$25 | U25: =$Q$25 | V25: =$Q$25 | W25: =$Q$25 | X25: =$Q$25 | Y25: =$Q$25 | ... AB25: =$Q$25 | AC25: =SUM(Q25:AB25) | AD25: 0.5 | AE25: 500 | AF25: =$AE$25 | AG25: =$AE$25 | AH25: =$AE$25 | AI25: =$AE$25 | AJ25: =$AE$25 | AK25: =$AE$25 | AL25: =$AE$25 | AM25: =$AE$25 | ... AP25: =$AE$25 | AQ25: =SUM(AE25:AP25) | AR25: 0.5 | AS25: 500 | AT25: =$AS$25 | AU25: =$AS$25 | AV25: =$AS$25 | AW25: =$AS$25 | AX25: =$AS$25 | AY25: =$AS$25 | AZ25: =$AS$25 | BA25: =$AS$25 | ... BD25: =$AS$25 | BE25: =SUM(AS25:BD25) | BF25: 0.5 | BG25: 1000 | BH25: =$BG$25 | BI25: =$BG$25 | BJ25: =$BG$25 | BK25: =$BG$25 | BL25: =$BG$25 | BM25: =$BG$25 | BN25: =$BG$25 | BO25: =$BG$25 | ... BR25: =$BG$25 | BS25: =SUM(BG25:BR25) | BT25: 0.5 | BU25: 100 | BV25: =$BG$25 | BW25: =$BG$25 | BX25: =$BG$25 | BY25: =$BG$25 | BZ25: =$BG$25 | CA25: =$BG$25 | CB25: =$BG$25 | CC25: =$BG$25 | ... CF25: =$BG$25 | CG25: =SUM(BU25:CF25) | CH25: 1
C26: =SUM(C8:C25) | D26: =SUM(D8:D24) | E26: =SUM(E8:E24) | F26: =SUM(F8:F24) | G26: =SUM(G8:G24) | H26: =SUM(H8:H24) | I26: =SUM(I8:I24) | J26: =SUM(J8:J24) | K26: =SUM(K8:K24) | ... O26: =SUM(O8:O24) | Q26: =SUM(Q8:Q25) | R26: =SUM(R8:R24) | S26: =SUM(S8:S24) | T26: =SUM(T8:T24) | U26: =SUM(U8:U24) | V26: =SUM(V8:V24) | W26: =SUM(W8:W24) | X26: =SUM(X8:X24) | Y26: =SUM(Y8:Y24) | ... AC26: =SUM(AC8:AC24) | AE26: =SUM(AE8:AE25) | AF26: =SUM(AF8:AF25) | AG26: =SUM(AG8:AG25) | AH26: =SUM(AH8:AH25) | AI26: =SUM(AI8:AI25) | AJ26: =SUM(AJ8:AJ25) | AK26: =SUM(AK8:AK25) | AL26: =SUM(AL8:AL25) | ... AP26: =SUM(AP8:AP25) | AQ26: =SUM(AQ8:AQ24) | AS26: =SUM(AS8:AS25) | AT26: =SUM(AT8:AT24) | AU26: =SUM(AU8:AU24) | AV26: =SUM(AV8:AV24) | AW26: =SUM(AW8:AW24) | AX26: =SUM(AX8:AX24) | AY26: =SUM(AY8:AY24) | AZ26: =SUM(AZ8:AZ24) | BA26: =SUM(BA8:BA24) | ... BE26: =SUM(BE8:BE24) | BG26: =SUM(BG8:BG25) | BH26: =SUM(BH8:BH24) | BI26: =SUM(BI8:BI24) | BJ26: =SUM(BJ8:BJ24) | BK26: =SUM(BK8:BK24) | BL26: =SUM(BL8:BL24) | BM26: =SUM(BM8:BM24) | BN26: =SUM(BN8:BN24) | BO26: =SUM(BO8:BO24) | ... BS26: =SUM(BS8:BS24) | BU26: =SUM(BU8:BU25) | BV26: =SUM(BV8:BV24) | BW26: =SUM(BW8:BW24) | BX26: =SUM(BX8:BX24) | BY26: =SUM(BY8:BY24) | BZ26: =SUM(BZ8:BZ24) | CA26: =SUM(CA8:CA24) | CB26: =SUM(CB8:CB24) | CC26: =SUM(CC8:CC24) | ... CG26: =SUM(CG8:CG24)
A27: FTE | P27: =SUM(P8:P26) | AD27: =SUM(AD8:AD26) | AR27: =SUM(AR8:AR26) | BF27: =SUM(BF8:BF25) | BT27: =SUM(BT8:BT25) | CH27: =SUM(CH8:CH25)
AO315: 1
AO316: 1
AO317: 1
AO318: 1
AO319: 1
AO320: 1
AO321: 1
AO322: 1
AO323: 1
AO324: 1
I406: 12
I407: =O25/I406
H408: 70000
H409: 12
H410: =H408/H409

Sheet Departmental Expenses
D2: 2025 | R2: 2026 | AF2: 2027 | AT2: 2028
D3: 45658 | E3: 45689 | F3: 45717 | G3: 45748 | H3: 45778 | I3: 45809 | J3: 45839 | K3: 45870 | L3: 45901 | M3: 45931 | N3: 45962 | O3: 45992 | P3: Total | R3: 46023 | S3: 46083 | T3: 46082 | U3: 46113 | V3: 46143 | W3: 46174 | X3: 46204 | Y3: 46235 | Z3: 13394 | AA3: 46296 | AB3: 46327 | AC3: 46357 | AD3: Total | AF3: 46388 | AG3: 46419 | AH3: 46447 | AI3: 46478 | AJ3: 46508 | AK3: 46539 | AL3: 46569 | AM3: 46600 | AN3: 46631 | AO3: 46661 | AP3: 46692 | AQ3: 46722 | AR3: Total | AT3: 46753 | AU3: 2/1/202 | AV3: 46813 | AW3: 46844 | AX3: 46874 | AY3: 46905 | AZ3: 46935 | BA3: 46966 | BB3: 46997 | BC3: 47027 | BD3: 47058 | BE3: 46722 | BF3: Total
A5: Sales and Marketing
A6: Branding | D6: 0 | E6: =$D$6 | F6: =$D$6 | G6: =$D$6 | H6: =$D$6 | I6: =$D$6 | J6: =$D$6 | K6: =$D$6 | L6: =$D$6 | ... O6: =$D$6 | P6: =SUM(D6:O6) | R6: 0 | S6: =$R$6 | T6: =$R$6 | U6: =$R$6 | V6: =$R$6 | W6: =$R$6 | X6: =$R$6 | Y6: =$R$6 | Z6: =$R$6 | ... AC6: =$R$6 | AD6: =SUM(R6:AC6) | AF6: 0 | AG6: =$AF$6 | AH6: =$AF$6 | AI6: =$AF$6 | AJ6: =$AF$6 | AK6: =$AF$6 | AL6: =$AF$6 | AM6: =$AF$6 | AN6: =$AF$6 | ... AQ6: =$AF$6 | AR6: =SUM(AF6:AQ6) | AT6: 0 | AU6: =$AT$6 | AV6: =$AT$6 | AW6: =$AT$6 | AX6: =$AT$6 | AY6: =$AT$6 | AZ6: =$AT$6 | BA6: =$AT$6 | BB6: =$AT$6 | ... BE6: =$AT$6 | BF6: =SUM(AT6:BE6)
A7: Messaging, Persona, | D7: 0 | E7: =$D$7 | F7: =$D$7 | G7: =$D$7 | H7: =$D$7 | I7: =$D$7 | J7: =$D$7 | K7: =$D$7 | L7: =$D$7 | ... O7: =$D$7 | P7: =SUM(D7:O7) | R7: 0 | S7: =$R$7 | T7: =$R$7 | U7: =$R$7 | V7: =$R$7 | W7: =$R$7 | X7: =$R$7 | Y7: =$R$7 | Z7: =$R$7 | ... AC7: =$R$7 | AD7: =SUM(R7:AC7) | AF7: 0 | AG7: =$AF$7 | AH7: =$AF$7 | AI7: =$AF$7 | AJ7: =$AF$7 | AK7: =$AF$7 | AL7: =$AF$7 | AM7: =$AF$7 | AN7: =$AF$7 | ... AQ7: =$AF$7 | AR7: =SUM(AF7:AQ7) | AT7: 0 | AU7: =$AT$7 | AV7: =$AT$7 | AW7: =$AT$7 | AX7: =$AT$7 | AY7: =$AT$7 | AZ7: =$AT$7 | BA7: =$AT$7 | BB7: =$AT$7 | ... BE7: =$AT$7 | BF7: =SUM(AT7:BE7)
A8: Website Development. (SEO, E Commerce Enablement) | D8: 0 | E8: =$D$8 | F8: =$D$8 | G8: =$D$8 | H8: =$D$8 | I8: =$D$8 | J8: =$D$8 | K8: =$D$8 | L8: =$D$8 | ... O8: =$D$8 | P8: =SUM(D8:O8) | R8: 0 | S8: =$R$8 | T8: =$R$8 | U8: =$R$8 | V8: =$R$8 | W8: =$R$8 | X8: =$R$8 | Y8: =$R$8 | Z8: =$R$8 | ... AC8: =$R$8 | AD8: =SUM(R8:AC8) | AF8: 0 | AG8: =$AF$8 | AH8: =$AF$8 | AI8: =$AF$8 | AJ8: =$AF$8 | AK8: =$AF$8 | AL8: =$AF$8 | AM8: =$AF$8 | AN8: =$AF$8 | ... AQ8: =$AF$8 | AR8: =SUM(AF8:AQ8) | AT8: 0 | AU8: =$AT$8 | AV8: =$AT$8 | AW8: =$AT$8 | AX8: =$AT$8 | AY8: =$AT$8 | AZ8: =$AT$8 | BA8: =$AT$8 | BB8: =$AT$8 | ... BE8: =$AT$8 | BF8: =SUM(AT8:BE8)
A9: Collateral by persona (3), Pitch, Digital One Page | D9: 0 | E9: =$D$9 | F9: =$D$9 | G9: =$D$9 | H9: =$D$9 | I9: =$D$9 | J9: =$D$9 | K9: =$D$9 | L9: =$D$9 | ... O9: =$D$9 | P9: =SUM(D9:O9) | R9: 0 | S9: =$R$9 | T9: =$R$9 | U9: =$R$9 | V9: =$R$9 | W9: =$R$9 | X9: =$R$9 | Y9: =$R$9 | Z9: =$R$9 | ... AC9: =$R$9 | AD9: =SUM(R9:AC9) | AF9: 0 | AG9: =$AF$9 | AH9: =$AF$9 | AI9: =$AF$9 | AJ9: =$AF$9 | AK9: =$AF$9 | AL9: =$AF$9 | AM9: =$AF$9 | AN9: =$AF$9 | ... AQ9: =$AF$9 | AR9: =SUM(AF9:AQ9) | AT9: 0 | AU9: =$AT$9 | AV9: =$AT$9 | AW9: =$AT$9 | AX9: =$AT$9 | AY9: =$AT$9 | AZ9: =$AT$9 | BA9: =$AT$9 | BB9: =$AT$9 | ... BE9: =$AT$9 | BF9: =SUM(AT9:BE9)
A10: Digital Marketing | D10: 0 | E10: =$D$10 | F10: =$D$10 | G10: =$D$10 | H10: =$D$10 | I10: =$D$10 | J10: =$D$10 | K10: =$D$10 | L10: =$D$10 | ... O10: =$D$10 | P10: =SUM(D10:O10) | R10: 0 | S10: =$R$10 | T10: =$R$10 | U10: =$R$10 | V10: =$R$10 | W10: =$R$10 | X10: =$R$10 | Y10: =$R$10 | Z10: =$R$10 | ... AC10: =$R$10 | AD10: =SUM(R10:AC10) | AF10: 0 | AG10: =$AF$10 | AH10: =$AF$10 | AI10: =$AF$10 | AJ10: =$AF$10 | AK10: =$AF$10 | AL10: =$AF$10 | AM10: =$AF$10 | AN10: =$AF$10 | ... AQ10: =$AF$10 | AR10: =SUM(AF10:AQ10) | AT10: 0 | AU10: =$AT$10 | AV10: =$AT$10 | AW10: =$AT$10 | AX10: =$AT$10 | AY10: =$AT$10 | AZ10: =$AT$10 | BA10: =$AT$10 | BB10: =$AT$10 | ... BE10: =$AT$10 | BF10: =SUM(AT10:BE10)
A11: Social Media Strategy | D11: 0 | E11: =$D$11 | F11: =$D$11 | G11: =$D$11 | H11: =$D$11 | I11: =$D$11 | J11: =$D$11 | K11: =$D$11 | L11: =$D$11 | ... O11: =$D$11 | P11: =SUM(D11:O11) | R11: 0 | S11: =$R$11 | T11: =$R$11 | U11: =$R$11 | V11: =$R$11 | W11: =$R$11 | X11: =$R$11 | Y11: =$R$11 | Z11: =$R$11 | ... AC11: =$R$11 | AD11: =SUM(R11:AC11) | AF11: 0 | AG11: =$AF$11 | AH11: =$AF$11 | AI11: =$AF$11 | AJ11: =$AF$11 | AK11: =$AF$11 | AL11: =$AF$11 | AM11: =$AF$11 | AN11: =$AF$11 | ... AQ11: =$AF$11 | AR11: =SUM(AF11:AQ11) | AT11: 3575 | AU11: =$AT$11 | AV11: =$AT$11 | AW11: =$AT$11 | AX11: =$AT$11 | AY11: =$AT$11 | AZ11: =$AT$11 | BA11: =$AT$11 | BB11: =$AT$11 | ... BE11: =$AT$11 | BF11: =SUM(AT11:BE11)
A12: Market fullfillment (SEM, e-mail, social, etc) | D12: 2175 | E12: =$D$12 | F12: =$D$12 | G12: =$D$12 | H12: =$D$12 | I12: =$D$12 | J12: =$D$12 | K12: =$D$12 | L12: =$D$12 | ... O12: =$D$12 | P12: =SUM(D12:O12) | R12: 2175 | S12: =$R$12 | T12: =$R$12 | U12: =$R$12 | V12: =$R$12 | W12: =$R$12 | X12: =$R$12 | Y12: =$R$12 | Z12: =$R$12 | ... AC12: =$R$12 | AD12: =SUM(R12:AC12) | AF12: 2175 | AG12: =$AF$12 | AH12: =$AF$12 | AI12: =$AF$12 | AJ12: =$AF$12 | AK12: =$AF$12 | AL12: =$AF$12 | AM12: =$AF$12 | AN12: =$AF$12 | ... AQ12: =$AF$12 | AR12: =SUM(AF12:AQ12) | AT12: 750 | AU12: =$AT$12 | AV12: =$AT$12 | AW12: =$AT$12 | AX12: =$AT$12 | AY12: =$AT$12 | AZ12: =$AT$12 | BA12: =$AT$12 | BB12: =$AT$12 | ... BE12: =$AT$12 | BF12: =SUM(AT12:BE12)
A13: Blog | D13: 500 | E13: =$D$13 | F13: =$D$13 | G13: =$D$13 | H13: =$D$13 | I13: =$D$13 | J13: =$D$13 | K13: =$D$13 | L13: =$D$13 | ... O13: =$D$13 | P13: =SUM(D13:O13) | R13: 500 | S13: =$R$13 | T13: =$R$13 | U13: =$R$13 | V13: =$R$13 | W13: =$R$13 | X13: =$R$13 | Y13: =$R$13 | Z13: =$R$13 | ... AC13: =$R$13 | AD13: =SUM(R13:AC13) | AF13: 500 | AG13: =$AF$13 | AH13: =$AF$13 | AI13: =$AF$13 | AJ13: =$AF$13 | AK13: =$AF$13 | AL13: =$AF$13 | AM13: =$AF$13 | AN13: =$AF$13 | ... AQ13: =$AF$13 | AR13: =SUM(AF13:AQ13) | AT13: 2000 | AU13: =$AT$13 | AV13: =$AT$13 | AW13: =$AT$13 | AX13: =$AT$13 | AY13: =$AT$13 | AZ13: =$AT$13 | BA13: =$AT$13 | BB13: =$AT$13 | ... BE13: =$AT$13 | BF13: =SUM(AT13:BE13)
A14: Account Based Marketing programming by customer | D14: 2000 | E14: =$D$14 | F14: =$D$14 | G14: =$D$14 | H14: =$D$14 | I14: =$D$14 | J14: =$D$14 | K14: =$D$14 | L14: =$D$14 | ... O14: =$D$14 | P14: =SUM(D14:O14) | R14: 2000 | S14: =$R$14 | T14: =$R$14 | U14: =$R$14 | V14: =$R$14 | W14: =$R$14 | X14: =$R$14 | Y14: =$R$14 | Z14: =$R$14 | ... AC14: =$R$14 | AD14: =SUM(R14:AC14) | AF14: 2000 | AG14: =$AF$14 | AH14: =$AF$14 | AI14: =$AF$14 | AJ14: =$AF$14 | AK14: =$AF$14 | AL14: =$AF$14 | AM14: =$AF$14 | AN14: =$AF$14 | ... AQ14: =$AF$14 | AR14: =SUM(AF14:AQ14) | AT14: 2000 | AU14: =$AT$14 | AV14: =$AT$14 | AW14: =$AT$14 | AX14: =$AT$14 | AY14: =$AT$14 | AZ14: =$AT$14 | BA14: =$AT$14 | BB14: =$AT$14 | ... BE14: =$AT$14 | BF14: =SUM(AT14:BE14)
A15: PR Firm | D15: 3000 | E15: =$D$15 | F15: =$D$15 | G15: =$D$15 | H15: =$D$15 | I15: =$D$15 | J15: =$D$15 | K15: =$D$15 | L15: =$D$15 | ... O15: =$D$15 | P15: =SUM(D15:O15) | R15: 2000 | S15: =$R$15 | T15: =$R$15 | U15: =$R$15 | V15: =$R$15 | W15: =$R$15 | X15: =$R$15 | Y15: =$R$15 | Z15: =$R$15 | ... AC15: =$R$15 | AD15: =SUM(R15:AC15) | AF15: 2000 | AG15: =$AF$15 | AH15: =$AF$15 | AI15: =$AF$15 | AJ15: =$AF$15 | AK15: =$AF$15 | AL15: =$AF$15 | AM15: =$AF$15 | AN15: =$AF$15 | ... AQ15: =$AF$15 | AR15: =SUM(AF15:AQ15) | AT15: 2000 | AU15: =$AT$15 | AV15: =$AT$15 | AW15: =$AT$15 | AX15: =$AT$15 | AY15: =$AT$15 | AZ15: =$AT$15 | BA15: =$AT$15 | BB15: =$AT$15 | ... BE15: =$AT$15 | BF15: =SUM(AT15:BE15)
A16: Client outreach | D16: 2000 | E16: =$D$16 | F16: =$D$16 | G16: =$D$16 | H16: =$D$16 | I16: =$D$16 | J16: =$D$16 | K16: =$D$16 | L16: =$D$16 | ... O16: =$D$16 | P16: =SUM(D16:O16) | R16: 2000 | S16: =$R$16 | T16: =$R$16 | U16: =$R$16 | V16: =$R$16 | W16: =$R$16 | X16: =$R$16 | Y16: =$R$16 | Z16: =$R$16 | ... AC16: =$R$16 | AD16: =SUM(R16:AC16) | AF16: 2000 | AG16: =$AF$16 | AH16: =$AF$16 | AI16: =$AF$16 | AJ16: =$AF$16 | AK16: =$AF$16 | AL16: =$AF$16 | AM16: =$AF$16 | AN16: =$AF$16 | ... AQ16: =$AF$16 | AR16: =SUM(AF16:AQ16) | AT16: 2000 | AU16: =$AT$16 | AV16: =$AT$16 | AW16: =$AT$16 | AX16: =$AT$16 | AY16: =$AT$16 | AZ16: =$AT$16 | BA16: =$AT$16 | BB16: =$AT$16 | ... BE16: =$AT$16 | BF16: =SUM(AT16:BE16)
A17: Customer Advisory | D17: 0 | E17: =$D$17 | F17: =$D$17 | G17: =$D$17 | H17: =$D$17 | I17: =$D$17 | J17: =$D$17 | K17: =$D$17 | L17: =$D$17 | ... O17: =$D$17 | P17: =SUM(D17:O17) | R17: 2000 | S17: =$R$17 | T17: =$R$17 | U17: =$R$17 | V17: =$R$17 | W17: =$R$17 | X17: =$R$17 | Y17: =$R$17 | Z17: =$R$17 | ... AC17: =$R$17 | AD17: =SUM(R17:AC17) | AF17: 2000 | AG17: =$AF$17 | AH17: =$AF$17 | AI17: =$AF$17 | AJ17: =$AF$17 | AK17: =$AF$17 | AL17: =$AF$17 | AM17: =$AF$17 | AN17: =$AF$17 | ... AQ17: =$AF$17 | AR17: =SUM(AF17:AQ17) | AT17: 2000 | AU17: =$AT$17 | AV17: =$AT$17 | AW17: =$AT$17 | AX17: =$AT$17 | AY17: =$AT$17 | AZ17: =$AT$17 | BA17: =$AT$17 | BB17: =$AT$17 | ... BE17: =$AT$17 | BF17: =SUM(AT17:BE17)
A18: Client Advisory | E18: 0 | F18: 0 | G18: 0 | H18: 0 | I18: 0 | J18: 5000 | K18: 0 | L18: 0 | M18: 0 | N18: 0 | O18: 5000 | P18: =SUM(D18:O18) | R18: 10000 | S18: 0 | T18: 0 | U18: 0 | V18: 0 | W18: 0 | X18: 5000 | Y18: 0 | Z18: 0 | AA18: 0 | AB18: 0 | AC18: 5000 | AD18: =SUM(R18:AC18) | AF18: 10000 | AG18: 0 | AH18: 0 | AI18: 0 | AJ18: 0 | AK18: 0 | AL18: 5000 | AM18: 0 | AN18: 0 | AO18: 0 | AP18: 0 | AQ18: 5000 | AR18: =SUM(AF18:AQ18) | AT18: 10000 | AU18: 0 | AV18: 0 | AW18: 0 | AX18: 0 | AY18: 0 | AZ18: 5000 | BA18: 0 | BB18: 0 | BC18: 0 | BD18: 0 | BE18: 5000 | BF18: =SUM(AT18:BE18)
D19: 0 | E19: =$D$19 | F19: =$D$19 | G19: =$D$19 | H19: =$D$19 | I19: =$D$19 | J19: =$D$19 | K19: =$D$19 | L19: =$D$19 | ... O19: =$D$19 | P19: =SUM(D19:O19) | R19: 0 | S19: =$R$19 | T19: =$R$19 | U19: =$R$19 | V19: =$R$19 | W19: =$R$19 | X19: =$R$19 | Y19: =$R$19 | Z19: =$R$19 | ... AC19: =$R$19 | AD19: =SUM(R19:AC19) | AF19: 0 | AG19: =$AF$19 | AH19: =$AF$19 | AI19: =$AF$19 | AJ19: =$AF$19 | AK19: =$AF$19 | AL19: =$AF$19 | AM19: =$AF$19 | AN19: =$AF$19 | ... AQ19: =$AF$19 | AR19: =SUM(AF19:AQ19) | AT19: 0 | AU19: =$AT$19 | AV19: =$AT$19 | AW19: =$AT$19 | AX19: =$AT$19 | AY19: =$AT$19 | AZ19: =$AT$19 | BA19: =$AT$19 | BB19: =$AT$19 | ... BE19: =$AT$19 | BF19: =SUM(AT19:BE19)
A20: Dues & Subscriptions | P20: - | AD20: - | AR20: - | BF20: =SUM(AT20:BE20)
A21: Adobe DC | N21: 180 | P21: 180 | AB21: 180 | AD21: 180 | AP21: 180 | AR21: 180 | BD21: 180 | BF21: =SUM(AT21:BE21)
A22: Adobe Stock | D22: 32 | E22: 32 | F22: 32 | G22: 32 | H22: 32 | I22: 32 | J22: 32 | K22: 32 | L22: 32 | M22: 32 | N22: 32 | O22: 32 | P22: 390 | R22: 32 | S22: 32 | T22: 32 | U22: 32 | V22: 32 | W22: 32 | X22: 32 | Y22: 32 | Z22: 32 | AA22: 32 | AB22: 32 | AC22: 32 | AD22: 390 | AF22: 32 | AG22: 32 | AH22: 32 | AI22: 32 | AJ22: 32 | AK22: 32 | AL22: 32 | AM22: 32 | AN22: 32 | AO22: 32 | AP22: 32 | AQ22: 32 | AR22: 390 | AT22: 32 | AU22: 32 | AV22: 32 | AW22: 32 | AX22: 32 | AY22: 32 | AZ22: 32 | BA22: 32 | BB22: 32 | BC22: 32 | BD22: 32 | BE22: 32 | BF22: =SUM(AT22:BE22)
A23: Adobe Illustrator | D23: 34 | E23: 34 | F23: 34 | G23: 34 | H23: 34 | I23: 34 | J23: 34 | K23: 34 | L23: 34 | M23: 34 | N23: 34 | O23: 34 | P23: 409 | R23: 34 | S23: 34 | T23: 34 | U23: 34 | V23: 34 | W23: 34 | X23: 34 | Y23: 34 | Z23: 34 | AA23: 34 | AB23: 34 | AC23: 34 | AD23: 409 | AF23: 34 | AG23: 34 | AH23: 34 | AI23: 34 | AJ23: 34 | AK23: 34 | AL23: 34 | AM23: 34 | AN23: 34 | AO23: 34 | AP23: 34 | AQ23: 34 | AR23: 409 | AT23: 34 | AU23: 34 | AV23: 34 | AW23: 34 | AX23: 34 | AY23: 34 | AZ23: 34 | BA23: 34 | BB23: 34 | BC23: 34 | BD23: 34 | BE23: 34 | BF23: =SUM(AT23:BE23)
A24: Hightail | K24: 180 | P24: 180 | Y24: 180 | AD24: 180 | AM24: 180 | AR24: 180 | BA24: 180 | BF24: =SUM(AT24:BE24)
A25: Zoom | F25: 150 | P25: 150 | T25: 150 | AD25: 150 | AH25: 150 | AR25: 150 | AV25: 150 | BF25: =SUM(AT25:BE25)
A26: Typeform | E26: - | F26: - | G26: - | H26: - | I26: 350 | J26: - | K26: - | L26: - | M26: - | N26: - | O26: - | P26: 350 | S26: - | T26: - | U26: - | V26: - | W26: 350 | X26: - | Y26: - | Z26: - | AA26: - | AB26: - | AC26: - | AD26: 350 | AG26: - | AH26: - | AI26: - | AJ26: - | AK26: 350 | AL26: - | AM26: - | AN26: - | AO26: - | AP26: - | AQ26: - | AR26: 350 | AU26: - | AV26: - | AW26: - | AX26: - | AY26: 350 | AZ26: - | BA26: - | BB26: - | BC26: - | BD26: - | BE26: - | BF26: =SUM(AT26:BE26)
A27: Canva | E27: - | F27: - | G27: 120 | H27: - | I27: - | J27: - | K27: - | L27: - | M27: - | N27: - | O27: - | P27: 120 | S27: - | T27: - | U27: 120 | V27: - | W27: - | X27: - | Y27: - | Z27: - | AA27: - | AB27: - | AC27: - | AD27: 120 | AG27: - | AH27: - | AI27: 120 | AJ27: - | AK27: - | AL27: - | AM27: - | AN27: - | AO27: - | AP27: - | AQ27: - | AR27: 120 | AU27: - | AV27: - | AW27: 120 | AX27: - | AY27: - | AZ27: - | BA27: - | BB27: - | BC27: - | BD27: - | BE27: - | BF27: =SUM(AT27:BE27)
A28: Headspace | L28: 72 | P28: 72 | Z28: 72 | AD28: 72 | AN28: 72 | AR28: 72 | BB28: 72 | BF28: =SUM(AT28:BE28)
A29: HBR | M29: 120 | P29: 120 | AA29: 120 | AD29: 120 | AO29: 120 | AR29: 120 | BC29: 120 | BF29: =SUM(AT29:BE29)
A30: Slide Team | D30: 0 | E30: 0 | F30: 0 | G30: 142 | H30: 0 | I30: 0 | J30: 0 | K30: 142 | L30: 0 | M30: 0 | N30: 0 | O30: 0 | P30: =SUM(D30:O30) | R30: 0 | S30: 0 | T30: 0 | U30: 142 | V30: 0 | W30: 0 | X30: 0 | Y30: 142 | Z30: 0 | AA30: 0 | AB30: 0 | AC30: 0 | AD30: =SUM(R30:AC30) | AF30: 0 | AG30: 0 | AH30: 0 | AI30: 142 | AJ30: 0 | AK30: 0 | AL30: 0 | AM30: 142 | AN30: 0 | AO30: 0 | AP30: 0 | AQ30: 0 | AR30: =SUM(AF30:AQ30) | AT30: 0 | AU30: 0 | AV30: 0 | AW30: 142 | AX30: 0 | AY30: 0 | AZ30: 0 | BA30: 142 | BB30: 0 | BC30: 0 | BD30: 0 | BE30: 0 | BF30: =SUM(AT30:BE30)
A31: Masterclass | F31: 179 | P31: 179 | T31: 179 | AD31: 179 | AH31: 179 | AR31: 179 | AV31: 179 | BF31: =SUM(AT31:BE31)
A32: Programs | BF32: =SUM(AT32:BE32)
A33: HubSpot | D33: 800 | E33: 800 | F33: 800 | G33: 800 | H33: 800 | I33: 800 | J33: 800 | K33: 800 | L33: 800 | M33: 800 | N33: 800 | O33: 800 | P33: =SUM(D33:O33) | R33: 800 | S33: 800 | T33: 800 | U33: 800 | V33: 800 | W33: 800 | X33: 800 | Y33: 800 | Z33: 800 | AA33: 800 | AB33: 800 | AC33: 800 | AD33: =SUM(R33:AC33) | AF33: 800 | AG33: 800 | AH33: 800 | AI33: 800 | AJ33: 800 | AK33: 800 | AL33: 800 | AM33: 800 | AN33: 800 | AO33: 800 | AP33: 800 | AQ33: 800 | AR33: =SUM(AF33:AQ33) | AT33: 800 | AU33: 800 | AV33: 800 | AW33: 800 | AX33: 800 | AY33: 800 | AZ33: 800 | BA33: 800 | BB33: 800 | BC33: 800 | BD33: 800 | BE33: 800 | BF33: =SUM(AT33:BE33)
A34: Trello | D34: 67 | E34: 67 | F34: 67 | G34: 67 | H34: 67 | I34: 67 | J34: 67 | K34: 67 | L34: 67 | M34: 67 | N34: 67 | O34: 67 | P34: =SUM(D34:O34) | R34: 67 | S34: 67 | T34: 67 | U34: 67 | V34: 67 | W34: 67 | X34: 67 | Y34: 67 | Z34: 67 | AA34: 67 | AB34: 67 | AC34: 67 | AD34: =SUM(R34:AC34) | AF34: 67 | AG34: 67 | AH34: 67 | AI34: 67 | AJ34: 67 | AK34: 67 | AL34: 67 | AM34: 67 | AN34: 67 | AO34: 67 | AP34: 67 | AQ34: 67 | AR34: =SUM(AF34:AQ34) | AT34: 67 | AU34: 67 | AV34: 67 | AW34: 67 | AX34: 67 | AY34: 67 | AZ34: 67 | BA34: 67 | BB34: 67 | BC34: 67 | BD34: 67 | BE34: 67 | BF34: =SUM(AT34:BE34)
A35: Confluence | P35: =SUM(D35:O35) | AD35: =SUM(R35:AC35) | AR35: =SUM(AF35:AQ35) | BF35: =SUM(AT35:BE35)
A36: Giro | P36: =SUM(D36:O36) | AD36: =SUM(R36:AC36) | AR36: =SUM(AF36:AQ36) | BF36: =SUM(AT36:BE36)
A37: * See COGS for systems support | D37: 0 | E37: =$D$37 | F37: =$D$37 | G37: =$D$37 | H37: =$D$37 | I37: =$D$37 | J37: =$D$37 | K37: =$D$37 | L37: =$D$37 | ... O37: =$D$37 | P37: =SUM(D37:O37) | R37: 0 | S37: =$R$37 | T37: =$R$37 | U37: =$R$37 | V37: =$R$37 | W37: =$R$37 | X37: =$R$37 | Y37: =$R$37 | Z37: =$R$37 | ... AC37: =$R$37 | AD37: =SUM(R37:AC37) | AF37: 0 | AG37: =$AF$37 | AH37: =$AF$37 | AI37: =$AF$37 | AJ37: =$AF$37 | AK37: =$AF$37 | AL37: =$AF$37 | AM37: =$AF$37 | AN37: =$AF$37 | ... AQ37: =$AF$37 | AR37: =SUM(AF37:AQ37) | AT37: 0 | AU37: =$AT$37 | AV37: =$AT$37 | AW37: =$AT$37 | AX37: =$AT$37 | AY37: =$AT$37 | AZ37: =$AT$37 | BA37: =$AT$37 | BB37: =$AT$37 | ... BE37: =$AT$37 | BF37: =SUM(AT37:BE37)
P38: =SUM(D38:O38) | AD38: =SUM(R38:AC38) | AR38: =SUM(AF38:AQ38) | BF38: =SUM(AT38:BE38)
A39: Office Expenses | D39: - | E39: - | F39: - | G39: - | H39: - | I39: - | J39: - | K39: - | L39: - | M39: - | N39: - | O39: - | P39: =SUM(D39:O39) | R39: - | S39: - | T39: - | U39: - | V39: - | W39: - | X39: - | Y39: - | Z39: - | AA39: - | AB39: - | AC39: - | AD39: =SUM(R39:AC39) | AF39: - | AG39: - | AH39: - | AI39: - | AJ39: - | AK39: - | AL39: - | AM39: - | AN39: - | AO39: - | AP39: - | AQ39: - | AR39: =SUM(AF39:AQ39) | AT39: - | AU39: - | AV39: - | AW39: - | AX39: - | AY39: - | AZ39: - | BA39: - | BB39: - | BC39: - | BD39: - | BE39: - | BF39: =SUM(AT39:BE39)
A40: Rent | D40: 0 | E40: 0 | F40: 0 | G40: 0 | H40: 0 | I40: 0 | J40: 0 | K40: 0 | L40: 0 | M40: 0 | N40: 0 | O40: 0 | P40: =SUM(D40:O40) | R40: 0 | S40: 0 | T40: 0 | U40: 0 | V40: 0 | W40: 0 | X40: 0 | Y40: 0 | Z40: 0 | AA40: 0 | AB40: 0 | AC40: 0 | AD40: =SUM(R40:AC40) | AF40: 0 | AG40: 0 | AH40: 0 | AI40: 0 | AJ40: 0 | AK40: 0 | AL40: 0 | AM40: 0 | AN40: 0 | AO40: 0 | AP40: 0 | AQ40: 0 | AR40: =SUM(AF40:AQ40) | AT40: 0 | AU40: 0 | AV40: 0 | AW40: 0 | AX40: 0 | AY40: 0 | AZ40: 0 | BA40: 0 | BB40: 0 | BC40: 0 | BD40: 0 | BE40: 0 | BF40: =SUM(AT40:BE40)
A41: Parking | D41: 0 | E41: =$D$41 | F41: =$D$41 | G41: =$D$41 | H41: =$D$41 | I41: =$D$41 | J41: =$D$41 | K41: =$D$41 | L41: =$D$41 | ... O41: =$D$41 | P41: =SUM(D41:O41) | R41: 0 | S41: =$R$41 | T41: =$R$41 | U41: =$R$41 | V41: =$R$41 | W41: =$R$41 | X41: =$R$41 | Y41: =$R$41 | Z41: =$R$41 | ... AC41: =$R$41 | AD41: =SUM(R41:AC41) | AF41: 0 | AG41: =$AF$41 | AH41: =$AF$41 | AI41: =$AF$41 | AJ41: =$AF$41 | AK41: =$AF$41 | AL41: =$AF$41 | AM41: =$AF$41 | AN41: =$AF$41 | ... AQ41: =$AF$41 | AR41: =SUM(AF41:AQ41) | AT41: 0 | AU41: =$AT$41 | AV41: =$AT$41 | AW41: =$AT$41 | AX41: =$AT$41 | AY41: =$AT$41 | AZ41: =$AT$41 | BA41: =$AT$41 | BB41: =$AT$41 | ... BE41: =$AT$41 | BF41: =SUM(AT41:BE41)
A42: Office Supplies | D42: 100 | E42: =$D$42 | F42: =$D$42 | G42: =$D$42 | H42: =$D$42 | I42: =$D$42 | J42: =$D$42 | K42: =$D$42 | L42: =$D$42 | ... O42: =$D$42 | P42: =SUM(D42:O42) | R42: 100 | S42: =$R$42 | T42: =$R$42 | U42: =$R$42 | V42: =$R$42 | W42: =$R$42 | X42: =$R$42 | Y42: =$R$42 | Z42: =$R$42 | ... AC42: =$R$42 | AD42: =SUM(R42:AC42) | AF42: 100 | AG42: =$AF$42 | AH42: =$AF$42 | AI42: =$AF$42 | AJ42: =$AF$42 | AK42: =$AF$42 | AL42: =$AF$42 | AM42: =$AF$42 | AN42: =$AF$42 | ... AQ42: =$AF$42 | AR42: =SUM(AF42:AQ42) | AT42: 100 | AU42: =$AT$42 | AV42: =$AT$42 | AW42: =$AT$42 | AX42: =$AT$42 | AY42: =$AT$42 | AZ42: =$AT$42 | BA42: =$AT$42 | BB42: =$AT$42 | ... BE42: =$AT$42 | BF42: =SUM(AT42:BE42)
A43: Phone Line | D43: - | E43: - | F43: - | G43: - | H43: - | I43: - | J43: - | K43: - | L43: - | M43: - | N43: - | O43: - | P43: =SUM(D43:O43) | R43: - | S43: - | T43: - | U43: - | V43: - | W43: - | X43: - | Y43: - | Z43: - | AA43: - | AB43: - | AC43: - | AD43: =SUM(R43:AC43) | AF43: - | AG43: - | AH43: - | AI43: - | AJ43: - | AK43: - | AL43: - | AM43: - | AN43: - | AO43: - | AP43: - | AQ43: - | AR43: =SUM(AF43:AQ43) | AT43: - | AU43: - | AV43: - | AW43: - | AX43: - | AY43: - | AZ43: - | BA43: - | BB43: - | BC43: - | BD43: - | BE43: - | BF43: =SUM(AT43:BE43)
A44: Internet | D44: - | E44: - | F44: - | G44: - | H44: - | I44: - | J44: - | K44: - | L44: - | M44: - | N44: - | O44: - | P44: =SUM(D45:O45) | R44: - | S44: - | T44: - | U44: - | V44: - | W44: - | X44: - | Y44: - | Z44: - | AA44: - | AB44: - | AC44: - | AD44: =SUM(R44:AC44) | AF44: - | AG44: - | AH44: - | AI44: - | AJ44: - | AK44: - | AL44: - | AM44: - | AN44: - | AO44: - | AP44: - | AQ44: - | AR44: =SUM(AF44:AQ44) | AT44: - | AU44: - | AV44: - | AW44: - | AX44: - | AY44: - | AZ44: - | BA44: - | BB44: - | BC44: - | BD44: - | BE44: - | BF44: =SUM(AT44:BE44)
A45: Wireless | D45: 4000 | E45: - | F45: - | G45: - | H45: - | I45: - | J45: - | K45: - | L45: - | M45: - | N45: - | O45: - | P45: 4000 | R45: 4000 | S45: - | T45: - | U45: - | V45: - | W45: - | X45: - | Y45: - | Z45: - | AA45: - | AB45: - | AC45: - | AD45: =SUM(R45:AC45) | AF45: 4000 | AG45: - | AH45: - | AI45: - | AJ45: - | AK45: - | AL45: - | AM45: - | AN45: - | AO45: - | AP45: - | AQ45: - | AR45: =SUM(AF45:AQ45) | AT45: 4000 | AU45: - | AV45: - | AW45: - | AX45: - | AY45: - | AZ45: - | BA45: - | BB45: - | BC45: - | BD45: - | BE45: - | BF45: =SUM(AT45:BE45)
A46: Equipment | D46: - | E46: - | F46: - | G46: - | H46: - | I46: - | J46: - | K46: - | L46: - | M46: - | N46: - | O46: - | P46: - | R46: - | S46: - | T46: - | U46: - | V46: - | W46: - | X46: - | Y46: - | Z46: - | AA46: - | AB46: - | AC46: - | AD46: =SUM(R46:AC46) | AF46: - | AG46: - | AH46: - | AI46: - | AJ46: - | AK46: - | AL46: - | AM46: - | AN46: - | AO46: - | AP46: - | AQ46: - | AR46: =SUM(AF46:AQ46) | AT46: - | AU46: - | AV46: - | AW46: - | AX46: - | AY46: - | AZ46: - | BA46: - | BB46: - | BC46: - | BD46: - | BE46: - | BF46: =SUM(AT46:BE46)
A47: Printers | D47: - | E47: - | F47: - | G47: - | H47: - | I47: - | J47: - | K47: - | L47: - | M47: - | N47: - | O47: - | P47: - | R47: - | S47: - | T47: - | U47: - | V47: - | W47: - | X47: - | Y47: - | Z47: - | AA47: - | AB47: - | AC47: - | AD47: =SUM(R47:AC47) | AF47: - | AG47: - | AH47: - | AI47: - | AJ47: - | AK47: - | AL47: - | AM47: - | AN47: - | AO47: - | AP47: - | AQ47: - | AR47: =SUM(AF47:AQ47) | AT47: - | AU47: - | AV47: - | AW47: - | AX47: - | AY47: - | AZ47: - | BA47: - | BB47: - | BC47: - | BD47: - | BE47: - | BF47: =SUM(AT47:BE47)
D48: - | E48: - | F48: - | G48: - | H48: - | I48: - | J48: - | K48: - | L48: - | M48: - | N48: - | O48: - | P48: - | R48: - | S48: - | T48: - | U48: - | V48: - | W48: - | X48: - | Y48: - | Z48: - | AA48: - | AB48: - | AC48: - | AD48: =SUM(R48:AC48) | AF48: - | AG48: - | AH48: - | AI48: - | AJ48: - | AK48: - | AL48: - | AM48: - | AN48: - | AO48: - | AP48: - | AQ48: - | AR48: =SUM(AF48:AQ48) | AT48: - | AU48: - | AV48: - | AW48: - | AX48: - | AY48: - | AZ48: - | BA48: - | BB48: - | BC48: - | BD48: - | BE48: - | BF48: =SUM(AT48:BE48)
D49: - | E49: - | F49: - | G49: - | H49: - | I49: - | J49: - | K49: - | L49: - | M49: - | N49: - | O49: - | P49: - | R49: - | S49: - | T49: - | U49: - | V49: - | W49: - | X49: - | Y49: - | Z49: - | AA49: - | AB49: - | AC49: - | AD49: =SUM(R49:AC49) | AF49: - | AG49: - | AH49: - | AI49: - | AJ49: - | AK49: - | AL49: - | AM49: - | AN49: - | AO49: - | AP49: - | AQ49: - | AR49: =SUM(AF49:AQ49) | AT49: - | AU49: - | AV49: - | AW49: - | AX49: - | AY49: - | AZ49: - | BA49: - | BB49: - | BC49: - | BD49: - | BE49: - | BF49: =SUM(AT49:BE49)
A50: Conferences and Partnerships: | D50: - | E50: - | F50: - | G50: - | H50: - | I50: - | J50: - | K50: - | L50: - | M50: - | N50: - | O50: - | P50: - | R50: - | S50: - | T50: - | U50: - | V50: - | W50: - | X50: - | Y50: - | Z50: - | AA50: - | AB50: - | AC50: - | AD50: =SUM(R50:AC50) | AF50: - | AG50: - | AH50: - | AI50: - | AJ50: - | AK50: - | AL50: - | AM50: - | AN50: - | AO50: - | AP50: - | AQ50: - | AR50: =SUM(AF50:AQ50) | AT50: - | AU50: - | AV50: - | AW50: - | AX50: - | AY50: - | AZ50: - | BA50: - | BB50: - | BC50: - | BD50: - | BE50: - | BF50: =SUM(AT50:BE50)
A51: Hospitality / Real Estate
A52: ALIS | I52: 6000 | P52: 3000 | W52: 6000 | AD52: =SUM(R52:AC52) | AK52: 6000 | AR52: 3000 | AY52: 6000 | BF52: =SUM(AT52:BE52)
A53: Lodging Conference | J53: 6000 | P53: 3000 | X53: 6000 | AD53: 3000 | AL53: 6000 | AR53: 3000 | AZ53: 6000 | BF53: =SUM(AT53:BE53)
A54: Hunter | D54: 0 | E54: 0 | F54: 3000 | G54: 0 | H54: 0 | I54: 0 | P54: =SUM(D54:O54) | R54: 0 | S54: 0 | T54: 3000 | U54: 0 | V54: 0 | W54: 0 | AD54: =SUM(R54:AC54) | AF54: 0 | AG54: 0 | AH54: 3000 | AI54: 0 | AJ54: 0 | AK54: 0 | AR54: =SUM(AF54:AQ54) | AT54: 0 | AU54: 0 | AV54: 3000 | AW54: 0 | AX54: 0 | AY54: 0 | BF54: =SUM(AT54:BE54)
A55: NYU | N55: 3000 | P55: 3000 | AB55: 3000 | AD55: 3000 | AP55: 3000 | AR55: 3000 | BD55: 3000 | BF55: =SUM(AT55:BE55)
A56: International Luxury / Hitec / HSMAI | I56: 3000 | P56: =SUM(D56:O56) | W56: 3000 | AD56: =SUM(R56:AC56) | AK56: 3000 | AR56: =SUM(AF56:AQ56) | AY56: 3000 | BF56: =SUM(AT56:BE56)
A57: AHLA | D57: 0 | P57: =SUM(D57:O57) | R57: 10000 | AD57: =SUM(R57:AC57) | AF57: 10000 | AR57: =SUM(AF57:AQ57) | AT57: 10000 | BF57: =SUM(AT57:BE57)
A58: Sponserships | D58: 0 | F58: 0 | I58: 0 | J58: 0 | N58: 0 | P58: =SUM(D58:O58) | R58: 0 | T58: 0 | W58: 0 | X58: 0 | AB58: 0 | AD58: =SUM(R58:AC58) | AF58: 10000 | AH58: 5000 | AK58: 5000 | AL58: 5000 | AP58: 5000 | AR58: =SUM(AF58:AQ58) | AT58: 10000 | AV58: 5000 | AY58: 5000 | AZ58: 5000 | BD58: 5000 | BF58: =SUM(AT58:BE58)
A59: Pharma
A60: Conference | E60: =$D$60 | F60: =$D$60 | G60: =$D$60 | H60: =$D$60 | I60: =$D$60 | J60: =$D$60 | K60: =$D$60 | L60: =$D$60 | ... O60: =$D$60 | P60: =SUM(D60:O60) | S60: 5000 | T60: =$R$60 | U60: =$R$60 | V60: =$R$60 | W60: =$R$60 | X60: =$R$60 | Y60: =$R$60 | Z60: =$R$60 | AA60: =$R$60 | ... AC60: =$R$60 | AD60: =SUM(R60:AC60) | AF60: 5000 | AR60: =SUM(AF60:AQ60) | AT60: 5000 | BF60: =SUM(AT60:BE60)
A61: Sponserships | E61: =$D$61 | F61: =$D$61 | G61: =$D$61 | H61: =$D$61 | I61: =$D$61 | J61: =$D$61 | K61: =$D$61 | L61: =$D$61 | ... O61: =$D$61 | P61: =SUM(D61:O61) | S61: 5000 | T61: =$R$61 | U61: =$R$61 | V61: =$R$61 | W61: =$R$61 | X61: =$R$61 | Y61: =$R$61 | Z61: =$R$61 | AA61: =$R$61 | ... AC61: =$R$61 | AD61: =SUM(R61:AC61) | AF61: 5000 | AP61: 0 | AQ61: 0 | AR61: =SUM(AF61:AQ61) | AT61: 5000 | BF61: =SUM(AT61:BE61)
A62: Law | F62: =$D$60 | AP62: 0 | AQ62: 0
A63: Conference | E63: =$D$60 | F63: =$D$60 | G63: =$D$60 | H63: =$D$60 | I63: =$D$60 | J63: =$D$60 | K63: =$D$60 | L63: =$D$60 | ... O63: =$D$60 | P63: =SUM(D63:O63) | S63: =$R$60 | T63: =$R$60 | U63: =$R$60 | V63: =$R$60 | W63: =$R$60 | X63: =$R$60 | Y63: =$R$60 | Z63: =$R$60 | ... AC63: =$R$60 | AD63: =SUM(R63:AC63) | AF63: 5000 | AP63: 0 | AQ63: 0 | AR63: =SUM(AF63:AQ63) | AT63: 5000 | BF63: =SUM(AT63:BE63)
A64: Sponserships | E64: =$D$61 | F64: =$D$61 | G64: =$D$61 | H64: =$D$61 | I64: =$D$61 | J64: =$D$61 | K64: =$D$61 | L64: =$D$61 | ... O64: =$D$61 | P64: =SUM(D64:O64) | S64: =$R$61 | T64: =$R$61 | U64: =$R$61 | V64: =$R$61 | W64: =$R$61 | X64: =$R$61 | Y64: =$R$61 | Z64: =$R$61 | ... AC64: =$R$61 | AD64: =SUM(R64:AC64) | AF64: 5000 | AP64: 0 | AQ64: 0 | AR64: =SUM(AF64:AQ64) | AT64: 5000 | BF64: =SUM(AT64:BE64)
A65: Travel: | P65: - | AD65: - | AR65: - | BF65: =SUM(AT65:BE65)
A66: Airline | D66: 4000 | E66: =$D$66 | F66: =$D$66 | G66: =$D$66 | H66: =$D$66 | I66: =$D$66 | J66: =$D$66 | K66: =$D$66 | L66: =$D$66 | ... O66: =$D$66 | P66: =SUM(D66:O66) | R66: 4000 | S66: =$R$66 | T66: =$R$66 | U66: =$R$66 | V66: =$R$66 | W66: =$R$66 | X66: =$R$66 | Y66: =$R$66 | Z66: =$R$66 | ... AC66: =$R$66 | AD66: =SUM(R66:AC66) | AF66: 4000 | AG66: =$AF$66 | AH66: =$AF$66 | AI66: =$AF$66 | AJ66: =$AF$66 | AK66: =$AF$66 | AL66: =$AF$66 | AM66: =$AF$66 | AN66: =$AF$66 | ... AP66: =$AF$66 | AQ66: 2000 | AR66: =SUM(AF66:AQ66) | AT66: 4000 | AU66: =$AT$66 | AV66: =$AT$66 | AW66: =$AT$66 | AX66: =$AT$66 | AY66: =$AT$66 | AZ66: =$AT$66 | BA66: =$AT$66 | BB66: =$AT$66 | ... BE66: =$AT$66 | BF66: =SUM(AT66:BE66)
A67: Hotel | D67: 2000 | E67: =$D$67 | F67: =$D$67 | G67: =$D$67 | H67: =$D$67 | I67: =$D$67 | J67: =$D$67 | K67: =$D$67 | L67: =$D$67 | ... O67: =$D$67 | P67: 12000 | R67: 1000 | S67: =$R$67 | T67: =$R$67 | U67: =$R$67 | V67: =$R$67 | W67: =$R$67 | X67: =$R$67 | Y67: =$R$67 | Z67: =$R$67 | ... AC67: =$R$67 | AD67: 12000 | AF67: 2000 | AG67: =$AF$67 | AH67: =$AF$67 | AI67: =$AF$67 | AJ67: =$AF$67 | AK67: =$AF$67 | AL67: =$AF$67 | AM67: =$AF$67 | AN67: =$AF$67 | ... AP67: =$AF$67 | AQ67: 1000 | AR67: 12000 | AT67: 2000 | AU67: =$AT$67 | AV67: =$AT$67 | AW67: =$AT$67 | AX67: =$AT$67 | AY67: =$AT$67 | AZ67: =$AT$67 | BA67: =$AT$67 | BB67: =$AT$67 | ... BE67: =$AT$67 | BF67: 12000
A68: Transport | D68: 250 | E68: =$D$68 | F68: =$D$68 | G68: =$D$68 | H68: =$D$68 | I68: =$D$68 | J68: =$D$68 | K68: =$D$68 | L68: =$D$68 | ... O68: =$D$68 | P68: =SUM(D68:O68) | R68: 250 | S68: =$R$68 | T68: =$R$68 | U68: =$R$68 | V68: =$R$68 | W68: =$R$68 | X68: =$R$68 | Y68: =$R$68 | Z68: =$R$68 | ... AC68: =$R$68 | AD68: =SUM(R68:AC68) | AF68: 250 | AG68: =$AF$68 | AH68: =$AF$68 | AI68: =$AF$68 | AJ68: =$AF$68 | AK68: =$AF$68 | AL68: =$AF$68 | AM68: =$AF$68 | AN68: =$AF$68 | ... AP68: =$AF$68 | AQ68: 250 | AR68: =SUM(AF68:AQ68) | AT68: 250 | AU68: =$AT$68 | AV68: =$AT$68 | AW68: =$AT$68 | AX68: =$AT$68 | AY68: =$AT$68 | AZ68: =$AT$68 | BA68: =$AT$68 | BB68: =$AT$68 | ... BE68: =$AT$68 | BF68: =SUM(AT68:BE68)
A69: Meals | D69: 500 | E69: =$D$69 | F69: =$D$69 | G69: =$D$69 | H69: =$D$69 | I69: =$D$69 | J69: =$D$69 | K69: =$D$69 | L69: =$D$69 | ... O69: =$D$69 | P69: =SUM(D69:O69) | R69: 500 | S69: =$R$69 | T69: =$R$69 | U69: =$R$69 | V69: =$R$69 | W69: =$R$69 | X69: =$R$69 | Y69: =$R$69 | Z69: =$R$69 | ... AC69: =$R$69 | AD69: =SUM(R69:AC69) | AF69: 500 | AG69: =$AF$69 | AH69: =$AF$69 | AI69: =$AF$69 | AJ69: =$AF$69 | AK69: =$AF$69 | AL69: =$AF$69 | AM69: =$AF$69 | AN69: =$AF$69 | ... AP69: =$AF$69 | AQ69: 500 | AR69: =SUM(AF69:AQ69) | AT69: 500 | AU69: =$AT$69 | AV69: =$AT$69 | AW69: =$AT$69 | AX69: =$AT$69 | AY69: =$AT$69 | AZ69: =$AT$69 | BA69: =$AT$69 | BB69: =$AT$69 | ... BE69: =$AT$69 | BF69: =SUM(AT69:BE69)
A70: Entertainment | D70: 500 | E70: =$D$70 | F70: =$D$70 | G70: =$D$70 | H70: =$D$70 | I70: =$D$70 | J70: =$D$70 | K70: =$D$70 | L70: =$D$70 | ... O70: =$D$70 | P70: =SUM(D70:O70) | R70: 1000 | S70: =$R$70 | T70: =$R$70 | U70: =$R$70 | V70: =$R$70 | W70: =$R$70 | X70: =$R$70 | Y70: =$R$70 | Z70: =$R$70 | ... AC70: =$R$70 | AD70: =SUM(R70:AC70) | AF70: 1000 | AG70: =$AF$70 | AH70: =$AF$70 | AI70: =$AF$70 | AJ70: =$AF$70 | AK70: =$AF$70 | AL70: =$AF$70 | AM70: =$AF$70 | AN70: =$AF$70 | ... AP70: =$AF$70 | AQ70: 500 | AR70: =SUM(AF70:AQ70) | AT70: 4000 | AU70: =$AT$70 | AV70: =$AT$70 | AW70: =$AT$70 | AX70: =$AT$70 | AY70: =$AT$70 | AZ70: =$AT$70 | BA70: =$AT$70 | BB70: =$AT$70 | ... BE70: =$AT$70 | BF70: =SUM(AT70:BE70)
D71: - | E71: - | F71: - | G71: - | H71: - | I71: - | J71: - | K71: - | L71: - | M71: - | N71: - | O71: - | P71: - | R71: - | S71: - | T71: - | U71: - | V71: - | W71: - | X71: - | Y71: - | Z71: - | AA71: - | AB71: - | AC71: - | AD71: - | AF71: - | AG71: - | AH71: - | AI71: - | AJ71: - | AK71: - | AL71: - | AM71: - | AN71: - | AO71: - | AP71: - | AQ71: - | AR71: - | AT71: - | AU71: - | AV71: - | AW71: - | AX71: - | AY71: - | AZ71: - | BA71: - | BB71: - | BC71: - | BD71: - | BE71: - | BF71: =SUM(AT71:BE71)
D72: - | E72: - | F72: - | G72: - | H72: - | I72: - | J72: - | K72: - | L72: - | M72: - | N72: - | O72: - | P72: - | R72: - | S72: - | T72: - | U72: - | V72: - | W72: - | X72: - | Y72: - | Z72: - | AA72: - | AB72: - | AC72: - | AD72: - | AF72: - | AG72: - | AH72: - | AI72: - | AJ72: - | AK72: - | AL72: - | AM72: - | AN72: - | AO72: - | AP72: - | AQ72: - | AR72: - | AT72: - | AU72: - | AV72: - | AW72: - | AX72: - | AY72: - | AZ72: - | BA72: - | BB72: - | BC72: - | BD72: - | BE72: - | BF72: =SUM(AT72:BE72)
A73: Legal and Professional Services | D73: - | E73: - | F73: - | G73: - | H73: - | I73: - | J73: - | K73: - | L73: - | M73: - | N73: - | O73: - | P73: - | R73: - | S73: - | T73: - | U73: - | V73: - | W73: - | X73: - | Y73: - | Z73: - | AA73: - | AB73: - | AC73: - | AD73: - | AF73: - | AG73: - | AH73: - | AI73: - | AJ73: - | AK73: - | AL73: - | AM73: - | AN73: - | AO73: - | AP73: - | AQ73: - | AR73: - | AT73: - | AU73: - | AV73: - | AW73: - | AX73: - | AY73: - | AZ73: - | BA73: - | BB73: - | BC73: - | BD73: - | BE73: - | BF73: =SUM(AT73:BE73)
A74: Legal | P74: - | AD74: - | AR74: - | BF74: =SUM(AT74:BE74)
A75: Contract / Agreements | D75: 1000 | E75: - | F75: - | G75: - | H75: - | I75: - | J75: - | K75: - | L75: - | M75: - | N75: - | O75: - | P75: =SUM(D75:O75) | R75: 2000 | S75: - | T75: - | U75: - | V75: - | W75: - | X75: - | Y75: - | Z75: - | AA75: - | AB75: - | AC75: - | AD75: =SUM(R75:AC75) | AF75: 2000 | AG75: - | AH75: - | AI75: - | AJ75: - | AK75: - | AL75: - | AM75: - | AN75: - | AO75: - | AP75: - | AQ75: - | AR75: =SUM(AF75:AQ75) | AT75: 2000 | AU75: - | AV75: - | AW75: - | AX75: - | AY75: - | AZ75: - | BA75: - | BB75: - | BC75: - | BD75: - | BE75: - | BF75: =SUM(AT75:BE75)
A76: Trademark | P76: - | AD76: - | AR76: - | BF76: =SUM(AT76:BE76)
E77: - | F77: - | G77: - | H77: - | I77: - | J77: - | K77: - | L77: - | M77: - | N77: - | O77: - | S77: - | T77: - | U77: - | V77: - | W77: - | X77: - | Y77: - | Z77: - | AA77: - | AB77: - | AC77: - | AG77: - | AH77: - | AI77: - | AJ77: - | AK77: - | AL77: - | AM77: - | AN77: - | AO77: - | AP77: - | AQ77: - | AU77: - | AV77: - | AW77: - | AX77: - | AY77: - | AZ77: - | BA77: - | BB77: - | BC77: - | BD77: - | BE77: - | BF77: =SUM(AT77:BE77)
A78: Professional Services | P78: - | AD78: - | AR78: - | BF78: =SUM(AT78:BE78)
A79: CFO - Fractional | D79: 5000 | P79: 5000 | R79: 5000 | AD79: 5000 | AF79: 5000 | AR79: 5000 | AT79: 5000 | BF79: =SUM(AT79:BE79)
A80: Human Resources | D80: 0 | P80: =SUM(D80:O80) | R80: 3000 | AD80: =SUM(R80:AC80) | AF80: 3000 | AR80: =SUM(AF80:AQ80) | AT80: 3000 | BF80: 3000
A81: Strategic Advisor | D81: 2200 | E81: 2200 | F81: 2200 | G81: 2200 | H81: 2200 | I81: 2200 | J81: 2200 | K81: 2200 | L81: 2200 | M81: 2200 | N81: 2200 | O81: 2200 | P81: 26400 | R81: 2200 | S81: 2200 | T81: 2200 | U81: 2200 | V81: 2200 | W81: 2200 | X81: 2200 | Y81: 2200 | Z81: 2200 | AA81: 2200 | AB81: 2200 | AC81: 2200 | AD81: 26400 | AF81: 2200 | AG81: 2200 | AH81: 2200 | AI81: 2200 | AJ81: 2200 | AK81: 2200 | AL81: 2200 | AM81: 2200 | AN81: 2200 | AO81: 2200 | AP81: 2200 | AQ81: 2200 | AR81: 26400 | AT81: 2200 | AU81: 2200 | AV81: 2200 | AW81: 2200 | AX81: 2200 | AY81: 2200 | AZ81: 2200 | BA81: 2200 | BB81: 2200 | BC81: 2200 | BD81: 2200 | BE81: 2200 | BF81: =SUM(AT81:BE81)
D82: =SUM(D19:D81) | E82: =SUM(E19:E81) | F82: =SUM(F19:F81) | G82: =SUM(G19:G81) | H82: =SUM(H19:H81) | I82: =SUM(I19:I81) | J82: =SUM(J19:J81) | K82: =SUM(K19:K81) | ... O82: =SUM(O19:O81) | P82: =SUM(P6:P81) | R82: =SUM(R19:R81) | S82: =SUM(S19:S81) | T82: =SUM(T19:T81) | U82: =SUM(U19:U81) | V82: =SUM(V19:V81) | W82: =SUM(W19:W81) | X82: =SUM(X19:X81) | Y82: =SUM(Y19:Y81) | ... AC82: =SUM(AC19:AC81) | AD82: =SUM(AD6:AD81) | AF82: =SUM(AF19:AF81) | AG82: =SUM(AG19:AG81) | AH82: =SUM(AH19:AH81) | AI82: =SUM(AI19:AI81) | AJ82: =SUM(AJ19:AJ81) | AK82: =SUM(AK19:AK81) | AL82: =SUM(AL19:AL81) | AM82: =SUM(AM19:AM81) | ... AQ82: =SUM(AQ19:AQ81) | AR82: =SUM(AR6:AR81) | AT82: =SUM(AT19:AT81) | AU82: =SUM(AU19:AU81) | AV82: =SUM(AV19:AV81) | AW82: =SUM(AW19:AW81) | AX82: =SUM(AX19:AX81) | AY82: =SUM(AY19:AY81) | AZ82: =SUM(AZ19:AZ81) | BA82: =SUM(BA19:BA81) | ... BE82: =SUM(BE19:BE81) | BF82: =SUM(BF6:BF81)

Sheet P&L Projections
N1: Forecast | AB1: Forecast | AP1: Forecast
F2: Assumptions | G2: 2025 | S2: 2025 | U2: 2026 | AG2: 2026 | AI2: 2027 | AU2: 2027 | AW2: 2028 | BI2: 2028
C3: Account | D3: Account Comments | E3: Driver | G3: 45658 | H3: 45718 | I3: 45717 | J3: 45748 | K3: 45778 | L3: 45809 | M3: 45839 | N3: 45870 | O3: 45901 | P3: 45931 | Q3: 45962 | R3: 45992 | S3: Total | U3: 46023 | V3: 46054 | W3: 46082 | X3: 46113 | Y3: 46143 | Z3: 46174 | AA3: 46204 | AB3: 46235 | AC3: 46266 | AD3: 46296 | AE3: 46327 | AF3: 46357 | AG3: Total | AI3: 46388 | AJ3: 46448 | AK3: 46447 | AL3: 46478 | AM3: 46508 | AN3: 46539 | AO3: 46569 | AP3: 46600 | AQ3: 46631 | AR3: 46661 | AS3: 46692 | AT3: 46722 | AU3: Total | AW3: 46753 | AX3: 46784 | AY3: 46813 | AZ3: 46844 | BA3: 46874 | BB3: 46905 | BC3: 46935 | BD3: 46966 | BE3: 46997 | BF3: 47027 | BG3: 47058 | BH3: 46722 | BI3: Total
B4: Revenue:
B5: Administrative
B6: Configuration | G6: ='Revenue 2025'!$D$97 | H6: ='Revenue 2025'!$E$97 | I6: ='Revenue 2025'!$F$97 | J6: ='Revenue 2025'!$G$97 | K6: ='Revenue 2025'!$H97 | L6: ='Revenue 2025'!$I$97 | M6: ='Revenue 2025'!$J$97 | N6: ='Revenue 2025'!$K$97 | O6: ='Revenue 2025'!$L$97 | P6: ='Revenue 2025'!$M$97 | Q6: ='Revenue 2025'!$N$97 | R6: ='Revenue 2025'!$O$97 | S6: =SUM(G6:R6) | U6: ='Revenue 2026'!$D$103 | V6: ='Revenue 2026'!$E$103 | W6: ='Revenue 2026'!$F$103 | X6: ='Revenue 2026'!$G$103 | Y6: ='Revenue 2026'!$H103 | Z6: ='Revenue 2026'!$I$103 | AA6: ='Revenue 2026'!$J$103 | AB6: ='Revenue 2026'!$K$103 | AC6: ='Revenue 2026'!$L$103 | AD6: ='Revenue 2026'!$M$103 | AE6: ='Revenue 2026'!$N$103 | AF6: ='Revenue 2026'!$O$103 | AG6: =SUM(U6:AF6) | AI6: ='Revenue 2027'!$D$103 | AJ6: ='Revenue 2027'!$E$103 | AK6: ='Revenue 2027'!$F$103 | AL6: ='Revenue 2027'!$G$103 | AM6: ='Revenue 2027'!$H103 | AN6: ='Revenue 2027'!$I$103 | AO6: ='Revenue 2027'!$J$103 | AP6: ='Revenue 2027'!$K$103 | AQ6: ='Revenue 2027'!$L$103 | AR6: ='Revenue 2027'!$M$103 | AS6: ='Revenue 2027'!$N$103 | AT6: ='Revenue 2027'!$O$103 | AU6: =SUM(AI6:AT6) | AW6: ='Revenue 2028'!D102 | AX6: ='Revenue 2028'!E102 | AY6: ='Revenue 2028'!F102 | AZ6: ='Revenue 2028'!G102 | BA6: ='Revenue 2028'!H102 | BB6: ='Revenue 2028'!I102 | BC6: ='Revenue 2028'!J102 | BD6: ='Revenue 2028'!K102 | ... BH6: ='Revenue 2028'!O102 | BI6: =SUM(AW6:BH6)
B7: On-Boarding- Administrator | G7: ='Revenue 2025'!$D$103 | H7: ='Revenue 2025'!$E$103 | I7: ='Revenue 2025'!$F$103 | J7: ='Revenue 2025'!$G$103 | K7: ='Revenue 2025'!$H$103 | L7: ='Revenue 2025'!$I$103 | M7: ='Revenue 2025'!$J$103 | N7: ='Revenue 2025'!$K$103 | O7: ='Revenue 2025'!$L$103 | P7: ='Revenue 2025'!$M$103 | Q7: ='Revenue 2025'!$N$103 | R7: ='Revenue 2025'!$O$103 | S7: =SUM(G7:R7) | U7: ='Revenue 2026'!$D$109 | V7: ='Revenue 2026'!$E$109 | W7: ='Revenue 2026'!$F$109 | X7: ='Revenue 2026'!$G$109 | Y7: ='Revenue 2026'!$H$109 | Z7: ='Revenue 2026'!$I$109 | AA7: ='Revenue 2026'!$J$109 | AB7: ='Revenue 2026'!$K$109 | AC7: ='Revenue 2026'!$L$109 | AD7: ='Revenue 2026'!$M$109 | AE7: ='Revenue 2026'!$N$109 | AF7: ='Revenue 2026'!$O$109 | AG7: =SUM(U7:AF7) | AI7: ='Revenue 2027'!$D$109 | AJ7: ='Revenue 2027'!$E$109 | AK7: ='Revenue 2027'!$F$109 | AL7: ='Revenue 2027'!$G$109 | AM7: ='Revenue 2027'!$H$109 | AN7: ='Revenue 2027'!$I$109 | AO7: ='Revenue 2027'!$J$109 | AP7: ='Revenue 2027'!$K$109 | AQ7: ='Revenue 2027'!$L$109 | AR7: ='Revenue 2027'!$M$109 | AS7: ='Revenue 2027'!$N$109 | AT7: ='Revenue 2027'!$O$109 | AU7: =SUM(AI7:AT7) | AW7: ='Revenue 2028'!D108 | AX7: ='Revenue 2028'!E108 | AY7: ='Revenue 2028'!F108 | AZ7: ='Revenue 2028'!G108 | BA7: ='Revenue 2028'!H108 | BB7: ='Revenue 2028'!I108 | BC7: ='Revenue 2028'!J108 | BD7: ='Revenue 2028'!K108 | ... BH7: ='Revenue 2028'!O108 | BI7: =SUM(AW7:BH7)
B8: On-Boarding Users | G8: ='Revenue 2025'!$D$109 | H8: ='Revenue 2025'!$E$109 | I8: ='Revenue 2025'!$F$109 | J8: ='Revenue 2025'!$G$109 | K8: ='Revenue 2025'!$H$109 | L8: ='Revenue 2025'!$I$109 | M8: ='Revenue 2025'!$J$109 | N8: ='Revenue 2025'!$K$109 | O8: ='Revenue 2025'!$L$109 | P8: ='Revenue 2025'!$M$109 | Q8: ='Revenue 2025'!$N$109 | R8: ='Revenue 2025'!$O$109 | S8: =SUM(G8:R8) | U8: ='Revenue 2026'!$D$115 | V8: ='Revenue 2026'!$E$115 | W8: ='Revenue 2026'!$F$115 | X8: ='Revenue 2026'!$G$115 | Y8: ='Revenue 2026'!$H$115 | Z8: ='Revenue 2026'!$I$115 | AA8: ='Revenue 2026'!$J$115 | AB8: ='Revenue 2026'!$K$115 | AC8: ='Revenue 2026'!$L$115 | AD8: ='Revenue 2026'!$M$115 | AE8: ='Revenue 2026'!$N$115 | AF8: ='Revenue 2026'!$O$115 | AG8: =SUM(U8:AF8) | AI8: ='Revenue 2027'!$D$115 | AJ8: ='Revenue 2027'!$E$115 | AK8: ='Revenue 2027'!$F$115 | AL8: ='Revenue 2027'!$G$115 | AM8: ='Revenue 2027'!$H$115 | AN8: ='Revenue 2027'!$I$115 | AO8: ='Revenue 2027'!$J$115 | AP8: ='Revenue 2027'!$K$115 | AQ8: ='Revenue 2027'!$L$115 | AR8: ='Revenue 2027'!$M$115 | AS8: ='Revenue 2027'!$N$115 | AT8: ='Revenue 2027'!$O$115 | AU8: =SUM(AI8:AT8) | AW8: ='Revenue 2028'!D114 | AX8: ='Revenue 2028'!E114 | AY8: ='Revenue 2028'!F114 | AZ8: ='Revenue 2028'!G114 | BA8: ='Revenue 2028'!H114 | BB8: ='Revenue 2028'!I114 | BC8: ='Revenue 2028'!J114 | BD8: ='Revenue 2028'!K114 | ... BH8: ='Revenue 2028'!O114 | BI8: =SUM(AW8:BH8)
B9: Import | G9: ='Revenue 2025'!$D$115 | H9: ='Revenue 2025'!$E$115 | I9: ='Revenue 2025'!$F$115 | J9: ='Revenue 2025'!$G$115 | K9: ='Revenue 2025'!$H$115 | L9: ='Revenue 2025'!$I$115 | M9: ='Revenue 2025'!$J$115 | N9: ='Revenue 2025'!$K$115 | O9: ='Revenue 2025'!$L$115 | P9: ='Revenue 2025'!$M$115 | Q9: ='Revenue 2025'!$N$115 | R9: ='Revenue 2025'!$O$115 | S9: =SUM(G9:R9) | U9: ='Revenue 2026'!$D$121 | V9: ='Revenue 2026'!$E$121 | W9: ='Revenue 2026'!$F$121 | X9: ='Revenue 2026'!$G$121 | Y9: ='Revenue 2026'!$H$121 | Z9: ='Revenue 2026'!$I$121 | AA9: ='Revenue 2026'!$J$121 | AB9: ='Revenue 2026'!$K$121 | AC9: ='Revenue 2026'!$L$121 | AD9: ='Revenue 2026'!$M$121 | AE9: ='Revenue 2026'!$N$121 | AF9: ='Revenue 2026'!$O$121 | AG9: =SUM(U9:AF9) | AI9: ='Revenue 2027'!$D$121 | AJ9: ='Revenue 2027'!$E$121 | AK9: ='Revenue 2027'!$F$121 | AL9: ='Revenue 2027'!$G$121 | AM9: ='Revenue 2027'!$H$121 | AN9: ='Revenue 2027'!$I$121 | AO9: ='Revenue 2027'!$J$121 | AP9: ='Revenue 2027'!$K$121 | AQ9: ='Revenue 2027'!$L$121 | AR9: ='Revenue 2027'!$M$121 | AS9: ='Revenue 2027'!$N$121 | AT9: ='Revenue 2027'!$O$121 | AU9: =SUM(AI9:AT9) | AW9: ='Revenue 2028'!D120 | AX9: ='Revenue 2028'!E120 | AY9: ='Revenue 2028'!F120 | AZ9: ='Revenue 2028'!G120 | BA9: ='Revenue 2028'!H120 | BB9: ='Revenue 2028'!I120 | BC9: ='Revenue 2028'!J120 | BD9: ='Revenue 2028'!K120 | ... BH9: ='Revenue 2028'!O120 | BI9: =SUM(AW9:BH9)
B10: Support | G10: ='Revenue 2025'!$D$158 | H10: ='Revenue 2025'!$D$158 | I10: ='Revenue 2025'!$D$158 | J10: ='Revenue 2025'!$D$158 | K10: ='Revenue 2025'!$D$158 | L10: ='Revenue 2025'!$D$158 | M10: ='Revenue 2025'!$D$158 | N10: ='Revenue 2025'!$D$158 | ... R10: ='Revenue 2025'!$D$158 | S10: =SUM(G10:R10) | U10: ='Revenue 2026'!$D$164 | V10: ='Revenue 2026'!$D$164 | W10: ='Revenue 2026'!$D$164 | X10: ='Revenue 2026'!$D$164 | Y10: ='Revenue 2026'!$D$164 | Z10: ='Revenue 2026'!$D$164 | AA10: ='Revenue 2026'!$D$164 | AB10: ='Revenue 2026'!$D$164 | ... AF10: ='Revenue 2026'!$D$164 | AG10: =SUM(U10:AF10) | AI10: ='Revenue 2027'!$D$164 | AJ10: ='Revenue 2027'!$D$164 | AK10: ='Revenue 2027'!$D$164 | AL10: ='Revenue 2027'!$D$164 | AM10: ='Revenue 2027'!$D$164 | AN10: ='Revenue 2027'!$D$164 | AO10: ='Revenue 2027'!$D$164 | AP10: ='Revenue 2027'!$D$164 | ... AT10: ='Revenue 2027'!$D$164 | AU10: =SUM(AI10:AT10) | AW10: ='Revenue 2028'!D163 | AX10: ='Revenue 2028'!E163 | AY10: ='Revenue 2028'!F163 | AZ10: ='Revenue 2028'!G163 | BA10: ='Revenue 2028'!H163 | BB10: ='Revenue 2028'!I163 | BC10: ='Revenue 2028'!J163 | BD10: ='Revenue 2028'!K163 | ... BH10: ='Revenue 2028'!O163 | BI10: =SUM(AW10:BH10)
B11: Industry Break Down
B12: Hospitality | G12: ='Revenue 2025'!$D$29 | H12: ='Revenue 2025'!$E$29 | I12: ='Revenue 2025'!$F$29 | J12: ='Revenue 2025'!$G$29 | K12: ='Revenue 2025'!$H$29 | L12: ='Revenue 2025'!$I$29 | M12: ='Revenue 2025'!$J$29 | N12: ='Revenue 2025'!$K$29 | O12: ='Revenue 2025'!$L$29 | P12: ='Revenue 2025'!$M$29 | Q12: ='Revenue 2025'!$N$29 | R12: ='Revenue 2025'!$O$29 | S12: =SUM(G12:R12) | U12: ='Revenue 2026'!$D$29 | V12: ='Revenue 2026'!$E$29 | W12: ='Revenue 2026'!$F$29 | X12: ='Revenue 2026'!$G$29 | Y12: ='Revenue 2026'!$H$29 | Z12: ='Revenue 2026'!$I$29 | AA12: ='Revenue 2026'!$J$29 | AB12: ='Revenue 2026'!$K$29 | AC12: ='Revenue 2026'!$L$29 | AD12: ='Revenue 2026'!$M$29 | AE12: ='Revenue 2026'!$N$29 | AF12: ='Revenue 2026'!$O$29 | AG12: =SUM(U12:AF12) | AI12: ='Revenue 2027'!$D$29 | AJ12: ='Revenue 2027'!$E$29 | AK12: ='Revenue 2027'!$F$29 | AL12: ='Revenue 2027'!$G$29 | AM12: ='Revenue 2027'!$H$29 | AN12: ='Revenue 2027'!$I$29 | AO12: ='Revenue 2027'!$J$29 | AP12: ='Revenue 2027'!$K$29 | AQ12: ='Revenue 2027'!$L$29 | AR12: ='Revenue 2027'!$M$29 | AS12: ='Revenue 2027'!$N$29 | AT12: ='Revenue 2027'!$O$29 | AU12: =SUM(AI12:AT12) | AW12: ='Revenue 2028'!D29 | AX12: ='Revenue 2028'!E29 | AY12: ='Revenue 2028'!F29 | AZ12: ='Revenue 2028'!G29 | BA12: ='Revenue 2028'!H29 | BB12: ='Revenue 2028'!I29 | BC12: ='Revenue 2028'!J29 | BD12: ='Revenue 2028'!K29 | ... BH12: ='Revenue 2028'!O29 | BI12: =SUM(AW12:BH12)
B13: Hospitality- Reseller | G13: ='Revenue 2025'!$D$35 | H13: ='Revenue 2025'!$E$35 | I13: ='Revenue 2025'!$F35 | J13: ='Revenue 2025'!$G$35 | K13: ='Revenue 2025'!$H$35 | L13: ='Revenue 2025'!$I$35 | M13: ='Revenue 2025'!$J$35 | N13: ='Revenue 2025'!$K$35 | O13: ='Revenue 2025'!$L$35 | P13: ='Revenue 2025'!$M$35 | Q13: ='Revenue 2025'!$N$35 | R13: ='Revenue 2025'!$O$35 | S13: =SUM(G13:R13) | U13: ='Revenue 2026'!$D$36 | V13: ='Revenue 2026'!$E$36 | W13: ='Revenue 2026'!$F36 | X13: ='Revenue 2026'!$G$36 | Y13: ='Revenue 2026'!$H$36 | Z13: ='Revenue 2026'!$I$36 | AA13: ='Revenue 2026'!$J$36 | AB13: ='Revenue 2026'!$K$36 | AC13: ='Revenue 2026'!$L$36 | AD13: ='Revenue 2026'!$M$36 | AE13: ='Revenue 2026'!$N$36 | AF13: ='Revenue 2026'!$O$36 | AG13: =SUM(U13:AF13) | AI13: ='Revenue 2027'!$D$36 | AJ13: ='Revenue 2027'!$E$36 | AK13: ='Revenue 2027'!$F36 | AL13: ='Revenue 2027'!$G$36 | AM13: ='Revenue 2027'!$H$36 | AN13: ='Revenue 2027'!$I$36 | AO13: ='Revenue 2027'!$J$36 | AP13: ='Revenue 2027'!$K$36 | AQ13: ='Revenue 2027'!$L$36 | AR13: ='Revenue 2027'!$M$36 | AS13: ='Revenue 2027'!$N$36 | AT13: ='Revenue 2027'!$O$36 | AU13: =SUM(AI13:AT13) | AW13: ='Revenue 2028'!D36 | AX13: ='Revenue 2028'!E36 | AY13: ='Revenue 2028'!F36 | AZ13: ='Revenue 2028'!G36 | BA13: ='Revenue 2028'!H36 | BB13: ='Revenue 2028'!I36 | BC13: ='Revenue 2028'!J36 | BD13: ='Revenue 2028'!K36 | ... BH13: ='Revenue 2028'!O36 | BI13: =SUM(AW13:BH13)
B14: Real Estate Development | G14: ='Revenue 2025'!$D$41 | H14: ='Revenue 2025'!$E$41 | I14: ='Revenue 2025'!$F$41 | J14: ='Revenue 2025'!$G$41 | K14: ='Revenue 2025'!$H$41 | L14: ='Revenue 2025'!$I$41 | M14: ='Revenue 2025'!$J$41 | N14: ='Revenue 2025'!$K$41 | O14: ='Revenue 2025'!$L$41 | P14: ='Revenue 2025'!$M$41 | Q14: ='Revenue 2025'!$N$41 | R14: ='Revenue 2025'!$O$41 | S14: =SUM(G14:R14) | U14: ='Revenue 2026'!$D$43 | V14: ='Revenue 2026'!$E$43 | W14: ='Revenue 2026'!$F$43 | X14: ='Revenue 2026'!$G$43 | Y14: ='Revenue 2026'!$H$43 | Z14: ='Revenue 2026'!$I$43 | AA14: ='Revenue 2026'!$J$43 | AB14: ='Revenue 2026'!$K$43 | AC14: ='Revenue 2026'!$L$43 | AD14: ='Revenue 2026'!$M$43 | AE14: ='Revenue 2026'!$N$43 | AF14: ='Revenue 2026'!$O$43 | AG14: =SUM(U14:AF14) | AI14: ='Revenue 2027'!$D$43 | AJ14: ='Revenue 2027'!$E$43 | AK14: ='Revenue 2027'!$F$43 | AL14: ='Revenue 2027'!$G$43 | AM14: ='Revenue 2027'!$H$43 | AN14: ='Revenue 2027'!$I$43 | AO14: ='Revenue 2027'!$J$43 | AP14: ='Revenue 2027'!$K$43 | AQ14: ='Revenue 2027'!$L$43 | AR14: ='Revenue 2027'!$M$43 | AS14: ='Revenue 2027'!$N$43 | AT14: ='Revenue 2027'!$O$43 | AU14: =SUM(AI14:AT14) | AW14: ='Revenue 2028'!D43 | AX14: ='Revenue 2028'!E43 | AY14: ='Revenue 2028'!F43 | AZ14: ='Revenue 2028'!G43 | BA14: ='Revenue 2028'!H43 | BB14: ='Revenue 2028'!I43 | BC14: ='Revenue 2028'!J43 | BD14: ='Revenue 2028'!K43 | ... BH14: ='Revenue 2028'!O43 | BI14: =SUM(AW14:BH14)
B15: Real Estate Development- Reseller | G15: ='Revenue 2025'!$D$47 | H15: ='Revenue 2025'!$E$47 | I15: ='Revenue 2025'!$F$47 | J15: ='Revenue 2025'!$G$47 | K15: ='Revenue 2025'!$H$47 | L15: ='Revenue 2025'!$I$47 | M15: ='Revenue 2025'!$J$47 | N15: ='Revenue 2025'!$K$47 | O15: ='Revenue 2025'!$L$47 | P15: ='Revenue 2025'!$M$47 | Q15: ='Revenue 2025'!$N$47 | R15: ='Revenue 2025'!$O$47 | S15: =SUM(G15:R15) | U15: ='Revenue 2026'!$D$50 | V15: ='Revenue 2026'!$E$50 | W15: ='Revenue 2026'!$F$50 | X15: ='Revenue 2026'!$G$50 | Y15: ='Revenue 2026'!$H$50 | Z15: ='Revenue 2026'!$I$50 | AA15: ='Revenue 2026'!$J$50 | AB15: ='Revenue 2026'!$K$50 | AC15: ='Revenue 2026'!$L$50 | AD15: ='Revenue 2026'!$M$50 | AE15: ='Revenue 2026'!$N$50 | AF15: ='Revenue 2026'!$O$50 | AG15: =SUM(U15:AF15) | AI15: ='Revenue 2027'!$D$50 | AJ15: ='Revenue 2027'!$E$50 | AK15: ='Revenue 2027'!$F$50 | AL15: ='Revenue 2027'!$G$50 | AM15: ='Revenue 2027'!$H$50 | AN15: ='Revenue 2027'!$I$50 | AO15: ='Revenue 2027'!$J$50 | AP15: ='Revenue 2027'!$K$50 | AQ15: ='Revenue 2027'!$L$50 | AR15: ='Revenue 2027'!$M$50 | AS15: ='Revenue 2027'!$N$50 | AT15: ='Revenue 2027'!$O$50 | AU15: =SUM(AI15:AT15) | AW15: ='Revenue 2028'!D50 | AX15: ='Revenue 2028'!E50 | AY15: ='Revenue 2028'!F50 | AZ15: ='Revenue 2028'!G50 | BA15: ='Revenue 2028'!H50 | BB15: ='Revenue 2028'!I50 | BC15: ='Revenue 2028'!J50 | BD15: ='Revenue 2028'!K50 | ... BH15: ='Revenue 2028'!O50 | BI15: =SUM(AW15:BH15)
B16: Pharma | G16: ='Revenue 2025'!$D$53 | H16: ='Revenue 2025'!$E$53 | I16: ='Revenue 2025'!$F$53 | J16: ='Revenue 2025'!$G$53 | K16: ='Revenue 2025'!$H$53 | L16: ='Revenue 2025'!$I$53 | M16: ='Revenue 2025'!$J$53 | N16: ='Revenue 2025'!$K$53 | O16: ='Revenue 2025'!$L$53 | P16: ='Revenue 2025'!$M$53 | Q16: ='Revenue 2025'!$N$53 | R16: ='Revenue 2025'!$O$53 | S16: =SUM(G16:R16) | U16: ='Revenue 2026'!$D$57 | V16: ='Revenue 2026'!$E$57 | W16: ='Revenue 2026'!$F$57 | X16: ='Revenue 2026'!$G$57 | Y16: ='Revenue 2026'!$H$57 | Z16: ='Revenue 2026'!$I$57 | AA16: ='Revenue 2026'!$J$57 | AB16: ='Revenue 2026'!$K$57 | AC16: ='Revenue 2026'!$L$57 | AD16: ='Revenue 2026'!$M$57 | AE16: ='Revenue 2026'!$N$57 | AF16: ='Revenue 2026'!$O$57 | AG16: =SUM(U16:AF16) | AI16: ='Revenue 2027'!$D$57 | AJ16: ='Revenue 2027'!$E$57 | AK16: ='Revenue 2027'!$F$57 | AL16: ='Revenue 2027'!$G$57 | AM16: ='Revenue 2027'!$H$57 | AN16: ='Revenue 2027'!$I$57 | AO16: ='Revenue 2027'!$J$57 | AP16: ='Revenue 2027'!$K$57 | AQ16: ='Revenue 2027'!$L$57 | AR16: ='Revenue 2027'!$M$57 | AS16: ='Revenue 2027'!$N$57 | AT16: ='Revenue 2027'!$O$57 | AU16: =SUM(AI16:AT16) | AW16: ='Revenue 2028'!D57 | AX16: ='Revenue 2028'!E57 | AY16: ='Revenue 2028'!F57 | AZ16: ='Revenue 2028'!G57 | BA16: ='Revenue 2028'!H57 | BB16: ='Revenue 2028'!I57 | BC16: ='Revenue 2028'!J57 | BD16: ='Revenue 2028'!K57 | ... BH16: ='Revenue 2028'!O57 | BI16: =SUM(AW16:BH16)
B17: Pharma- Reseller | G17: ='Revenue 2025'!$D$59 | H17: ='Revenue 2025'!$E$59 | I17: ='Revenue 2025'!$F59 | J17: ='Revenue 2025'!$G$59 | K17: ='Revenue 2025'!$H$59 | L17: ='Revenue 2025'!$I$59 | M17: ='Revenue 2025'!X59 | N17: ='Revenue 2025'!$K$59 | O17: ='Revenue 2025'!$L$59 | P17: ='Revenue 2025'!$M$59 | Q17: ='Revenue 2025'!$N$59 | R17: ='Revenue 2025'!$O$59 | S17: =SUM(H17:R17) | U17: ='Revenue 2026'!$D$64 | V17: ='Revenue 2026'!$E$64 | W17: ='Revenue 2026'!$F64 | X17: ='Revenue 2026'!$G$64 | Y17: ='Revenue 2026'!$H$64 | Z17: ='Revenue 2026'!$I$64 | AA17: ='Revenue 2026'!AL64 | AB17: ='Revenue 2026'!$K$64 | AC17: ='Revenue 2026'!$L$64 | AD17: ='Revenue 2026'!$M$64 | AE17: ='Revenue 2026'!$N$64 | AF17: ='Revenue 2026'!$O$64 | AG17: =SUM(V17:AF17) | AI17: ='Revenue 2027'!$D$64 | AJ17: ='Revenue 2027'!$E$64 | AK17: ='Revenue 2027'!$F64 | AL17: ='Revenue 2027'!$G$64 | AM17: ='Revenue 2027'!$H$64 | AN17: ='Revenue 2027'!$I$64 | AO17: ='Revenue 2027'!AZ64 | AP17: ='Revenue 2027'!$K$64 | AQ17: ='Revenue 2027'!$L$64 | AR17: ='Revenue 2027'!$M$64 | AS17: ='Revenue 2027'!$N$64 | AT17: ='Revenue 2027'!$O$64 | AU17: =SUM(AJ17:AT17) | AW17: ='Revenue 2028'!D64 | AX17: ='Revenue 2028'!E64 | AY17: ='Revenue 2028'!F64 | AZ17: ='Revenue 2028'!G64 | BA17: ='Revenue 2028'!H64 | BB17: ='Revenue 2028'!I64 | BC17: ='Revenue 2028'!J64 | BD17: ='Revenue 2028'!K64 | ... BH17: ='Revenue 2028'!O64 | BI17: =SUM(AX17:BH17)
B18: Start up - Small Firms | G18: ='Revenue 2025'!$D$66 | H18: ='Revenue 2025'!$E$66 | I18: ='Revenue 2025'!$F$66 | J18: ='Revenue 2025'!$G$66 | K18: ='Revenue 2025'!$H$66 | L18: ='Revenue 2025'!$I$66 | M18: ='Revenue 2025'!$J66 | N18: ='Revenue 2025'!$K$66 | O18: ='Revenue 2025'!$L$66 | P18: ='Revenue 2025'!$M$66 | Q18: ='Revenue 2025'!$N$66 | R18: ='Revenue 2025'!$O$66 | S18: =SUM(G18:R18) | U18: ='Revenue 2026'!$D$71 | V18: ='Revenue 2026'!$E$71 | W18: ='Revenue 2026'!$F$71 | X18: ='Revenue 2026'!$G$71 | Y18: ='Revenue 2026'!$H$71 | Z18: ='Revenue 2026'!$I$71 | AA18: ='Revenue 2026'!$J71 | AB18: ='Revenue 2026'!$K$71 | AC18: ='Revenue 2026'!$L$71 | AD18: ='Revenue 2026'!$M$71 | AE18: ='Revenue 2026'!$N$71 | AF18: ='Revenue 2026'!$O$71 | AG18: =SUM(U18:AF18) | AI18: ='Revenue 2027'!$D$71 | AJ18: ='Revenue 2027'!$E$71 | AK18: ='Revenue 2027'!$F$71 | AL18: ='Revenue 2027'!$G$71 | AM18: ='Revenue 2027'!$H$71 | AN18: ='Revenue 2027'!$I$71 | AO18: ='Revenue 2027'!$J71 | AP18: ='Revenue 2027'!$K$71 | AQ18: ='Revenue 2027'!$L$71 | AR18: ='Revenue 2027'!$M$71 | AS18: ='Revenue 2027'!$N$71 | AT18: ='Revenue 2027'!$O$71 | AU18: =SUM(AI18:AT18) | AW18: ='Revenue 2028'!$D$71 | AX18: ='Revenue 2028'!$D$71 | AY18: ='Revenue 2028'!$D$71 | AZ18: ='Revenue 2028'!$D$71 | BA18: ='Revenue 2028'!$D$71 | BB18: ='Revenue 2028'!$D$71 | BC18: ='Revenue 2028'!$D$71 | BD18: ='Revenue 2028'!$D$71 | ... BH18: ='Revenue 2028'!$D$71 | BI18: =SUM(AW18:BH18)
B19: Start up Reseller | G19: ='Revenue 2025'!$D$72 | H19: ='Revenue 2025'!$E$72 | I19: ='Revenue 2025'!$F$72 | J19: ='Revenue 2025'!$G$72 | K19: ='Revenue 2025'!$H$72 | L19: ='Revenue 2025'!$I$72 | M19: ='Revenue 2025'!$J$72 | N19: ='Revenue 2025'!$K$72 | O19: ='Revenue 2025'!$L$72 | P19: ='Revenue 2025'!$M$72 | Q19: ='Revenue 2025'!$N$72 | R19: ='Revenue 2025'!$O$72 | S19: =SUM(G19:R19) | U19: ='Revenue 2026'!$D$78 | V19: ='Revenue 2026'!$E$78 | W19: ='Revenue 2026'!$F$78 | X19: ='Revenue 2026'!$G$78 | Y19: ='Revenue 2026'!$H$78 | Z19: ='Revenue 2026'!$I$78 | AA19: ='Revenue 2026'!$J$78 | AB19: ='Revenue 2026'!$K$78 | AC19: ='Revenue 2026'!$L$78 | AD19: ='Revenue 2026'!$M$78 | AE19: ='Revenue 2026'!$N$78 | AF19: ='Revenue 2026'!$O$78 | AG19: =SUM(U19:AF19) | AI19: ='Revenue 2027'!$D$78 | AJ19: ='Revenue 2027'!$E$78 | AK19: ='Revenue 2027'!$F$78 | AL19: ='Revenue 2027'!$G$78 | AM19: ='Revenue 2027'!$H$78 | AN19: ='Revenue 2027'!$I$78 | AO19: ='Revenue 2027'!$J$78 | AP19: ='Revenue 2027'!$K$78 | AQ19: ='Revenue 2027'!$L$78 | AR19: ='Revenue 2027'!$M$78 | AS19: ='Revenue 2027'!$N$78 | AT19: ='Revenue 2027'!$O$78 | AU19: =SUM(AI19:AT19) | AW19: ='Revenue 2028'!D78 | AX19: ='Revenue 2028'!E78 | AY19: ='Revenue 2028'!F78 | AZ19: ='Revenue 2028'!G78 | BA19: ='Revenue 2028'!H78 | BB19: ='Revenue 2028'!I78 | BC19: ='Revenue 2028'!J78 | BD19: ='Revenue 2028'!K78 | ... BH19: ='Revenue 2028'!O78 | BI19: =SUM(AW19:BH19)
B20: Training / Consultancy Training as a Service
B21: Thought Library | D21: Added: Initial Setup | G21: ='Revenue 2025'!$D$79 | H21: ='Revenue 2025'!$E$79 | I21: ='Revenue 2025'!$F$79 | J21: ='Revenue 2025'!$G$79 | K21: ='Revenue 2025'!$H$79 | L21: ='Revenue 2025'!$I$79 | M21: ='Revenue 2025'!$J$79 | N21: ='Revenue 2025'!$K$79 | O21: ='Revenue 2025'!$L$79 | P21: ='Revenue 2025'!$M$79 | Q21: ='Revenue 2025'!$N$79 | R21: ='Revenue 2025'!$O$79 | S21: =SUM(G21:R21) | U21: ='Revenue 2026'!$D$85 | V21: ='Revenue 2026'!$E$85 | W21: ='Revenue 2026'!$F$85 | X21: ='Revenue 2026'!$G$85 | Y21: ='Revenue 2026'!$H$85 | Z21: ='Revenue 2026'!$I$85 | AA21: ='Revenue 2026'!$J$85 | AB21: ='Revenue 2026'!$K$85 | AC21: ='Revenue 2026'!$L$85 | AD21: ='Revenue 2026'!$M$85 | AE21: ='Revenue 2026'!$N$85 | AF21: ='Revenue 2026'!$O$85 | AG21: =SUM(U21:AF21) | AI21: ='Revenue 2027'!$D$85 | AJ21: ='Revenue 2027'!$E$85 | AK21: ='Revenue 2027'!$F$85 | AL21: ='Revenue 2027'!$G$85 | AM21: ='Revenue 2027'!$H$85 | AN21: ='Revenue 2027'!$I$85 | AO21: ='Revenue 2027'!$J$85 | AP21: ='Revenue 2027'!$K$85 | AQ21: ='Revenue 2027'!$L$85 | AR21: ='Revenue 2027'!$M$85 | AS21: ='Revenue 2027'!$N$85 | AT21: ='Revenue 2027'!$O$85 | AU21: =SUM(AI21:AT21) | AW21: ='Revenue 2028'!D85 | AX21: ='Revenue 2028'!E85 | AY21: ='Revenue 2028'!F85 | AZ21: ='Revenue 2028'!G85 | BA21: ='Revenue 2028'!H85 | BB21: ='Revenue 2028'!I85 | BC21: ='Revenue 2028'!J85 | BD21: ='Revenue 2028'!K85 | ... BH21: ='Revenue 2028'!O85 | BI21: =SUM(AW21:BH21)
B22: Consultancy Services | G22: ='Revenue 2025'!$D$85 | H22: ='Revenue 2025'!$E$85 | I22: ='Revenue 2025'!$F$85 | J22: ='Revenue 2025'!$G$85 | K22: ='Revenue 2025'!$H$85 | L22: ='Revenue 2025'!$I$85 | M22: ='Revenue 2025'!$J$85 | N22: ='Revenue 2025'!$K$85 | O22: ='Revenue 2025'!$L$85 | P22: ='Revenue 2025'!$M$85 | Q22: ='Revenue 2025'!$N$85 | R22: ='Revenue 2025'!$O$85 | S22: =SUM(G22:R22) | U22: ='Revenue 2026'!$D$91 | V22: ='Revenue 2026'!$E$91 | W22: ='Revenue 2026'!$F$91 | X22: ='Revenue 2026'!$G$91 | Y22: ='Revenue 2026'!$H$91 | Z22: ='Revenue 2026'!$I$91 | AA22: ='Revenue 2026'!$J$91 | AB22: ='Revenue 2026'!$K$91 | AC22: ='Revenue 2026'!$L$91 | AD22: ='Revenue 2026'!$M$91 | AE22: ='Revenue 2026'!$N$91 | AF22: ='Revenue 2026'!$O$91 | AG22: =SUM(U22:AF22) | AI22: ='Revenue 2027'!$D$91 | AJ22: ='Revenue 2027'!$E$91 | AK22: ='Revenue 2027'!$F$91 | AL22: ='Revenue 2027'!$G$91 | AM22: ='Revenue 2027'!$H$91 | AN22: ='Revenue 2027'!$I$91 | AO22: ='Revenue 2027'!$J$91 | AP22: ='Revenue 2027'!$K$91 | AQ22: ='Revenue 2027'!$L$91 | AR22: ='Revenue 2027'!$M$91 | AS22: ='Revenue 2027'!$N$91 | AT22: ='Revenue 2027'!$O$91 | AU22: =SUM(AI22:AT22) | AW22: ='Revenue 2028'!D91 | AX22: ='Revenue 2028'!E91 | AY22: ='Revenue 2028'!F91 | AZ22: ='Revenue 2028'!G91 | BA22: ='Revenue 2028'!H91 | BB22: ='Revenue 2028'!I91 | BC22: ='Revenue 2028'!J91 | BD22: ='Revenue 2028'!K91 | ... BH22: ='Revenue 2028'!O91 | BI22: =SUM(AW22:BH22)
S23: =SUM(G23:R23) | AG23: =SUM(U23:AF23) | AU23: =SUM(AI23:AT23) | BI23: =SUM(AW23:BH23)
B24: Total Revenue | C24: TotalRev | G24: =SUM(G5:G23) | H24: =SUM(H5:H23) | I24: =SUM(I5:I23) | J24: =SUM(J5:J23) | K24: =SUM(K5:K23) | L24: =SUM(L5:L23) | M24: =SUM(M5:M23) | N24: =SUM(N5:N23) | ... R24: =SUM(R5:R23) | S24: =SUM(G24:R24) | U24: =SUM(U5:U23) | V24: =SUM(V5:V23) | W24: =SUM(W5:W23) | X24: =SUM(X5:X23) | Y24: =SUM(Y5:Y23) | Z24: =SUM(Z5:Z23) | AA24: =SUM(AA5:AA23) | AB24: =SUM(AB5:AB23) | ... AF24: =SUM(AF5:AF23) | AG24: =SUM(U24:AF24) | AI24: =SUM(AI5:AI23) | AJ24: =SUM(AJ5:AJ23) | AK24: =SUM(AK5:AK23) | AL24: =SUM(AL5:AL23) | AM24: =SUM(AM5:AM23) | AN24: =SUM(AN5:AN23) | AO24: =SUM(AO5:AO23) | AP24: =SUM(AP5:AP23) | ... AT24: =SUM(AT5:AT23) | AU24: =SUM(AI24:AT24) | AW24: =SUM(AW5:AW23) | AX24: =SUM(AX5:AX23) | AY24: =SUM(AY5:AY23) | AZ24: =SUM(AZ5:AZ23) | BA24: =SUM(BA5:BA23) | BB24: =SUM(BB5:BB23) | BC24: =SUM(BC5:BC23) | BD24: =SUM(BD5:BD23) | ... BH24: =SUM(BH5:BH23) | BI24: =SUM(AW24:BH24)
S25: =SUM(G25:R25) | AG25: =SUM(U25:AF25) | AU25: =SUM(AI25:AT25) | BI25: =SUM(AW25:BH25)
B26: Cost of Sales: | S26: =SUM(G26:R26) | AG26: =SUM(U26:AF26) | AU26: =SUM(AI26:AT26) | BI26: =SUM(AW26:BH26)
B27: Administrative
B28: Configuration | G28: ='Revenue 2025'!$D$98 | H28: ='Revenue 2025'!$E$98 | I28: ='Revenue 2025'!$F$98 | J28: ='Revenue 2025'!$G$98 | K28: ='Revenue 2025'!$H$98 | L28: ='Revenue 2025'!$I$98 | M28: ='Revenue 2025'!$J$98 | N28: ='Revenue 2025'!$K$98 | O28: ='Revenue 2025'!$L$98 | P28: ='Revenue 2025'!$M$98 | Q28: ='Revenue 2025'!$N$98 | R28: ='Revenue 2025'!$O$98 | S28: =SUM(G28:R28) | U28: ='Revenue 2026'!$D$104 | V28: ='Revenue 2026'!$E$104 | W28: ='Revenue 2026'!$F$104 | X28: ='Revenue 2026'!$G$104 | Y28: ='Revenue 2026'!$H$104 | Z28: ='Revenue 2026'!$I$104 | AA28: ='Revenue 2026'!$J$104 | AB28: ='Revenue 2026'!$K$104 | AC28: ='Revenue 2026'!$L$104 | AD28: ='Revenue 2026'!$M$104 | AE28: ='Revenue 2026'!$N$104 | AF28: ='Revenue 2026'!$O$104 | AG28: =SUM(U28:AF28) | AI28: ='Revenue 2027'!$D$104 | AJ28: ='Revenue 2027'!$E$104 | AK28: ='Revenue 2027'!$F$104 | AL28: ='Revenue 2027'!$G$104 | AM28: ='Revenue 2027'!$H$104 | AN28: ='Revenue 2027'!$I$104 | AO28: ='Revenue 2027'!$J$104 | AP28: ='Revenue 2027'!$K$104 | AQ28: ='Revenue 2027'!$L$104 | AR28: ='Revenue 2027'!$M$104 | AS28: ='Revenue 2027'!$N$104 | AT28: ='Revenue 2027'!$O$104 | AU28: =SUM(AI28:AT28) | AW28: ='Revenue 2028'!D103 | AX28: ='Revenue 2028'!E103 | AY28: ='Revenue 2028'!F103 | AZ28: ='Revenue 2028'!G103 | BA28: ='Revenue 2028'!H103 | BB28: ='Revenue 2028'!I103 | BC28: ='Revenue 2028'!J103 | BD28: ='Revenue 2028'!K103 | ... BH28: ='Revenue 2028'!O103 | BI28: =SUM(AW28:BH28)
B29: On-Boarding- Administrator | G29: ='Revenue 2025'!$D$104 | H29: ='Revenue 2025'!$E$104 | I29: ='Revenue 2025'!$F$104 | J29: ='Revenue 2025'!$G$104 | K29: ='Revenue 2025'!$H$104 | L29: ='Revenue 2025'!$I$104 | M29: ='Revenue 2025'!$J$104 | N29: ='Revenue 2025'!$K$104 | O29: ='Revenue 2025'!$L$104 | P29: ='Revenue 2025'!AA103 | Q29: ='Revenue 2025'!$N$104 | R29: ='Revenue 2025'!$O$104 | S29: =SUM(G29:R29) | U29: ='Revenue 2026'!$D$110 | V29: ='Revenue 2026'!$E$110 | W29: ='Revenue 2026'!$F$110 | X29: ='Revenue 2026'!$G$110 | Y29: ='Revenue 2026'!$H$110 | Z29: ='Revenue 2026'!$I$110 | AA29: ='Revenue 2026'!$J$110 | AB29: ='Revenue 2026'!$K$110 | AC29: ='Revenue 2026'!$L$110 | AD29: ='Revenue 2026'!AO109 | AE29: ='Revenue 2026'!$N$110 | AF29: ='Revenue 2026'!$O$110 | AG29: =SUM(U29:AF29) | AI29: ='Revenue 2027'!$D$110 | AJ29: ='Revenue 2027'!$E$110 | AK29: ='Revenue 2027'!$F$110 | AL29: ='Revenue 2027'!$G$110 | AM29: ='Revenue 2027'!$H$110 | AN29: ='Revenue 2027'!$I$110 | AO29: ='Revenue 2027'!$J$110 | AP29: ='Revenue 2027'!$K$110 | AQ29: ='Revenue 2027'!$L$110 | AR29: ='Revenue 2027'!BC109 | AS29: ='Revenue 2027'!$N$110 | AT29: ='Revenue 2027'!$O$110 | AU29: =SUM(AI29:AT29) | AW29: ='Revenue 2028'!D109 | AX29: ='Revenue 2028'!E109 | AY29: ='Revenue 2028'!F109 | AZ29: ='Revenue 2028'!G109 | BA29: ='Revenue 2028'!H109 | BB29: ='Revenue 2028'!I109 | BC29: ='Revenue 2028'!J109 | BD29: ='Revenue 2028'!K109 | ... BH29: ='Revenue 2028'!O109 | BI29: =SUM(AW29:BH29)
B30: On-Boarding Users | G30: ='Revenue 2025'!$D$110 | H30: ='Revenue 2025'!$E$110 | I30: ='Revenue 2025'!$F$110 | J30: ='Revenue 2025'!$G$110 | K30: ='Revenue 2025'!$H$110 | L30: ='Revenue 2025'!$I$110 | M30: ='Revenue 2025'!$J$110 | N30: ='Revenue 2025'!$K$110 | O30: ='Revenue 2025'!$L$110 | P30: ='Revenue 2025'!$M$110 | Q30: ='Revenue 2025'!$N$110 | R30: ='Revenue 2025'!$O$110 | S30: =SUM(G30:R30) | U30: ='Revenue 2026'!$D$116 | V30: ='Revenue 2026'!$E$116 | W30: ='Revenue 2026'!$F$116 | X30: ='Revenue 2026'!$G$116 | Y30: ='Revenue 2026'!$H$116 | Z30: ='Revenue 2026'!$I$116 | AA30: ='Revenue 2026'!$J$116 | AB30: ='Revenue 2026'!$K$116 | AC30: ='Revenue 2026'!$L$116 | AD30: ='Revenue 2026'!$M$116 | AE30: ='Revenue 2026'!$N$116 | AF30: ='Revenue 2026'!$O$116 | AG30: =SUM(U30:AF30) | AI30: ='Revenue 2027'!$D$116 | AJ30: ='Revenue 2027'!$E$116 | AK30: ='Revenue 2027'!$F$116 | AL30: ='Revenue 2027'!$G$116 | AM30: ='Revenue 2027'!$H$116 | AN30: ='Revenue 2027'!$I$116 | AO30: ='Revenue 2027'!$J$116 | AP30: ='Revenue 2027'!$K$116 | AQ30: ='Revenue 2027'!$L$116 | AR30: ='Revenue 2027'!$M$116 | AS30: ='Revenue 2027'!$N$116 | AT30: ='Revenue 2027'!$O$116 | AU30: =SUM(AI30:AT30) | AW30: ='Revenue 2028'!D115 | AX30: ='Revenue 2028'!E115 | AY30: ='Revenue 2028'!F115 | AZ30: ='Revenue 2028'!G115 | BA30: ='Revenue 2028'!H115 | BB30: ='Revenue 2028'!I115 | BC30: ='Revenue 2028'!J115 | BD30: ='Revenue 2028'!K115 | ... BH30: ='Revenue 2028'!O115 | BI30: =SUM(AW30:BH30)
B31: Import | G31: ='Revenue 2025'!$D$116 | H31: ='Revenue 2025'!$E$116 | I31: ='Revenue 2025'!$F$116 | J31: ='Revenue 2025'!$G$116 | K31: ='Revenue 2025'!$H$116 | L31: ='Revenue 2025'!$I$116 | M31: ='Revenue 2025'!$J$116 | N31: ='Revenue 2025'!$K$116 | O31: ='Revenue 2025'!$L$116 | P31: ='Revenue 2025'!$M$116 | Q31: ='Revenue 2025'!$N$116 | R31: ='Revenue 2025'!$O$116 | U31: ='Revenue 2026'!$D$122 | V31: ='Revenue 2026'!$E$122 | W31: ='Revenue 2026'!$F$122 | X31: ='Revenue 2026'!$G$122 | Y31: ='Revenue 2026'!$H$122 | Z31: ='Revenue 2026'!$I$122 | AA31: ='Revenue 2026'!$J$122 | AB31: ='Revenue 2026'!$K$122 | AC31: ='Revenue 2026'!$L$122 | AD31: ='Revenue 2026'!$M$122 | AE31: ='Revenue 2026'!$N$122 | AF31: ='Revenue 2026'!$O$122 | AI31: ='Revenue 2027'!$D$122 | AJ31: ='Revenue 2027'!$E$122 | AK31: ='Revenue 2027'!$F$122 | AL31: ='Revenue 2027'!$G$122 | AM31: ='Revenue 2027'!$H$122 | AN31: ='Revenue 2027'!$I$122 | AO31: ='Revenue 2027'!$J$122 | AP31: ='Revenue 2027'!$K$122 | AQ31: ='Revenue 2027'!$L$122 | AR31: ='Revenue 2027'!$M$122 | AS31: ='Revenue 2027'!$N$122 | AT31: ='Revenue 2027'!$O$122 | AW31: ='Revenue 2028'!D121 | AX31: ='Revenue 2028'!E121 | AY31: ='Revenue 2028'!F121 | AZ31: ='Revenue 2028'!G121 | BA31: ='Revenue 2028'!H121 | BB31: ='Revenue 2028'!I121 | BC31: ='Revenue 2028'!J121 | BD31: ='Revenue 2028'!K121 | ... BH31: ='Revenue 2028'!O121 | BI31: =SUM(AW31:BH31)
B32: Support | G32: ='Revenue 2025'!$D$159 | H32: ='Revenue 2025'!$D$159 | I32: ='Revenue 2025'!$D$159 | J32: ='Revenue 2025'!$D$159 | K32: ='Revenue 2025'!$D$159 | L32: ='Revenue 2025'!$D$159 | M32: ='Revenue 2025'!$D$159 | N32: ='Revenue 2025'!$D$159 | ... R32: ='Revenue 2025'!$D$159 | S32: =SUM(G32:R32) | U32: ='Revenue 2026'!$D$165 | V32: ='Revenue 2026'!$D$165 | W32: ='Revenue 2026'!$D$165 | X32: ='Revenue 2026'!$D$165 | Y32: ='Revenue 2026'!$D$165 | Z32: ='Revenue 2026'!$D$165 | AA32: ='Revenue 2026'!$D$165 | AB32: ='Revenue 2026'!$D$165 | ... AF32: ='Revenue 2026'!$D$165 | AG32: =SUM(U32:AF32) | AI32: ='Revenue 2027'!$D$165 | AJ32: ='Revenue 2027'!$D$165 | AK32: ='Revenue 2027'!$D$165 | AL32: ='Revenue 2027'!$D$165 | AM32: ='Revenue 2027'!$D$165 | AN32: ='Revenue 2027'!$D$165 | AO32: ='Revenue 2027'!$D$165 | AP32: ='Revenue 2027'!$D$165 | ... AT32: ='Revenue 2027'!$D$165 | AU32: =SUM(AI32:AT32) | AW32: ='Revenue 2028'!D164 | AX32: ='Revenue 2028'!E164 | AY32: ='Revenue 2028'!F164 | AZ32: ='Revenue 2028'!G164 | BA32: ='Revenue 2028'!H164 | BB32: ='Revenue 2028'!I164 | BC32: ='Revenue 2028'!J164 | BD32: ='Revenue 2028'!K164 | ... BH32: ='Revenue 2028'!O164 | BI32: =SUM(AW32:BH32)
B33: Industry Break Down
B34: Hospitality | G34: ='Revenue 2025'!$D$30 | H34: ='Revenue 2025'!$E$30 | I34: ='Revenue 2025'!$F$30 | J34: ='Revenue 2025'!$G$30 | K34: ='Revenue 2025'!$H$30 | L34: ='Revenue 2025'!$I29 | M34: ='Revenue 2025'!$J$30 | N34: ='Revenue 2025'!$K$30 | O34: ='Revenue 2025'!$L$30 | P34: ='Revenue 2025'!$M$30 | Q34: ='Revenue 2025'!$N$30 | R34: ='Revenue 2025'!$O$30 | S34: =SUM(G34:R34) | U34: ='Revenue 2026'!$D$30 | V34: ='Revenue 2026'!$E$30 | W34: ='Revenue 2026'!$F$30 | X34: ='Revenue 2026'!$G$30 | Y34: ='Revenue 2026'!$H$30 | Z34: ='Revenue 2026'!$I29 | AA34: ='Revenue 2026'!$J$30 | AB34: ='Revenue 2026'!$K$30 | AC34: ='Revenue 2026'!$L$30 | AD34: ='Revenue 2026'!$M$30 | AE34: ='Revenue 2026'!$N$30 | AF34: ='Revenue 2026'!$O$30 | AG34: =SUM(U34:AF34) | AI34: ='Revenue 2027'!$D$30 | AJ34: ='Revenue 2027'!$E$30 | AK34: ='Revenue 2027'!$F$30 | AL34: ='Revenue 2027'!$G$30 | AM34: ='Revenue 2027'!$H$30 | AN34: ='Revenue 2027'!$I29 | AO34: ='Revenue 2027'!$J$30 | AP34: ='Revenue 2027'!$K$30 | AQ34: ='Revenue 2027'!$L$30 | AR34: ='Revenue 2027'!$M$30 | AS34: ='Revenue 2027'!$N$30 | AT34: ='Revenue 2027'!$O$30 | AU34: =SUM(AI34:AT34) | AW34: ='Revenue 2028'!D30 | AX34: ='Revenue 2028'!E30 | AY34: ='Revenue 2028'!F30 | AZ34: ='Revenue 2028'!G30 | BA34: ='Revenue 2028'!H30 | BB34: ='Revenue 2028'!I30 | BC34: ='Revenue 2028'!J30 | BD34: ='Revenue 2028'!K30 | ... BH34: ='Revenue 2028'!O30 | BI34: =SUM(AW34:BH34)
B35: Hospitality- Reseller | G35: ='Revenue 2025'!$D$36 | H35: ='Revenue 2025'!$E$36 | I35: ='Revenue 2025'!$F$36 | J35: ='Revenue 2025'!$G$36 | K35: ='Revenue 2025'!$H$36 | L35: ='Revenue 2025'!$I$36 | M35: ='Revenue 2025'!$J$36 | N35: ='Revenue 2025'!$K$36 | O35: ='Revenue 2025'!$L$36 | P35: ='Revenue 2025'!$M$36 | Q35: ='Revenue 2025'!$N$36 | R35: ='Revenue 2025'!$O$36 | S35: =SUM(G35:R35) | U35: ='Revenue 2026'!$D$37 | V35: ='Revenue 2026'!$E$37 | W35: ='Revenue 2026'!$F$37 | X35: ='Revenue 2026'!$G$37 | Y35: ='Revenue 2026'!$H$37 | Z35: ='Revenue 2026'!$I$37 | AA35: ='Revenue 2026'!$J$37 | AB35: ='Revenue 2026'!$K$37 | AC35: ='Revenue 2026'!$L$37 | AD35: ='Revenue 2026'!$M$37 | AE35: ='Revenue 2026'!$N$37 | AF35: ='Revenue 2026'!$O$37 | AG35: =SUM(U35:AF35) | AI35: ='Revenue 2027'!$D$37 | AJ35: ='Revenue 2027'!$E$37 | AK35: ='Revenue 2027'!$F$37 | AL35: ='Revenue 2027'!$G$37 | AM35: ='Revenue 2027'!$H$37 | AN35: ='Revenue 2027'!$I$37 | AO35: ='Revenue 2027'!$J$37 | AP35: ='Revenue 2027'!$K$37 | AQ35: ='Revenue 2027'!$L$37 | AR35: ='Revenue 2027'!$M$37 | AS35: ='Revenue 2027'!$N$37 | AT35: ='Revenue 2027'!$O$37 | AU35: =SUM(AI35:AT35) | AW35: ='Revenue 2028'!D37 | AX35: ='Revenue 2028'!E37 | AY35: ='Revenue 2028'!F37 | AZ35: ='Revenue 2028'!G37 | BA35: ='Revenue 2028'!H37 | BB35: ='Revenue 2028'!I37 | BC35: ='Revenue 2028'!J37 | BD35: ='Revenue 2028'!K37 | ... BH35: ='Revenue 2028'!O37 | BI35: =SUM(AW35:BH35)
B36: Real Estate Development | G36: ='Revenue 2025'!$D$42 | H36: ='Revenue 2025'!$E$42 | I36: ='Revenue 2025'!$F$42 | J36: ='Revenue 2025'!$G$42 | K36: ='Revenue 2025'!$H$42 | L36: ='Revenue 2025'!$I$42 | M36: ='Revenue 2025'!$J$42 | N36: ='Revenue 2025'!$K$42 | O36: ='Revenue 2025'!$L$42 | P36: ='Revenue 2025'!$M$42 | Q36: ='Revenue 2025'!$N$42 | R36: ='Revenue 2025'!$O$42 | S36: =SUM(G36:R36) | U36: ='Revenue 2026'!$D$44 | V36: ='Revenue 2026'!$E$44 | W36: ='Revenue 2026'!$F$44 | X36: ='Revenue 2026'!$G$44 | Y36: ='Revenue 2026'!$H$44 | Z36: ='Revenue 2026'!$I$44 | AA36: ='Revenue 2026'!$J$44 | AB36: ='Revenue 2026'!$K$44 | AC36: ='Revenue 2026'!$L$44 | AD36: ='Revenue 2026'!$M$44 | AE36: ='Revenue 2026'!$N$44 | AF36: ='Revenue 2026'!$O$44 | AG36: =SUM(U36:AF36) | AI36: ='Revenue 2027'!$D$44 | AJ36: ='Revenue 2027'!$E$44 | AK36: ='Revenue 2027'!$F$44 | AL36: ='Revenue 2027'!$G$44 | AM36: ='Revenue 2027'!$H$44 | AN36: ='Revenue 2027'!$I$44 | AO36: ='Revenue 2027'!$J$44 | AP36: ='Revenue 2027'!$K$44 | AQ36: ='Revenue 2027'!$L$44 | AR36: ='Revenue 2027'!$M$44 | AS36: ='Revenue 2027'!$N$44 | AT36: ='Revenue 2027'!$O$44 | AU36: =SUM(AI36:AT36) | AW36: ='Revenue 2028'!D44 | AX36: ='Revenue 2028'!E44 | AY36: ='Revenue 2028'!F44 | AZ36: ='Revenue 2028'!G44 | BA36: ='Revenue 2028'!H44 | BB36: ='Revenue 2028'!I44 | BC36: ='Revenue 2028'!J44 | BD36: ='Revenue 2028'!K44 | ... BH36: ='Revenue 2028'!O44 | BI36: =SUM(AW36:BH36)
B37: Real Estate Development- Reseller | G37: ='Revenue 2025'!$D$48 | H37: ='Revenue 2025'!$E$48 | I37: ='Revenue 2025'!$F$48 | J37: ='Revenue 2025'!$G$48 | K37: ='Revenue 2025'!$H$48 | L37: ='Revenue 2025'!$I$48 | M37: ='Revenue 2025'!$J$48 | N37: ='Revenue 2025'!$K$48 | O37: ='Revenue 2025'!$L$48 | P37: ='Revenue 2025'!$M$48 | Q37: ='Revenue 2025'!$N$48 | R37: ='Revenue 2025'!$O$48 | S37: =SUM(G37:R37) | U37: ='Revenue 2026'!$D$51 | V37: ='Revenue 2026'!$E$51 | W37: ='Revenue 2026'!$F$51 | X37: ='Revenue 2026'!$G$51 | Y37: ='Revenue 2026'!$H$51 | Z37: ='Revenue 2026'!$I$51 | AA37: ='Revenue 2026'!$J$51 | AB37: ='Revenue 2026'!$K$51 | AC37: ='Revenue 2026'!$L$51 | AD37: ='Revenue 2026'!$M$51 | AE37: ='Revenue 2026'!$N$51 | AF37: ='Revenue 2026'!$O$51 | AG37: =SUM(U37:AF37) | AI37: ='Revenue 2027'!$D$51 | AJ37: ='Revenue 2027'!$E$51 | AK37: ='Revenue 2027'!$F$51 | AL37: ='Revenue 2027'!$G$51 | AM37: ='Revenue 2027'!$H$51 | AN37: ='Revenue 2027'!$I$51 | AO37: ='Revenue 2027'!$J$51 | AP37: ='Revenue 2027'!$K$51 | AQ37: ='Revenue 2027'!$L$51 | AR37: ='Revenue 2027'!$M$51 | AS37: ='Revenue 2027'!$N$51 | AT37: ='Revenue 2027'!$O$51 | AU37: =SUM(AI37:AT37) | AW37: ='Revenue 2028'!D51 | AX37: ='Revenue 2028'!E51 | AY37: ='Revenue 2028'!F51 | AZ37: ='Revenue 2028'!G51 | BA37: ='Revenue 2028'!H51 | BB37: ='Revenue 2028'!I51 | BC37: ='Revenue 2028'!J51 | BD37: ='Revenue 2028'!K51 | ... BH37: ='Revenue 2028'!O51 | BI37: =SUM(AW37:BH37)
B38: Pharma | G38: ='Revenue 2025'!$D$54 | H38: ='Revenue 2025'!$E$54 | I38: ='Revenue 2025'!$F$54 | J38: ='Revenue 2025'!$G$54 | K38: ='Revenue 2025'!$H$54 | L38: ='Revenue 2025'!$I$54 | M38: ='Revenue 2025'!$J$54 | N38: ='Revenue 2025'!$K$54 | O38: ='Revenue 2025'!$L$54 | P38: ='Revenue 2025'!$M$54 | Q38: ='Revenue 2025'!$N$54 | R38: ='Revenue 2025'!$O$54 | S38: =SUM(G38:R38) | U38: ='Revenue 2026'!$D$58 | V38: ='Revenue 2026'!$E$58 | W38: ='Revenue 2026'!$F$58 | X38: ='Revenue 2026'!$G$58 | Y38: ='Revenue 2026'!$H$58 | Z38: ='Revenue 2026'!$I$58 | AA38: ='Revenue 2026'!$J$58 | AB38: ='Revenue 2026'!$K$58 | AC38: ='Revenue 2026'!$L$58 | AD38: ='Revenue 2026'!$M$58 | AE38: ='Revenue 2026'!$N$58 | AF38: ='Revenue 2026'!$O$58 | AG38: =SUM(U38:AF38) | AI38: ='Revenue 2027'!$D$58 | AJ38: ='Revenue 2027'!$E$58 | AK38: ='Revenue 2027'!$F$58 | AL38: ='Revenue 2027'!$G$58 | AM38: ='Revenue 2027'!$H$58 | AN38: ='Revenue 2027'!$I$58 | AO38: ='Revenue 2027'!$J$58 | AP38: ='Revenue 2027'!$K$58 | AQ38: ='Revenue 2027'!$L$58 | AR38: ='Revenue 2027'!$M$58 | AS38: ='Revenue 2027'!$N$58 | AT38: ='Revenue 2027'!$O$58 | AU38: =SUM(AI38:AT38) | AW38: ='Revenue 2028'!D58 | AX38: ='Revenue 2028'!E58 | AY38: ='Revenue 2028'!F58 | AZ38: ='Revenue 2028'!G58 | BA38: ='Revenue 2028'!H58 | BB38: ='Revenue 2028'!I58 | BC38: ='Revenue 2028'!J58 | BD38: ='Revenue 2028'!K58 | ... BH38: ='Revenue 2028'!O58 | BI38: =SUM(AW38:BH38)
